Workbook

Sheet 引用数据库
A1: 面板可见 | B1: 实际参与游戏内功能或数值计算，当数值存在(非空)时，在对应道具的面板可见 | I1: Item大类 | N1: 武器类型 | P1: ="种类" & COUNTIF(Q2:Q100,">0") | Q1: ="数量" & SUM(Q2:Q100) | R1: ="技能" & SUM(R2:R100) | S1: 伤害/子弹类型 | V1: =SUM(V2:V15) | W1: 品质 | Y1: 类目 | Z1: 阵营 | AD1: 装备 | AE1: 系列 | AF1: 装备系列 | AG1: Name | AH1: 来自阵营 | AI1: 描述 | AJ1: Count | AL1: 义体类型 | AO1: =SUM(AO3:AO11) | AQ1: 效果TAG | AR1: =SUM(AR2:AR100) | AS1: 描述
A2: 特殊显示 | B2: 只显示在特定（比如游戏内wiki）页面的信息 | I2: WPN | J2: Weapon | K2: 武器 | N2: 手枪 | O2: Pistol | P2: 01 | Q2: =COUNTIF('武器'!H:H,N2)/6 | R2: =COUNTIF('武器技能'!E:E,N2) | S2: 动能 | T2: Kinetic | U2: 01 | V2: =COUNTIF('武器'!I:I,S2) | W2: 01 | Y2: CYB | Z2: 纪念碑 | AA2: Monument | AB2: MM | AC2: 01 | AD2: =COUNTIF('义体&义体技能'!E:E,Z2) | AE2: =COUNTIF(AH:AH,Z2) | AF2: 奥德赛 | AG2: Odyssey | AH2: 纪念碑 | AI2: 用于归纳所有“致敬”类的义体和芯片。 | AJ2: =IF(COUNTIF('义体&义体技能'!Z:Z,AF2)=0,"",COUNTIF('义体&义体技能'!Z:Z,AF2)) | AL2: 行为芯片 | AM2: Chip | AN2: 99 | AO2: =COUNTIF('义体&义体技能'!F:F,AL2) | AQ2: 增伤 | AR2: =COUNTIF('义体&义体技能'!AE:AE,AQ2) | AS2: 增加造成的伤害 | AU2: 智脑 | AV2: ExoBrain | AW2: 00 | AX2: =COUNTIF('武器'!H:H,AU2)/6 | AY2: =COUNTIF('武器技能'!E:E,AU2)
A3: 面板隐藏 | B3: 实际参与游戏内功能或数值计算，在对应道具的面板不可见 | I3: EOB | J3: ExoBrain | K3: 智脑 | N3: 步枪 | O3: Rifle | P3: 02 | Q3: =COUNTIF('武器'!H:H,N3)/6 | R3: =COUNTIF('武器技能'!E:E,N3) | S3: 电磁 | T3: Electrical | U3: 02 | V3: =COUNTIF('武器'!I:I,S3) | W3: 02 | Z3: 野望 | AA3: Wild Watch | AB3: WW | AC3: 02 | AD3: =COUNTIF('义体&义体技能'!E:E,Z3) | AE3: =COUNTIF(AH:AH,Z3) | AF3: 公域 | AG3: Public Domain | AH3: 纪念碑 | AI3: 不提供特殊机制，但按百分比提升所有基础属性（血、攻、防、速）。装备的“公域”系列越多，加成越高。简单的数值美学。 | AJ3: =IF(COUNTIF('义体&义体技能'!Z:Z,AF3)=0,"",COUNTIF('义体&义体技能'!Z:Z,AF3)) | AL3: 主手 | AM3: MainHand | AN3: 01 | AO3: =COUNTIF('义体&义体技能'!F:F,AL3) | AQ3: 减伤 | AR3: =COUNTIF('义体&义体技能'!AE:AE,AQ3) | AS3: 伤害减免、生存强化
A4: 仅用于计算 | B4: 不参与实际游戏内功能或数值计算，仅用于在配表时计算数据平衡 | I4: CYB | J4: Cyborg | K4: 义体 | N4: 冲锋枪 | O4: Submachine Gun | P4: 03 | Q4: =COUNTIF('武器'!H:H,N4)/6 | R4: =COUNTIF('武器技能'!E:E,N4) | S4: 热能 | T4: Thermal | U4: 03 | V4: =COUNTIF('武器'!I:I,S4) | W4: 03 | Z4: 劳旅 | AA4: L.Labor | AB4: LL | AC4: 03 | AD4: =COUNTIF('义体&义体技能'!E:E,Z4) | AE4: =COUNTIF(AH:AH,Z4) | AF4: 档案馆 | AG4: Archive | AH4: 纪念碑 | AI4: 在一个关卡内，击杀敌人越多，临时属性提升越高（关卡结束重置）。或者提供额外的经验值/熟练度获取。 | AJ4: =IF(COUNTIF('义体&义体技能'!Z:Z,AF4)=0,"",COUNTIF('义体&义体技能'!Z:Z,AF4)) | AL4: 副手 | AM4: OffHand | AN4: 02 | AO4: =COUNTIF('义体&义体技能'!F:F,AL4) | AQ4: 会心 | AR4: =COUNTIF('义体&义体技能'!AE:AE,AQ4) | AS4: 暴击率、暴击伤害
A5: 游戏内不涉及 | B5: 仅涉及项目管理、设计等信息 | I5: CHP | J5: BehaviorChip | K5: 行为芯片 | N5: 霰弹枪 | O5: Shotgun | P5: 04 | Q5: =COUNTIF('武器'!H:H,N5)/6 | R5: =COUNTIF('武器技能'!E:E,N5) | S5: 纳米 | T5: Nano | U5: 04 | V5: =COUNTIF('武器'!I:I,S5) | W5: 04 | Z5: 新浦会 | AA5: Syn Pu | AB5: SP | AC5: 04 | AD5: =COUNTIF('义体&义体技能'!E:E,Z5) | AE5: =COUNTIF(AH:AH,Z5) | AF5: 图灵 | AG5: Turing | AH5: 纪念碑 | AI5: 成功“完美闪避”敌人的攻击后，该敌人进入“被看破”状态，受到的下一次伤害翻倍。适合高手“防反流”。 | AJ5: =IF(COUNTIF('义体&义体技能'!Z:Z,AF5)=0,"",COUNTIF('义体&义体技能'!Z:Z,AF5)) | AL5: 腿部 | AM5: Leg | AN5: 03 | AO5: =COUNTIF('义体&义体技能'!F:F,AL5) | AQ5: DOT | AR5: =COUNTIF('义体&义体技能'!AE:AE,AQ5) | AS5: 持续伤害
I6: SDA/SDP | J6: Spell | K6: 技能 | N6: 狙击枪 | O6: Sniper Rifle | P6: 05 | Q6: =COUNTIF('武器'!H:H,N6)/6 | R6: =COUNTIF('武器技能'!E:E,N6) | T6: Radioactive | U6: 05 | V6: =COUNTIF('武器'!I:I,S6) | W6: 05 | Z6: 洛克海德 | AA6: Lock Header | AB6: LH | AC6: 05 | AD6: =COUNTIF('义体&义体技能'!E:E,Z6) | AE6: =COUNTIF(AH:AH,Z6) | AF6: 泰坦 | AG6: Titan | AH6: 纪念碑 | AI6: 缩窄攻击范围，强化所有的直线型攻击（如刺击、激光），增加其射程和判定宽度。 | AJ6: =IF(COUNTIF('义体&义体技能'!Z:Z,AF6)=0,"",COUNTIF('义体&义体技能'!Z:Z,AF6)) | AL6: 皮肤 | AM6: Skin | AN6: 04 | AO6: =COUNTIF('义体&义体技能'!F:F,AL6) | AQ6: 扩散 | AR6: =COUNTIF('义体&义体技能'!AE:AE,AQ6) | AS6: 范围传递、连锁爆炸
A7: 技能序号介绍 | B7: SKL01010001 | C7: SKL (技能) | D7: 01 (主/被动) | E7: 01 (武器种类/义体部位/智脑释放) | F7: 01 (技能用途) | G7: 00 (名称哈希) | I7: AMM | J7: Ammo | K7: 弹药 | N7: 喷射器 | O7: Thrower | P7: 06 | Q7: =COUNTIF('武器'!H:H,N7)/6 | R7: =COUNTIF('武器技能'!E:E,N7) | T7: Neural | U7: 06 | V7: =COUNTIF('武器'!I:I,S7) | Z7: 寰宇 | AA7: Omniverse | AB7: OV | AC7: 06 | AD7: =COUNTIF('义体&义体技能'!E:E,Z7) | AE7: =COUNTIF(AH:AH,Z7) | AF7: 街头小子 | AG7: Street Kid | AH7: 野望 | AI7: 持有的金钱（或代币）越多，伤害越高。或者击杀敌人掉落更多金钱。适合“贪婪流”运营。 | AJ7: =IF(COUNTIF('义体&义体技能'!Z:Z,AF7)=0,"",COUNTIF('义体&义体技能'!Z:Z,AF7)) | AL7: 骨骼 | AM7: Bones | AN7: 05 | AO7: =COUNTIF('义体&义体技能'!F:F,AL7) | AQ7: 减益 | AR7: =COUNTIF('义体&义体技能'!AE:AE,AQ7) | AS7: 麻痹、易伤、降防等非伤害负面状态
A8: 武器序号介绍 | B8: WPN01010101 | C8: WPN (武器) | D8: 01 (阵营) | E8: 01 (武器种类) | F8: 01 (伤害类型) | G8: 01 (品质) | I8: BUF | K8: BUFF | N8: 发射器 | O8: Launcher | P8: 07 | Q8: =COUNTIF('武器'!H:H,N8)/6 | R8: =COUNTIF('武器技能'!E:E,N8) | Z8: 致远生物 | AA8: Bio Nexus | AB8: BN | AC8: 07 | AD8: =COUNTIF('义体&义体技能'!E:E,Z8) | AE8: =COUNTIF(AH:AH,Z8) | AF8: 夜幕刺客 | AG8: Night Assassin | AH8: 野望 | AI8: 爆发、暴击、脆皮。极致的玻璃大炮，追求一击必杀，但自身防御极低。 | AJ8: =IF(COUNTIF('义体&义体技能'!Z:Z,AF8)=0,"",COUNTIF('义体&义体技能'!Z:Z,AF8)) | AL8: 肺叶 | AM8: Lung | AN8: 06 | AO8: =COUNTIF('义体&义体技能'!F:F,AL8) | AQ8: 冷却 | AR8: =COUNTIF('义体&义体技能'!AE:AE,AQ8) | AS8: 技能冷却、能量回复
A9: 义体序号介绍 | B9: CYB01010101 | C9: CYB (义体) | D9: 01 (阵营) | E9: 01 (部位) | F9: 01 (系列) | G9: 00 (名称哈希) | I9: HPT | K9: 回复道具 | N9: 短刀 | O9: Kinfe | P9: 08 | Q9: =COUNTIF('武器'!H:H,N9)/6 | R9: =COUNTIF('武器技能'!E:E,N9) | Z9: 律动智能 | AA9: Rhythm Intelligence | AB9: RI | AC9: 08 | AD9: =COUNTIF('义体&义体技能'!E:E,Z9) | AE9: =COUNTIF(AH:AH,Z9) | AF9: 炼狱 | AG9: Inferno | AH9: 野望 | AI9: 火焰、爆炸、自伤。大范围的燃烧和爆炸伤害，往往容易误伤自己或队友。 | AJ9: =IF(COUNTIF('义体&义体技能'!Z:Z,AF9)=0,"",COUNTIF('义体&义体技能'!Z:Z,AF9)) | AL9: 眼球 | AM9: Eye | AN9: 07 | AO9: =COUNTIF('义体&义体技能'!F:F,AL9) | AQ9: 增益 | AR9: =COUNTIF('义体&义体技能'!AE:AE,AQ9) | AS9: 攻速叠加、属性成长
A10: 智脑序号介绍 | B10: CYB01010101 | C10: ITB (智脑) | D10: 01 (阵营) | E10: 00 (占位符) | F10: 00 (占位符) | G10: 00 (名称哈希) | I10: LVL | K10: 关卡道具 | N10: 长刀 | O10: Sword | P10: 09 | Q10: =COUNTIF('武器'!H:H,N10)/6 | R10: =COUNTIF('武器技能'!E:E,N10) | Z10: 耶利哥 | AA10: Jericho | AB10: JC | AC10: 09 | AD10: =COUNTIF('义体&义体技能'!E:E,Z10) | AE10: =COUNTIF(AH:AH,Z10) | AF10: 头奖 | AG10: Jackpot | AH10: 野望 | AI10: 随机性、赌博、暴富。攻击伤害浮动巨大，或有几率造成特殊的“幸运一击”（如秒杀小怪或掉落翻倍）。 | AJ10: =IF(COUNTIF('义体&义体技能'!Z:Z,AF10)=0,"",COUNTIF('义体&义体技能'!Z:Z,AF10)) | AL10: 心脏 | AM10: Heart | AN10: 08 | AO10: =COUNTIF('义体&义体技能'!F:F,AL10) | AQ10: 控制 | AR10: =COUNTIF('义体&义体技能'!AE:AE,AQ10) | AS10: 击倒、眩晕、硬直
I11: STY | K11: 剧情道具 | N11: 武士刀 | O11: Katana | P11: 10 | Q11: =COUNTIF('武器'!H:H,N11)/6 | R11: =COUNTIF('武器技能'!E:E,N11) | Z11: 东海工业 | AA11: Donghai Industry | AB11: DH | AC11: 10 | AD11: =COUNTIF('义体&义体技能'!E:E,Z11) | AE11: =COUNTIF(AH:AH,Z11) | AF11: 废土 | AG11: Wasteland | AH11: 野望 | AI11: 霸体 + 反伤的“刺猬流”被动输出。 | AJ11: =IF(COUNTIF('义体&义体技能'!Z:Z,AF11)=0,"",COUNTIF('义体&义体技能'!Z:Z,AF11)) | AL11: 内脑 | AM11: InnerBrain | AN11: 09 | AO11: =COUNTIF('义体&义体技能'!F:F,AL11) | AQ11: 体力 | AR11: =COUNTIF('义体&义体技能'!AE:AE,AQ11) | AS11: 体力消耗、恢复
N12: 巨剑 | O12: Great Sword | P12: 11 | Q12: =COUNTIF('武器'!H:H,N12)/6 | R12: =COUNTIF('武器技能'!E:E,N12) | AF12: 劳工 | AG12: Workforce | AH12: 劳旅 | AI12: 负重、耐力、持续作业。基础工业外骨骼，增加耐力条上限、恢复效率和武器、装备的使用效率。 | AJ12: =IF(COUNTIF('义体&义体技能'!Z:Z,AF12)=0,"",COUNTIF('义体&义体技能'!Z:Z,AF12)) | AQ12: 潜行 | AR12: =COUNTIF('义体&义体技能'!AE:AE,AQ12) | AS12: 潜行、光学迷彩
N13: 锤 | O13: Hammer | P13: 12 | Q13: =COUNTIF('武器'!H:H,N13)/6 | R13: =COUNTIF('武器技能'!E:E,N13) | AF13: 强袭 | AG13: Strike | AH13: 劳旅 | AI13: 大幅提升攻击的“削韧值”（打出敌人硬直的能力）。对已被击晕/倒地的敌人造成巨额额外伤害。 | AJ13: =IF(COUNTIF('义体&义体技能'!Z:Z,AF13)=0,"",COUNTIF('义体&义体技能'!Z:Z,AF13)) | AQ13: 反伤 | AR13: =COUNTIF('义体&义体技能'!AE:AE,AQ13) | AS13: 受击触发反击、能量脉冲
N14: 巨锤 | O14: Great Hammer | P14: 13 | Q14: =COUNTIF('武器'!H:H,N14)/6 | R14: =COUNTIF('武器技能'!E:E,N14) | AF14: 爆破组 | AG14: Demolition | AH14: 劳旅 | AI14: 定点爆破、陷阱、破坏环境。基于矿业炸药改装，擅长埋设地雷或炸开墙壁/掩体。 | AJ14: =IF(COUNTIF('义体&义体技能'!Z:Z,AF14)=0,"",COUNTIF('义体&义体技能'!Z:Z,AF14)) | AQ14: 随机性 | AR14: =COUNTIF('义体&义体技能'!AE:AE,AQ14) | AS14: 概率触发、超载风险
N15: 拳套 | O15: Kuckles | P15: 14 | Q15: =COUNTIF('武器'!H:H,N15)/6 | R15: =COUNTIF('武器技能'!E:E,N15) | AF15: 重构 | AG15: Reconstruct | AH15: 劳旅 | AI15: 建造、修理、炮塔。搭建临时掩体或维修友方机械单位。 | AJ15: =IF(COUNTIF('义体&义体技能'!Z:Z,AF15)=0,"",COUNTIF('义体&义体技能'!Z:Z,AF15)) | AQ15: 射程 | AR15: =COUNTIF('义体&义体技能'!AE:AE,AQ15) | AS15: 远程精准、有效距离
N16: 弓 | O16: Bow | P16: 15 | Q16: =COUNTIF('武器'!H:H,N16)/6 | R16: =COUNTIF('武器技能'!E:E,N16) | AF16: 液压 | AG16: Hydraulic | AH16: 劳旅 | AI16: 蓄力、极高单发伤害。利用液压系统进行超强力的蓄力攻击，机动性差但威力惊人。 | AJ16: =IF(COUNTIF('义体&义体技能'!Z:Z,AF16)=0,"",COUNTIF('义体&义体技能'!Z:Z,AF16)) | AQ16: 位移 | AR16: =COUNTIF('义体&义体技能'!AE:AE,AQ16) | AS16: 冲刺、翻滚、穿透
N17: 特殊 | O17: Special | P17: 16 | Q17: =COUNTIF('武器'!H:H,N17)/6 | R17: =COUNTIF('武器技能'!E:E,N17) | AF17: 小巷手艺 | AG17: Traceless | AH17: 新浦会 | AI17: 潜行、高机动、消音。不仅提供隐身能力，还能在移动中规避伤害，适合刺客流。 | AJ17: =IF(COUNTIF('义体&义体技能'!Z:Z,AF17)=0,"",COUNTIF('义体&义体技能'!Z:Z,AF17)) | AQ17: 经济 | AR17: =COUNTIF('义体&义体技能'!AE:AE,AQ17) | AS17: 折扣、资源获取优化
AF18: 踏雪无痕 | AG18: Alleycraft | AH18: 新浦会 | AI18: 处决、背刺、流血。 | AJ18: =IF(COUNTIF('义体&义体技能'!Z:Z,AF18)=0,"",COUNTIF('义体&义体技能'!Z:Z,AF18)) | AQ18: 攻速 | AR18: =COUNTIF('义体&义体技能'!AE:AE,AQ18) | AS18: 攻击速度相关
AF19: 龙头 | AG19: Dragon Head | AH19: 新浦会 | AI19: 周围的敌人攻击力降低、受到的伤害增加。适合喜欢冲入敌群站桩输出的近战Build。 | AJ19: =IF(COUNTIF('义体&义体技能'!Z:Z,AF19)=0,"",COUNTIF('义体&义体技能'!Z:Z,AF19)) | AQ19: 切换 | AR19: =COUNTIF('义体&义体技能'!AE:AE,AQ19) | AS19: 武器切换相关
AF20: 夜宴 | AG20: Banquet | AH20: 新浦会 | AI20: 恢复、增益、投掷。通过特殊的“食物”或药物提供临时Buff，或投掷燃烧瓶/毒酒。 | AJ20: =IF(COUNTIF('义体&义体技能'!Z:Z,AF20)=0,"",COUNTIF('义体&义体技能'!Z:Z,AF20))
AF21: 清道夫 | AG21: Cleaner | AH21: 新浦会 | AI21: 尸体利用、战后处理。击杀敌人后获得额外收益，或利用尸体制造陷阱/障碍。 | AJ21: =IF(COUNTIF('义体&义体技能'!Z:Z,AF21)=0,"",COUNTIF('义体&义体技能'!Z:Z,AF21))
AF22: 私人武装 | AG22: PMC Issue | AH22: 洛克海德 | AI22: 连续命中同一敌人时，伤害逐次提升（可叠加层数）。一旦未命中则层数清零。鼓励高精准度的持续输出。 | AJ22: =IF(COUNTIF('义体&义体技能'!Z:Z,AF22)=0,"",COUNTIF('义体&义体技能'!Z:Z,AF22))
AF23: 风暴 | AG23: Huracan | AH23: 洛克海德 | AI23: 自动“标记”血量最高的敌人，对标记目标造成的伤害提升或者尝试造成额外伤害判定。专攻精英怪和BOSS。 | AJ23: =IF(COUNTIF('义体&义体技能'!Z:Z,AF23)=0,"",COUNTIF('义体&义体技能'!Z:Z,AF23))
AF24: 先锋 | AG24: Vanguard | AH24: 洛克海德 | AI24: 向着敌人移动或冲刺时，受到的伤害大幅降低。冲刺结束时会对面前敌人造成击退。适合近战突脸。 | AJ24: =IF(COUNTIF('义体&义体技能'!Z:Z,AF24)=0,"",COUNTIF('义体&义体技能'!Z:Z,AF24))
AF25: 重装 | AG25: Heavy Duty | AH25: 洛克海德 | AI25: 原地站立不动时，攻速和射速随时间提升。移动会重置加成。适合“炮台流”玩法。 | AJ25: =IF(COUNTIF('义体&义体技能'!Z:Z,AF25)=0,"",COUNTIF('义体&义体技能'!Z:Z,AF25))
AF26: 维和 | AG26: Peacekeeper | AH26: 洛克海德 | AI26: 生命值低时，自动触发回血或无敌效果（有冷却）。减少异常状态的持续时间。万金油生存系列。 | AJ26: =IF(COUNTIF('义体&义体技能'!Z:Z,AF26)=0,"",COUNTIF('义体&义体技能'!Z:Z,AF26))
AF27: 链接者 | AG27: Linker | AH27: 寰宇 | AI27: 伤害传递、群体株连。通过在敌人间建立数据链接，让单体攻击变为群体毁灭。 | AJ27: =IF(COUNTIF('义体&义体技能'!Z:Z,AF27)=0,"",COUNTIF('义体&义体技能'!Z:Z,AF27))
AF28: 防火墙 | AG28: Faraday Cage | AH28: 寰宇 | AI28: 提供一层可再生的“能量护盾”（独立于血量）。护盾存在时，受击会向周围释放冲击波反弹伤害。适合“护盾流”或容错率较高的Build。 | AJ28: =IF(COUNTIF('义体&义体技能'!Z:Z,AF28)=0,"",COUNTIF('义体&义体技能'!Z:Z,AF28))
AF29: 超频 | AG29: Overclock | AH29: 寰宇 | AI29: 大幅缩减技能（行为芯片/智脑）的冷却时间，但每次使用技能都会扣除自身微量生命值或增加受到的伤害。适合“技能狂轰滥炸”流派。 | AJ29: =IF(COUNTIF('义体&义体技能'!Z:Z,AF29)=0,"",COUNTIF('义体&义体技能'!Z:Z,AF29))
AF30: 法拉第笼 | AG30: Counter-Net | AH30: 寰宇 | AI30: 干扰、削弱、视觉剥夺。使敌人致盲、命中率下降或瘫痪其特殊能力。 | AJ30: =IF(COUNTIF('义体&义体技能'!Z:Z,AF30)=0,"",COUNTIF('义体&义体技能'!Z:Z,AF30))
AF31: 临时任务 | AG31: Zero-Day | AH31: 寰宇 | AI31: 爆发、一次性、高风险。基于漏洞利用的高伤装备，往往伴随着过热或自身负面效果。 | AJ31: =IF(COUNTIF('义体&义体技能'!Z:Z,AF31)=0,"",COUNTIF('义体&义体技能'!Z:Z,AF31))
... AF51: 反应堆 | AG51: Reactor | AH51: 东海工业 | AI51: 辐射、能量光环。背负小型反应堆，持续对周围造成辐射伤害。 | AJ51: =IF(COUNTIF('义体&义体技能'!Z:Z,AF51)=0,"",COUNTIF('义体&义体技能'!Z:Z,AF51))

Sheet 阵营列表
A1: 编号 | B1: 名称 | C1: 性质 | D1: 公司定位 | E1: 装备风格 | F1: 命名风格
A2: 01 | B2: 纪念碑 | C2: 组织 | D2: 即使公司们一拖再拖，20世纪的大部分技术专利都已经入公共知识产权领域。而AI梦时代创造的大部分技术都遵循开源法规，这批科技古董反而成了最值钱的复古科幻纪念品。一直以来，大量非盈利团体致力于保证这些专利产品的持续开放性。 2032年，几个重要团体共同建立了纪念碑基金会，全权托管于管理ASI「M.O.N.U.M.」，意图创造没有偏见的公共知识产权管理组织。 数年后，「M.O.N.U.M.」被发现自上线之初，便无差别的窃取所有可访问的知识产权，并将其公开发布到互联网，但由于纪念碑组织的特殊性，该基金会既没有被关停，也没有任何人被问责，只是法律上被定义为非法。 即使步入了数据隔离时代，「M.O.N.U.M.」则依旧在旧互联网活跃。 | E2: 纪念碑的武器大多为现实世界已有、已经构思的武器，或者基于其微调、整合的版本。 | F2: 大多围绕欧美传说出发，也契合纪念碑本身来自欧美非盈利组织的根源性？
A3: 02 | B3: 野望 | C3: 组织 | D3: 活跃于全球的分布式地下组织，被大部分政府和公司定义为恐怖组织，但从未有人或团体以野望的名义对任何活动或袭击负责。 通过独特的交易与金融体系，野望为任何人提供任何其想要的产品和装备，无论是否受到专利保护、是否在该地区合法、是否对使用者本身有危险。 野望没有一个明确的动机，似乎只是一群人借用一个名号行事，也因此几乎无法被打击清除，事实上，大部分特许政府和中立公司都与野望有过不同形式的合作。 野望的产品标识最早出现的时间已不可考，应远早于「数据隔离」时代。 | E3: 野望的武器大多数为非常野路子的组合，特色看点/描述在于组合思路而非武器本身。 | F3: 围绕各种流行网络梗、黑客概念命名。
A4: 03 | B4: 劳旅 | C4: 组织 | D4: “不夜城”最大的劳动力外包团体，提供所有你能想到的工业、建筑、体力、流水线人力外包服务，之所以从未以公司自称，据说是为了规避各种企业法和税款。 由于其不是公司，因此其雇员也不受任何公司或政府的劳动法保护，但即便如此，在自动化机械大行其道的今天，一份劳旅的工作邀约已经是不夜城底层居民能找到的最为体面的工作之一。 劳旅自消泡事件后成立，大规模去AI运动，给带来前所未有的基础生产力缺口，动荡的环境也给了它成长的机会。 | E4: 劳旅的武器大多为工业器械而非武器，但有着不错的战斗表现。 | F4: 围绕装备本身的趣闻触发，有丰富的街头戏谑质感。
A5: 04 | B5: 新浦会 | C5: 组织 | D5: “不夜城”核心城区的最主要黑帮组织，为中立公司、特许政府提供各类服务，包括但不限于地区管控、强制征收、黑色军事行动等。 「新浦会」的历史源远流长。「AI梦」时代，所有非法暴力团体都受到大数据监控，导致影响力受限，但「新浦会」凭借其扎实的地方影响力和相对稳定的合法生意存活了下来。 自「消泡」事件后，它快速重新占据特许政府和中立公司无法触及的社区角落，提供餐饮、外送以及其他一系列个人服务，成为城市“毛细血管”的真正领导者，但内部也随着快速膨胀开始动荡。 “师傅” - 家钰（Yacco）成年后，以雷厉之势肃清了内部异己，前所未有团结的「新浦会」很快成为了不夜城核心城区毫无争议的地下之王。 | E5: 新浦会大多数武器有着隐蔽的外形和解构，便于在各类潜入任务中藏匿武器，作为不夜城最大的餐饮联盟，它们能藏的地方很多。 | F5: 围绕中国传统、尤其是春秋时期、山海经等老故事取材命名。
A6: 05 | B6: 洛克海德 | C6: 中立公司 | D6: 来自北美洲的老牌军工复合体，其自研的「S.T.O.R.M.」系统是世界上最早出现、也可能是最优秀的战术战略指挥ASI。 在过去的几十年时间里，通过结合自身的战斗装备硬件与AI战术部署服务，一直在军备领域占据绝对主导地位，即使是进入数据隔离时代，其武器订单依旧处于行业领先地位。 企业战争开始的前10年，洛克海德将总部迁至不夜城，并最终打响了企业战争的第一枪。 | E6: 典型的新美国风格制式装备，恰到好处的精密和可靠性，一切都为了高性价比的完成任务设计。 | F6: 风格类似典型的美制式武器命名。
A7: 06 | B7: 寰宇 | C7: 中立公司 | D7: 来自北欧、专注于信息技术和网络安全的公司，最初推出了SDN技术。 在企业战争中，寰宇通过提供先进的网络战技术和数据服务，借此机会在不夜城（Noctropolis）开展了自己的业务。 | E7: 专注于高水平的数字战，武器显得科幻、大多数附带各种网络攻击手段。 | F7: 围绕新浪潮和赛博朋克科幻小说的内容、梗、标题命名。
A8: 07 | B8: 东海工业 | C8: 中立公司 | D8: 东亚地区的工业巨头，引领了21世纪下半叶一系列工业、尤其是重工业与建筑工业的技术进步，最早在不夜城实现了的纤维大厦商业化建设。 作为不夜城（Noctropolis）本地发展起来的中立公司，有着难以撼动的民间支持率。 | E8: 扎实的装备、可靠、务实、质朴，而技术本身具备相当的领先性和实用性，尤其是在防御装备方面。 | F8: 围绕中国近代历史故事和地理特色命名。
A9: 08 | B9: 耶利哥 | C9: 中立公司 | D9: 成立于中亚地区的中立公司，在湿件控制领域有着领先的技术，与律动智能（Rhythm Intelligence）有着频繁的业务冲突。 消泡事件期间，耶利哥是首先公开销毁所有ASI的集团。 | E9: 在湿件研发领域有着相当的技术领先性，也是少数具有纳米武器量产经验的公司。 | F9: 围绕中亚、伊斯兰世界的传说和经典故事出发命名。
A10: 09 | B10: 律动智能 | C10: 中立公司 | D10: 发源自东南亚的机器人与人工智能企业。即使在ASI被宣布违法后，依旧致力于传统AI技术的开发。 该公司现在提供了大部分纤维城的无人浮空车控制系统，也在全球交通运输市场占有最高份额。 | E10: 大量围绕自动化（自动瞄准、追踪）技术的武器被装备给该公司的员工。 | F10: 围绕中、日、韩的传说和小说、经典故事出发。本来赛博朋克故事里亚洲才是世界的中心。
A11: 10 | B11: 致远生物 | C11: 中立公司 | D11: 来自于西欧的生物科技公司，在融合打印技术上的积累无人能敌。 似乎在基因改造技术上也颇有建树，但受制于社会伦理，并没有太多公开成果。 该公司提供了市场上超过40%份额的药物品类。 | E11: 有相当多提供肉体强化的义体，让员工可以以“超人”的强度作战，充分发挥其基因科研优势。 | F11: 围绕欧洲神话、经典故事命名。

Sheet 武器
B1: Name | D1: UUID | E1: Faction | F1: Quality | N1: DamageRange | W1: MinSpreadAngle | X1: MaxSpreadAngle | Y1: SpreadDelta | Z1: SpreadReduce | AA1: SpreadReduceInterval | AB1: MoveSpreadIncrease | AC1: MoveSpreadMultiply | AG1: SpreadRange | AJ1: Strength | AK1: Reflex | AL1: Intelligence | BB1: AdjustFactor | BH1: PoiseDamage | BL1: A.A. | BQ1: AmmoC | BR1: AmmoValue | BS1: InitialActionCnt | BT1: CheckPerAttack | BW1: StaminaCost | CA1: BaseDamage | CB1: AdjustDamage | CC1: PreCorrectDamage | CJ1: WeaponFactorCal | CK1: WeaponFactor | CN1: PostCorrectDamage | CP1: DPA | CQ1: DPS | CV1: APS | DC1: 开发 | DD1: 配置
A2: 资产名称 | B2: 中文名称 | C2: 英文名称 | D2: UUID | E2: 阵营 | F2: 品质 | G2: 攻击类型 | H2: 武器类型 | I2: 伤害类型 | J2: 攻击模式 | K2: 伤害类型 | M2: 移速 | N2: 伤害半径 | O2: 伤害角度 | P2: 前摇 | Q2: 伤害 | R2: 后摇 | S2: 间隔 | T2: 攻击时长 | U2: 卡肉时长 | W2: 最小散布 | X2: 最大散布 | Y2: 扩张速度 | Z2: 回馈速度 | AA2: 散布回复间隔 | AB2: 移动散布增长 | AC2: 移动散布倍率 | AD2: 移动最小散布 | AE2: 移动最大散布 | AG2: 攻击声音范围 | AH2: 击中声音范围 | AJ2: 力量补正 | AK2: 反应补正 | AL2: 智力补正 | AM2: 力量等级 | AN2: 反应等级 | AO2: 智力等级 | AP2: 力量假设 | AQ2: 反应假设 | AR2: 智力假设 | AS2: 代谢补正 | AT2: 适应补正 | AU2: 耐力补正 | AV2: 单项上限 | AW2: 最大单项 | AX2: 专精率 | AY2: 总和上限 | AZ2: 补正总和 | BA2: 利用率 | BB2: 补正系数 | BD2: 冲击等级 | BE2: 冲击类型 | BF2: 韧性伤害水平 | BG2: 参考韧性伤害 | BH2: 韧性伤害 | BJ2: 异常积蓄水平 | BK2: 参考异常积蓄 | BL2: 异常积蓄 | BN2: 装弹量 | BO2: 装弹间隔 | BP2: 参考子弹消耗 | BQ2: 子弹消耗 | BR2: 子弹价值 | BS2: 发射弹丸 | BT2: 每动判定 | BV2: 期望体力消耗 | BW2: 体力消耗 | BX2: 体力价值 | BY2: 体力消耗/s | CA2: 基础伤害 | CB2: 补正伤害 | CC2: 矫正前伤害 | CD2: 伤害系数 | CE2: 射程系数 | CF2: 命中系数 | CG2: 冲击系数 | CH2: 异常系数 | CI2: 霰弹系数 | CJ2: 期望系数 | CK2: 武器系数 | CL2: 标准系数 | CM2: 系数价值 | CN2: 矫正后伤害 | CP2: 每动伤害 | CQ2: 每秒伤害 | CR2: ATK | CS2: TTK | CT2: 增额 | CU2: 增幅 | CV2: 每秒异常 | CW2: TTA | CY2: 描述 | DA2: 武器技能 | DC2: =COUNTIF(DC3:DC996,"完成") | DD2: =COUNTIF(DD3:DD996,"完成")
A3: DSRevolver | B3: DS左轮 | D3: =IF($A3="","","WPN"&VLOOKUP(E3,'引用数据库'!Z:AC,4,FALSE)&VLOOKUP(H3,'引用数据库'!N:P,3,FALSE)&VLOOKUP(I3,'引用数据库'!S:U,3,FALSE)&TEXT(F3,"00")) | E3: 纪念碑 | F3: 0 | G3: 远程 | H3: 手枪 | I3: 动能 | J3: 手动 | K3: 1 | M3: 1 | N3: =BO3 | O3: N/A | P3: 0 | Q3: 0 | R3: 0.35 | S3: 0 | T3: =SUM(P3:S3) | U3: =2*T3/(15*(1+(5-BD3)*0.1)) | W3: 0 | X3: 20 | Y3: 0.075 | Z3: 0.15 | AA3: 0.5 | AB3: 5 | AC3: 1.5 | AD3: =(W3+AB3)*AC3 | AE3: =(X3+AB3)*AC3 | AJ3: 0.3 | AK3: 0.763 | AL3: 0 | AM3: =IFS(AJ3 > 1.25, "S", AJ3 > 1, "A", AJ3 > 0.75, "B", AJ3 > 0.5, "C", AJ3 > 0.25, "D", AJ3 > 0, "E", TRUE, "-") | AN3: =IFS(AK3 > 1.25, "S", AK3 > 1, "A", AK3 > 0.75, "B", AK3 > 0.5, "C", AK3 > 0.25, "D", AK3 > 0, "E", TRUE, "-") | AO3: =IFS(AL3 > 1.25, "S", AL3 > 1, "A", AL3 > 0.75, "B", AL3 > 0.5, "C", AL3 > 0.25, "D", AL3 > 0, "E", TRUE, "-") | AP3: 10 | AQ3: 10 | AR3: 10 | AV3: =IF(SUM(AJ3:AL3)=0, 0, (1 + F3 * 0.1) * (0.75 + 0.25 * MAX(0, MIN(1, IF(MAX(AJ3:AL3)=0, 0, (3*MAX(AJ3:AL3)-SUM(AJ3:AL3)) / (2*MAX(AJ3:AL3))))))) | AW3: =MAX(AJ3:AL3) | AX3: =IF(AW3=0, "", AW3 / ((1 + 0.1*N(F3)))) | AY3: =IF(SUM(AJ3:AL3)=0, 0, (1 + F3 * 0.1) * (1 + ((SUM(AJ3:AL3) - MAX(AJ3:AL3)) / (2 * MAX(AJ3:AL3))) * (1/0.75 - 1))) | AZ3: =AJ3+AK3+AL3 | BA3: =IF(AZ3=0, "", AZ3 / ((1 + 0.1*N(F3))/0.75)) | BB3: 0.1 | BD3: 10 | BE3: 7 | BF3: 3 | BG3: =T3*20*(16 * BF3) / (15 + 20 * BF3 - 3 * POWER(BF3, 2))/BT3/BS3 | BH3: =BG3 | BJ3: 3 | BK3: =T3*33*(16 * BJ3) / (15 + 20 * BJ3 - 3 * POWER(BJ3, 2))/BT3/BS3 | BL3: =BK3 | BN3: 6 | BO3: 3 | BP3: =ROUND(CP3/10,2) | BQ3: 1 | BR3: =IFERROR(BQ3*100/CP3,"N/A") | BS3: 1 | BT3: 1 | BV3: =CP3/1.5 | BW3: =ROUND(BV3) | BX3: =CP3/BW3 | BY3: =BW3/T3 | CA3: 10 | CB3: =CA3*BB3*(AP3*AJ3+AQ3*AK3+AR3*AL3) | CC3: =CA3+CB3 | CD3: =T3 * 2 / BS3 / BT3 * (0.9 + 0.2 * IF(G3="近战", EXP(-64 * (T3 - 0.75)^2), EXP(-400 * (T3 - 0.15)^2))) | CE3: =0.9 + 0.2 / (1 + (N3/600)^1) | CF3: =LET( k, K9, be, BS9, bf, BT9, m, N9, n, O9, v, X9, vEff, IF(ISNUMBER(v), v, 0), angle, IF( ISNUMBER(n), IF(n>0, n, IF(ISNUMBER(v), IF(v>0, v, 0), 0 ) ), IF(ISNUMBER(v), IF(v>0, v, 0), 0 ) ), T, IF(k=1, be * bf * 20 / MAX(vEff, 1), IF(k=2, (m/150)^2 * (angle/120), IF(k=3, be * (MIN(bf, 99)/99) * (m/1000), be * bf * (m/1000) * (n/200)^2 ))), b, 0.8, c, 1.2, r, (c-1)/(1-b), k_s, 1, b + (c-b) / (1 + r * EXP(-k_s*(1-T)))) | CG3: =IF(T3<=0,1, (0.9 + 0.2 / (1 + EXP(-0.8 * (5 - BD3)))) * (0.9 + 0.2 / (1 + EXP(-1 * (3.5 - BE3)))) * (0.9 + 0.2 / (1 + EXP(-0.6 * (20 - BS3*BH3/T3))))) | CH3: =IF(T3<=0, 1, 0.9 + 0.2 / (1 + EXP(0.1 * (BL3*BS3*BT3/T3 - 33)))) | CI3: =LET( x_val, W3, bq_val, BS3, Check_Fail, OR(NOT(ISNUMBER(x_val)), bq_val <= 1), IF(Check_Fail, 1, LET( Ratio, x_val / bq_val, calc_A, 2.2 / (1 + EXP(-0.276 * (Ratio - 0.66))), calc_B, 2.2 / (1 + EXP(-0.0138 * (x_val - 13.2))), calc_A + calc_B ) )) | CJ3: =CD3*CE3*CF3*CG3*CH3*CI3 | CK3: =CJ3 | CL3: =T3 * 2 / BS3 / BT3 | CM3: =CK3/CL3 | CN3: =CK3*CC3 | CP3: =CN3*BS3*BT3 | CQ3: =CP3/T3 | CR3: =100/CP3 | CS3: =100/CQ3 | CV3: =BL3/T3 | CW3: =100/CV3 | CY3: 黑市中最常见的左轮手枪。 设计精巧，操控简单，一般人也能迅速上手。 设计蓝图在数据隔离时代之前就已经流入黑市。 几经迭代后，在各路雇佣兵手里活跃至今天。 | DA3: =TEXTJOIN("、", TRUE, FILTER('武器技能'!B:B, '武器技能'!E:E = H3)) | DC3: 完成 | DD3: 完成
A4: DSRevolver | B4: DS左轮 | D4: =IF($A4="","","WPN"&VLOOKUP(E4,'引用数据库'!Z:AC,4,FALSE)&VLOOKUP(H4,'引用数据库'!N:P,3,FALSE)&VLOOKUP(I4,'引用数据库'!S:U,3,FALSE)&TEXT(F4,"00")) | E4: 纪念碑 | F4: 1 | G4: 远程 | H4: 手枪 | I4: 动能 | J4: 手动 | K4: =K3 | M4: =M3 | N4: =N3 | O4: N/A | P4: 0 | Q4: 0 | R4: 0.35 | S4: 0 | T4: =SUM(P4:S4) | U4: =2*T4/(15*(1+(5-BD4)*0.1)) | W4: =W3 | X4: =X3 | Y4: =Y3 | Z4: =Z3 | AA4: =AA3 | AB4: =AB3 | AC4: =AC3 | AD4: =AD3 | AE4: =AE3 | AJ4: =AJ3+0.05 | AK4: 0.83 | AL4: 0 | AM4: =IFS(AJ4 > 1.25, "S", AJ4 > 1, "A", AJ4 > 0.75, "B", AJ4 > 0.5, "C", AJ4 > 0.25, "D", AJ4 > 0, "E", TRUE, "-") | AN4: =IFS(AK4 > 1.25, "S", AK4 > 1, "A", AK4 > 0.75, "B", AK4 > 0.5, "C", AK4 > 0.25, "D", AK4 > 0, "E", TRUE, "-") | AO4: =IFS(AL4 > 1.25, "S", AL4 > 1, "A", AL4 > 0.75, "B", AL4 > 0.5, "C", AL4 > 0.25, "D", AL4 > 0, "E", TRUE, "-") | AP4: 10 | AQ4: 10 | AR4: 10 | AV4: =IF(SUM(AJ4:AL4)=0, 0, (1 + F4 * 0.1) * (0.75 + 0.25 * MAX(0, MIN(1, IF(MAX(AJ4:AL4)=0, 0, (3*MAX(AJ4:AL4)-SUM(AJ4:AL4)) / (2*MAX(AJ4:AL4))))))) | AW4: =MAX(AJ4:AL4) | AX4: =IF(AW4=0, "", AW4 / ((1 + 0.1*N(F4)))) | AY4: =IF(SUM(AJ4:AL4)=0, 0, (1 + F4 * 0.1) * (1 + ((SUM(AJ4:AL4) - MAX(AJ4:AL4)) / (2 * MAX(AJ4:AL4))) * (1/0.75 - 1))) | AZ4: =AJ4+AK4+AL4 | BA4: =IF(AZ4=0, "", AZ4 / ((1 + 0.1*N(F4))/0.75)) | BB4: 0.1 | BD4: =BD3 | BE4: =BE3 | BH4: =BH3 | BL4: =BL3 | BN4: =BN3 | BO4: =BO3 | BQ4: =BQ3 | BR4: =IFERROR(BQ4*100/CP4,"N/A") | BS4: 1 | BT4: =BT3 | BW4: =BW3 | BX4: =CP4/BW4 | BY4: =BW4/T4 | CA4: =CA3+20 | CB4: =CA4*BB4*(AP4*AJ4+AQ4*AK4+AR4*AL4) | CC4: =CA4+CB4 | CK4: =CK3 | CN4: =CK4*CC4 | CP4: =CN4*BS4*BT4 | CQ4: =CP4/T4 | CR4: =100/CP4 | CS4: =100/CQ4 | CT4: =CQ4-CQ3 | CU4: =(CQ4-CQ3)/CQ3 | CV4: =BL4/T4 | CW4: =100/CV4 | DC4: 完成 | DD4: 完成
A5: DSRevolver | B5: DS左轮 | D5: =IF($A5="","","WPN"&VLOOKUP(E5,'引用数据库'!Z:AC,4,FALSE)&VLOOKUP(H5,'引用数据库'!N:P,3,FALSE)&VLOOKUP(I5,'引用数据库'!S:U,3,FALSE)&TEXT(F5,"00")) | E5: 纪念碑 | F5: 2 | G5: 远程 | H5: 手枪 | I5: 动能 | J5: 手动 | K5: =K4 | M5: =M4 | N5: =N4 | O5: N/A | P5: 0 | Q5: 0 | R5: 0.35 | S5: 0 | T5: =SUM(P5:S5) | U5: =2*T5/(15*(1+(5-BD5)*0.1)) | W5: =W4 | X5: =X4 | Y5: =Y4 | Z5: =Z4 | AA5: =AA4 | AB5: =AB4 | AC5: =AC4 | AD5: =AD4 | AE5: =AE4 | AJ5: =AJ4+0.05 | AK5: 0.89 | AL5: 0 | AM5: =IFS(AJ5 > 1.25, "S", AJ5 > 1, "A", AJ5 > 0.75, "B", AJ5 > 0.5, "C", AJ5 > 0.25, "D", AJ5 > 0, "E", TRUE, "-") | AN5: =IFS(AK5 > 1.25, "S", AK5 > 1, "A", AK5 > 0.75, "B", AK5 > 0.5, "C", AK5 > 0.25, "D", AK5 > 0, "E", TRUE, "-") | AO5: =IFS(AL5 > 1.25, "S", AL5 > 1, "A", AL5 > 0.75, "B", AL5 > 0.5, "C", AL5 > 0.25, "D", AL5 > 0, "E", TRUE, "-") | AP5: 10 | AQ5: 10 | AR5: 10 | AV5: =IF(SUM(AJ5:AL5)=0, 0, (1 + F5 * 0.1) * (0.75 + 0.25 * MAX(0, MIN(1, IF(MAX(AJ5:AL5)=0, 0, (3*MAX(AJ5:AL5)-SUM(AJ5:AL5)) / (2*MAX(AJ5:AL5))))))) | AW5: =MAX(AJ5:AL5) | AX5: =IF(AW5=0, "", AW5 / ((1 + 0.1*N(F5)))) | AY5: =IF(SUM(AJ5:AL5)=0, 0, (1 + F5 * 0.1) * (1 + ((SUM(AJ5:AL5) - MAX(AJ5:AL5)) / (2 * MAX(AJ5:AL5))) * (1/0.75 - 1))) | AZ5: =AJ5+AK5+AL5 | BA5: =IF(AZ5=0, "", AZ5 / ((1 + 0.1*N(F5))/0.75)) | BB5: 0.1 | BD5: =BD4 | BE5: =BE4 | BH5: =BH4 | BL5: =BL4 | BN5: =BN4 | BO5: =BO4 | BQ5: =BQ4 | BR5: =IFERROR(BQ5*100/CP5,"N/A") | BS5: 1 | BT5: =BT4 | BW5: =BW4 | BX5: =CP5/BW5 | BY5: =BW5/T5 | CA5: =CA4+10 | CB5: =CA5*BB5*(AP5*AJ5+AQ5*AK5+AR5*AL5) | CC5: =CA5+CB5 | CK5: =CK4 | CN5: =CK5*CC5 | CP5: =CN5*BS5*BT5 | CQ5: =CP5/T5 | CR5: =100/CP5 | CS5: =100/CQ5 | CT5: =CQ5-CQ4 | CU5: =(CQ5-CQ4)/CQ4 | CV5: =BL5/T5 | CW5: =100/CV5 | DC5: 完成 | DD5: 完成
A6: DSRevolver | B6: DS左轮 | D6: =IF($A6="","","WPN"&VLOOKUP(E6,'引用数据库'!Z:AC,4,FALSE)&VLOOKUP(H6,'引用数据库'!N:P,3,FALSE)&VLOOKUP(I6,'引用数据库'!S:U,3,FALSE)&TEXT(F6,"00")) | E6: 纪念碑 | F6: 3 | G6: 远程 | H6: 手枪 | I6: 动能 | J6: 手动 | K6: =K5 | M6: =M5 | N6: =N5 | O6: N/A | P6: 0 | Q6: 0 | R6: 0.35 | S6: 0 | T6: =SUM(P6:S6) | U6: =2*T6/(15*(1+(5-BD6)*0.1)) | W6: =W5 | X6: =X5 | Y6: =Y5 | Z6: =Z5 | AA6: =AA5 | AB6: =AB5 | AC6: =AC5 | AD6: =AD5 | AE6: =AE5 | AJ6: =AJ5+0.05 | AK6: 0.95 | AL6: 0 | AM6: =IFS(AJ6 > 1.25, "S", AJ6 > 1, "A", AJ6 > 0.75, "B", AJ6 > 0.5, "C", AJ6 > 0.25, "D", AJ6 > 0, "E", TRUE, "-") | AN6: =IFS(AK6 > 1.25, "S", AK6 > 1, "A", AK6 > 0.75, "B", AK6 > 0.5, "C", AK6 > 0.25, "D", AK6 > 0, "E", TRUE, "-") | AO6: =IFS(AL6 > 1.25, "S", AL6 > 1, "A", AL6 > 0.75, "B", AL6 > 0.5, "C", AL6 > 0.25, "D", AL6 > 0, "E", TRUE, "-") | AP6: 10 | AQ6: 10 | AR6: 10 | AV6: =IF(SUM(AJ6:AL6)=0, 0, (1 + F6 * 0.1) * (0.75 + 0.25 * MAX(0, MIN(1, IF(MAX(AJ6:AL6)=0, 0, (3*MAX(AJ6:AL6)-SUM(AJ6:AL6)) / (2*MAX(AJ6:AL6))))))) | AW6: =MAX(AJ6:AL6) | AX6: =IF(AW6=0, "", AW6 / ((1 + 0.1*N(F6)))) | AY6: =IF(SUM(AJ6:AL6)=0, 0, (1 + F6 * 0.1) * (1 + ((SUM(AJ6:AL6) - MAX(AJ6:AL6)) / (2 * MAX(AJ6:AL6))) * (1/0.75 - 1))) | AZ6: =AJ6+AK6+AL6 | BA6: =IF(AZ6=0, "", AZ6 / ((1 + 0.1*N(F6))/0.75)) | BB6: 0.1 | BD6: =BD5 | BE6: =BE5 | BH6: =BH5 | BL6: =BL5 | BN6: =BN5 | BO6: =BO5 | BQ6: =BQ5 | BR6: =IFERROR(BQ6*100/CP6,"N/A") | BS6: 1 | BT6: =BT5 | BW6: =BW5 | BX6: =CP6/BW6 | BY6: =BW6/T6 | CA6: =CA5+10 | CB6: =CA6*BB6*(AP6*AJ6+AQ6*AK6+AR6*AL6) | CC6: =CA6+CB6 | CK6: =CK5 | CN6: =CK6*CC6 | CP6: =CN6*BS6*BT6 | CQ6: =CP6/T6 | CR6: =100/CP6 | CS6: =100/CQ6 | CT6: =CQ6-CQ5 | CU6: =(CQ6-CQ5)/CQ5 | CV6: =BL6/T6 | CW6: =100/CV6 | DC6: 完成 | DD6: 完成
A7: DSRevolver | B7: DS左轮 | D7: =IF($A7="","","WPN"&VLOOKUP(E7,'引用数据库'!Z:AC,4,FALSE)&VLOOKUP(H7,'引用数据库'!N:P,3,FALSE)&VLOOKUP(I7,'引用数据库'!S:U,3,FALSE)&TEXT(F7,"00")) | E7: 纪念碑 | F7: 4 | G7: 远程 | H7: 手枪 | I7: 动能 | J7: 手动 | K7: =K6 | M7: =M6 | N7: =N6 | O7: N/A | P7: 0 | Q7: 0 | R7: 0.35 | S7: 0 | T7: =SUM(P7:S7) | U7: =2*T7/(15*(1+(5-BD7)*0.1)) | W7: =W6 | X7: =X6 | Y7: =Y6 | Z7: =Z6 | AA7: =AA6 | AB7: =AB6 | AC7: =AC6 | AD7: =AD6 | AE7: =AE6 | AJ7: =AJ6+0.05 | AK7: 1.02 | AL7: 0 | AM7: =IFS(AJ7 > 1.25, "S", AJ7 > 1, "A", AJ7 > 0.75, "B", AJ7 > 0.5, "C", AJ7 > 0.25, "D", AJ7 > 0, "E", TRUE, "-") | AN7: =IFS(AK7 > 1.25, "S", AK7 > 1, "A", AK7 > 0.75, "B", AK7 > 0.5, "C", AK7 > 0.25, "D", AK7 > 0, "E", TRUE, "-") | AO7: =IFS(AL7 > 1.25, "S", AL7 > 1, "A", AL7 > 0.75, "B", AL7 > 0.5, "C", AL7 > 0.25, "D", AL7 > 0, "E", TRUE, "-") | AP7: 10 | AQ7: 10 | AR7: 10 | AV7: =IF(SUM(AJ7:AL7)=0, 0, (1 + F7 * 0.1) * (0.75 + 0.25 * MAX(0, MIN(1, IF(MAX(AJ7:AL7)=0, 0, (3*MAX(AJ7:AL7)-SUM(AJ7:AL7)) / (2*MAX(AJ7:AL7))))))) | AW7: =MAX(AJ7:AL7) | AX7: =IF(AW7=0, "", AW7 / ((1 + 0.1*N(F7)))) | AY7: =IF(SUM(AJ7:AL7)=0, 0, (1 + F7 * 0.1) * (1 + ((SUM(AJ7:AL7) - MAX(AJ7:AL7)) / (2 * MAX(AJ7:AL7))) * (1/0.75 - 1))) | AZ7: =AJ7+AK7+AL7 | BA7: =IF(AZ7=0, "", AZ7 / ((1 + 0.1*N(F7))/0.75)) | BB7: 0.1 | BD7: =BD6 | BE7: =BE6 | BH7: =BH6 | BL7: =BL6 | BN7: =BN6 | BO7: =BO6 | BQ7: =BQ6 | BR7: =IFERROR(BQ7*100/CP7,"N/A") | BS7: 1 | BT7: =BT6 | BW7: =BW6 | BX7: =CP7/BW7 | BY7: =BW7/T7 | CA7: =CA6+10 | CB7: =CA7*BB7*(AP7*AJ7+AQ7*AK7+AR7*AL7) | CC7: =CA7+CB7 | CK7: =CK6 | CN7: =CK7*CC7 | CP7: =CN7*BS7*BT7 | CQ7: =CP7/T7 | CR7: =100/CP7 | CS7: =100/CQ7 | CT7: =CQ7-CQ6 | CU7: =(CQ7-CQ6)/CQ6 | CV7: =BL7/T7 | CW7: =100/CV7 | DC7: 完成 | DD7: 完成
A8: DSRevolver | B8: DS左轮 | D8: =IF($A8="","","WPN"&VLOOKUP(E8,'引用数据库'!Z:AC,4,FALSE)&VLOOKUP(H8,'引用数据库'!N:P,3,FALSE)&VLOOKUP(I8,'引用数据库'!S:U,3,FALSE)&TEXT(F8,"00")) | E8: 纪念碑 | F8: 5 | G8: 远程 | H8: 手枪 | I8: 动能 | J8: 手动 | K8: =K7 | M8: =M7 | N8: =N7 | O8: N/A | P8: 0 | Q8: 0 | R8: 0.35 | S8: 0 | T8: =SUM(P8:S8) | U8: =2*T8/(15*(1+(5-BD8)*0.1)) | W8: =W7 | X8: =X7 | Y8: =Y7 | Z8: =Z7 | AA8: =AA7 | AB8: =AB7 | AC8: =AC7 | AD8: =AD7 | AE8: =AE7 | AJ8: =AJ7+0.05 | AK8: 1.08 | AL8: 0 | AM8: =IFS(AJ8 > 1.25, "S", AJ8 > 1, "A", AJ8 > 0.75, "B", AJ8 > 0.5, "C", AJ8 > 0.25, "D", AJ8 > 0, "E", TRUE, "-") | AN8: =IFS(AK8 > 1.25, "S", AK8 > 1, "A", AK8 > 0.75, "B", AK8 > 0.5, "C", AK8 > 0.25, "D", AK8 > 0, "E", TRUE, "-") | AO8: =IFS(AL8 > 1.25, "S", AL8 > 1, "A", AL8 > 0.75, "B", AL8 > 0.5, "C", AL8 > 0.25, "D", AL8 > 0, "E", TRUE, "-") | AP8: 10 | AQ8: 10 | AR8: 10 | AV8: =IF(SUM(AJ8:AL8)=0, 0, (1 + F8 * 0.1) * (0.75 + 0.25 * MAX(0, MIN(1, IF(MAX(AJ8:AL8)=0, 0, (3*MAX(AJ8:AL8)-SUM(AJ8:AL8)) / (2*MAX(AJ8:AL8))))))) | AW8: =MAX(AJ8:AL8) | AX8: =IF(AW8=0, "", AW8 / ((1 + 0.1*N(F8)))) | AY8: =IF(SUM(AJ8:AL8)=0, 0, (1 + F8 * 0.1) * (1 + ((SUM(AJ8:AL8) - MAX(AJ8:AL8)) / (2 * MAX(AJ8:AL8))) * (1/0.75 - 1))) | AZ8: =AJ8+AK8+AL8 | BA8: =IF(AZ8=0, "", AZ8 / ((1 + 0.1*N(F8))/0.75)) | BB8: 0.1 | BD8: =BD7 | BE8: =BE7 | BH8: =BH7 | BL8: =BL7 | BN8: =BN7 | BO8: =BO7 | BQ8: =BQ7 | BR8: =IFERROR(BQ8*100/CP8,"N/A") | BS8: 1 | BT8: =BT7 | BW8: =BW7 | BX8: =CP8/BW8 | BY8: =BW8/T8 | CA8: =CA7+10 | CB8: =CA8*BB8*(AP8*AJ8+AQ8*AK8+AR8*AL8) | CC8: =CA8+CB8 | CK8: =CK7 | CN8: =CK8*CC8 | CP8: =CN8*BS8*BT8 | CQ8: =CP8/T8 | CR8: =100/CP8 | CS8: =100/CQ8 | CT8: =CQ8-CQ7 | CU8: =(CQ8-CQ7)/CQ7 | CV8: =BL8/T8 | CW8: =100/CV8 | DC8: 完成 | DD8: 完成
A9: AsFire | B9: 若火 | D9: =IF($A9="","","WPN"&VLOOKUP(E9,'引用数据库'!Z:AC,4,FALSE)&VLOOKUP(H9,'引用数据库'!N:P,3,FALSE)&VLOOKUP(I9,'引用数据库'!S:U,3,FALSE)&TEXT(F9,"00")) | E9: 野望 | F9: 0 | G9: 近战 | H9: 武士刀 | I9: 热能 | J9: 手动 | K9: 2 | M9: 1 | N9: 170 | O9: 120 | P9: 0.367 | Q9: 0.176 | R9: 0.257 | S9: 0 | T9: =SUM(P9:S9) | U9: =2*T9/(15*(1+(5-BD9)*0.1)) | W9: N/A | X9: N/A | Y9: N/A | Z9: N/A | AD9: N/A | AE9: N/A | AJ9: 0.12 | AK9: 0.9 | AL9: 0 | AM9: =IFS(AJ9 > 1.25, "S", AJ9 > 1, "A", AJ9 > 0.75, "B", AJ9 > 0.5, "C", AJ9 > 0.25, "D", AJ9 > 0, "E", TRUE, "-") | AN9: =IFS(AK9 > 1.25, "S", AK9 > 1, "A", AK9 > 0.75, "B", AK9 > 0.5, "C", AK9 > 0.25, "D", AK9 > 0, "E", TRUE, "-") | AO9: =IFS(AL9 > 1.25, "S", AL9 > 1, "A", AL9 > 0.75, "B", AL9 > 0.5, "C", AL9 > 0.25, "D", AL9 > 0, "E", TRUE, "-") | AP9: 10 | AQ9: 10 | AR9: 10 | AV9: =IF(SUM(AJ9:AL9)=0, 0, (1 + F9 * 0.1) * (0.75 + 0.25 * MAX(0, MIN(1, IF(MAX(AJ9:AL9)=0, 0, (3*MAX(AJ9:AL9)-SUM(AJ9:AL9)) / (2*MAX(AJ9:AL9))))))) | AW9: =MAX(AJ9:AL9) | AX9: =IF(AW9=0, "", AW9 / ((1 + 0.1*N(F9)))) | AY9: =IF(SUM(AJ9:AL9)=0, 0, (1 + F9 * 0.1) * (1 + ((SUM(AJ9:AL9) - MAX(AJ9:AL9)) / (2 * MAX(AJ9:AL9))) * (1/0.75 - 1))) | AZ9: =AJ9+AK9+AL9 | BA9: =IF(AZ9=0, "", AZ9 / ((1 + 0.1*N(F9))/0.75)) | BB9: 0.1 | BD9: 3 | BE9: 2 | BF9: 3 | BG9: =T9*20*(16 * BF9) / (15 + 20 * BF9 - 3 * POWER(BF9, 2))/BT9/BS9 | BH9: =BG9 | BJ9: 4 | BK9: =T9*33*(16 * BJ9) / (15 + 20 * BJ9 - 3 * POWER(BJ9, 2))/BT9/BS9 | BL9: =BK9 | BN9: N/A | BO9: N/A | BP9: 0 | BQ9: 0 | BR9: =IFERROR(BQ9*100/CP9,"N/A") | BS9: 1 | BT9: 1 | BV9: =CP9/1.5 | BW9: =ROUND(BV9) | BX9: =CP9/BW9 | BY9: =BW9/T9 | CA9: 10 | CB9: =CA9*BB9*(AP9*AJ9+AQ9*AK9+AR9*AL9) | CC9: =CA9+CB9 | CD9: =T9 * 2 / BS9 / BT9 * (0.9 + 0.2 * IF(G9="近战", EXP(-64 * (T9 - 0.75)^2), EXP(-400 * (T9 - 0.15)^2))) | CE9: =0.9 + 0.2 / (1 + (N9/600)^1) | CF9: =LET( k, K9, be, BS9, bf, BT9, m, N9, n, O9, v, X9, vEff, IF(ISNUMBER(v), v, 0), angle, IF( ISNUMBER(n), IF(n>0, n, IF(ISNUMBER(v), IF(v>0, v, 0), 0 ) ), IF(ISNUMBER(v), IF(v>0, v, 0), 0 ) ), T, IF(k=1, be * bf * 20 / MAX(vEff, 1), IF(k=2, (m/150)^2 * (angle/120), IF(k=3, be * (MIN(bf, 99)/99) * (m/1000), be * bf * (m/1000) * (n/200)^2 ))), b, 0.8, c, 1.2, r, (c-1)/(1-b), k_s, 1, b + (c-b) / (1 + r * EXP(-k_s*(1-T)))) | CG9: =IF(T9<=0,1, (0.9 + 0.2 / (1 + EXP(-0.8 * (5 - BD9)))) * (0.9 + 0.2 / (1 + EXP(-1 * (3.5 - BE9)))) * (0.9 + 0.2 / (1 + EXP(-0.6 * (20 - BS9*BH9/T9))))) | CH9: =IF(T9<=0, 1, 0.9 + 0.2 / (1 + EXP(0.1 * (BL9*BS9*BT9/T9 - 33)))) | CI9: =LET( x_val, W9, bq_val, BS9, Check_Fail, OR(NOT(ISNUMBER(x_val)), bq_val <= 1), IF(Check_Fail, 1, LET( Ratio, x_val / bq_val, calc_A, 2.2 / (1 + EXP(-0.276 * (Ratio - 0.66))), calc_B, 2.2 / (1 + EXP(-0.0138 * (x_val - 13.2))), calc_A + calc_B ) )) | CJ9: =CD9*CE9*CF9*CG9*CH9*CI9 | CK9: =CJ9 | CL9: =T9 * 2 / BS9 / BT9 | CM9: =CK9/CL9 | CN9: =CK9*CC9 | CP9: =CN9*BS9*BT9 | CQ9: =CP9/T9 | CR9: =100/CP9 | CS9: =100/CQ9 | CV9: =BL9/T9 | CW9: =100/CV9 | CY9: 在低阶雇佣兵圈广泛流通的近战武器。 采用热能刀身设计，可以应对多种作战需求。 黑市上流通的多种版本蓝图使其稳定性堪忧， 各大企业均未将其纳入制式装备序列。 | DA9: =TEXTJOIN("、", TRUE, FILTER('武器技能'!B:B, '武器技能'!E:E = H9)) | DC9: 完成 | DD9: 完成
A10: AsFire | B10: 若火 | D10: =IF($A10="","","WPN"&VLOOKUP(E10,'引用数据库'!Z:AC,4,FALSE)&VLOOKUP(H10,'引用数据库'!N:P,3,FALSE)&VLOOKUP(I10,'引用数据库'!S:U,3,FALSE)&TEXT(F10,"00")) | E10: 野望 | F10: 1 | G10: =G9 | H10: 武士刀 | I10: 热能 | J10: 手动 | K10: =K9 | M10: =M9 | N10: 170 | O10: 120 | P10: =P9 | Q10: =Q9 | R10: =R9 | S10: 0 | T10: =SUM(P10:S10) | U10: =2*T10/(15*(1+(5-BD10)*0.1)) | W10: N/A | X10: N/A | Y10: N/A | Z10: N/A | AD10: N/A | AE10: N/A | AJ10: =AJ9 | AK10: 0.92 | AL10: 0.1 | AM10: =IFS(AJ10 > 1.25, "S", AJ10 > 1, "A", AJ10 > 0.75, "B", AJ10 > 0.5, "C", AJ10 > 0.25, "D", AJ10 > 0, "E", TRUE, "-") | AN10: =IFS(AK10 > 1.25, "S", AK10 > 1, "A", AK10 > 0.75, "B", AK10 > 0.5, "C", AK10 > 0.25, "D", AK10 > 0, "E", TRUE, "-") | AO10: =IFS(AL10 > 1.25, "S", AL10 > 1, "A", AL10 > 0.75, "B", AL10 > 0.5, "C", AL10 > 0.25, "D", AL10 > 0, "E", TRUE, "-") | AP10: 10 | AQ10: 10 | AR10: 10 | AV10: =IF(SUM(AJ10:AL10)=0, 0, (1 + F10 * 0.1) * (0.75 + 0.25 * MAX(0, MIN(1, IF(MAX(AJ10:AL10)=0, 0, (3*MAX(AJ10:AL10)-SUM(AJ10:AL10)) / (2*MAX(AJ10:AL10))))))) | AW10: =MAX(AJ10:AL10) | AX10: =IF(AW10=0, "", AW10 / ((1 + 0.1*N(F10)))) | AY10: =IF(SUM(AJ10:AL10)=0, 0, (1 + F10 * 0.1) * (1 + ((SUM(AJ10:AL10) - MAX(AJ10:AL10)) / (2 * MAX(AJ10:AL10))) * (1/0.75 - 1))) | AZ10: =AJ10+AK10+AL10 | BA10: =IF(AZ10=0, "", AZ10 / ((1 + 0.1*N(F10))/0.75)) | BB10: 0.1 | BD10: =BD9 | BE10: =BE9 | BH10: =BH9 | BL10: =BL9 | BN10: N/A | BO10: N/A | BQ10: =BQ9 | BR10: =IFERROR(BQ10*100/CP10,"N/A") | BS10: 1 | BT10: 1 | BW10: =BW9 | BX10: =CP10/BW10 | BY10: =BW10/T10 | CA10: =CA9+20 | CB10: =CA10*BB10*(AP10*AJ10+AQ10*AK10+AR10*AL10) | CC10: =CA10+CB10 | CK10: =CK9 | CN10: =CK10*CC10 | CP10: =CN10*BS10*BT10 | CQ10: =CP10/T10 | CR10: =100/CP10 | CS10: =100/CQ10 | CT10: =CQ10-CQ9 | CU10: =(CQ10-CQ9)/CQ9 | CV10: =BL10/T10 | CW10: =100/CV10 | DC10: 完成 | DD10: 完成
A11: AsFire | B11: 若火 | D11: =IF($A11="","","WPN"&VLOOKUP(E11,'引用数据库'!Z:AC,4,FALSE)&VLOOKUP(H11,'引用数据库'!N:P,3,FALSE)&VLOOKUP(I11,'引用数据库'!S:U,3,FALSE)&TEXT(F11,"00")) | E11: 野望 | F11: 2 | G11: =G10 | H11: 武士刀 | I11: 热能 | J11: 手动 | K11: =K10 | M11: =M10 | N11: 170 | O11: 120 | P11: =P10 | Q11: =Q10 | R11: =R10 | S11: 0 | T11: =SUM(P11:S11) | U11: =2*T11/(15*(1+(5-BD11)*0.1)) | W11: N/A | X11: N/A | Y11: N/A | Z11: N/A | AD11: N/A | AE11: N/A | AJ11: =AJ10 | AK11: =AK10+0.1 | AL11: 0.1 | AM11: =IFS(AJ11 > 1.25, "S", AJ11 > 1, "A", AJ11 > 0.75, "B", AJ11 > 0.5, "C", AJ11 > 0.25, "D", AJ11 > 0, "E", TRUE, "-") | AN11: =IFS(AK11 > 1.25, "S", AK11 > 1, "A", AK11 > 0.75, "B", AK11 > 0.5, "C", AK11 > 0.25, "D", AK11 > 0, "E", TRUE, "-") | AO11: =IFS(AL11 > 1.25, "S", AL11 > 1, "A", AL11 > 0.75, "B", AL11 > 0.5, "C", AL11 > 0.25, "D", AL11 > 0, "E", TRUE, "-") | AP11: 10 | AQ11: 10 | AR11: 10 | AV11: =IF(SUM(AJ11:AL11)=0, 0, (1 + F11 * 0.1) * (0.75 + 0.25 * MAX(0, MIN(1, IF(MAX(AJ11:AL11)=0, 0, (3*MAX(AJ11:AL11)-SUM(AJ11:AL11)) / (2*MAX(AJ11:AL11))))))) | AW11: =MAX(AJ11:AL11) | AX11: =IF(AW11=0, "", AW11 / ((1 + 0.1*N(F11)))) | AY11: =IF(SUM(AJ11:AL11)=0, 0, (1 + F11 * 0.1) * (1 + ((SUM(AJ11:AL11) - MAX(AJ11:AL11)) / (2 * MAX(AJ11:AL11))) * (1/0.75 - 1))) | AZ11: =AJ11+AK11+AL11 | BA11: =IF(AZ11=0, "", AZ11 / ((1 + 0.1*N(F11))/0.75)) | BB11: 0.1 | BD11: =BD10 | BE11: =BE10 | BH11: =BH10 | BL11: =BL10 | BN11: N/A | BO11: N/A | BQ11: =BQ10 | BR11: =IFERROR(BQ11*100/CP11,"N/A") | BS11: 1 | BT11: 1 | BW11: =BW10 | BX11: =CP11/BW11 | BY11: =BW11/T11 | CA11: =CA10+10 | CB11: =CA11*BB11*(AP11*AJ11+AQ11*AK11+AR11*AL11) | CC11: =CA11+CB11 | CK11: =CK10 | CN11: =CK11*CC11 | CP11: =CN11*BS11*BT11 | CQ11: =CP11/T11 | CR11: =100/CP11 | CS11: =100/CQ11 | CT11: =CQ11-CQ10 | CU11: =(CQ11-CQ10)/CQ10 | CV11: =BL11/T11 | CW11: =100/CV11 | DC11: 完成 | DD11: 完成
A12: AsFire | B12: 若火 | D12: =IF($A12="","","WPN"&VLOOKUP(E12,'引用数据库'!Z:AC,4,FALSE)&VLOOKUP(H12,'引用数据库'!N:P,3,FALSE)&VLOOKUP(I12,'引用数据库'!S:U,3,FALSE)&TEXT(F12,"00")) | E12: 野望 | F12: 3 | G12: =G11 | H12: 武士刀 | I12: 热能 | J12: 手动 | K12: =K11 | M12: =M11 | N12: 170 | O12: 120 | P12: =P11 | Q12: =Q11 | R12: =R11 | S12: 0 | T12: =SUM(P12:S12) | U12: =2*T12/(15*(1+(5-BD12)*0.1)) | W12: N/A | X12: N/A | Y12: N/A | Z12: N/A | AD12: N/A | AE12: N/A | AJ12: =AJ11 | AK12: =AK11+0.1 | AL12: 0.1 | AM12: =IFS(AJ12 > 1.25, "S", AJ12 > 1, "A", AJ12 > 0.75, "B", AJ12 > 0.5, "C", AJ12 > 0.25, "D", AJ12 > 0, "E", TRUE, "-") | AN12: =IFS(AK12 > 1.25, "S", AK12 > 1, "A", AK12 > 0.75, "B", AK12 > 0.5, "C", AK12 > 0.25, "D", AK12 > 0, "E", TRUE, "-") | AO12: =IFS(AL12 > 1.25, "S", AL12 > 1, "A", AL12 > 0.75, "B", AL12 > 0.5, "C", AL12 > 0.25, "D", AL12 > 0, "E", TRUE, "-") | AP12: 10 | AQ12: 10 | AR12: 10 | AV12: =IF(SUM(AJ12:AL12)=0, 0, (1 + F12 * 0.1) * (0.75 + 0.25 * MAX(0, MIN(1, IF(MAX(AJ12:AL12)=0, 0, (3*MAX(AJ12:AL12)-SUM(AJ12:AL12)) / (2*MAX(AJ12:AL12))))))) | AW12: =MAX(AJ12:AL12) | AX12: =IF(AW12=0, "", AW12 / ((1 + 0.1*N(F12)))) | AY12: =IF(SUM(AJ12:AL12)=0, 0, (1 + F12 * 0.1) * (1 + ((SUM(AJ12:AL12) - MAX(AJ12:AL12)) / (2 * MAX(AJ12:AL12))) * (1/0.75 - 1))) | AZ12: =AJ12+AK12+AL12 | BA12: =IF(AZ12=0, "", AZ12 / ((1 + 0.1*N(F12))/0.75)) | BB12: 0.1 | BD12: =BD11 | BE12: =BE11 | BH12: =BH11 | BL12: =BL11 | BN12: N/A | BO12: N/A | BQ12: =BQ11 | BR12: =IFERROR(BQ12*100/CP12,"N/A") | BS12: 1 | BT12: 1 | BW12: =BW11 | BX12: =CP12/BW12 | BY12: =BW12/T12 | CA12: =CA11+10 | CB12: =CA12*BB12*(AP12*AJ12+AQ12*AK12+AR12*AL12) | CC12: =CA12+CB12 | CK12: =CK11 | CN12: =CK12*CC12 | CP12: =CN12*BS12*BT12 | CQ12: =CP12/T12 | CR12: =100/CP12 | CS12: =100/CQ12 | CT12: =CQ12-CQ11 | CU12: =(CQ12-CQ11)/CQ11 | CV12: =BL12/T12 | CW12: =100/CV12 | DC12: 完成 | DD12: 完成
A13: AsFire | B13: 若火 | D13: =IF($A13="","","WPN"&VLOOKUP(E13,'引用数据库'!Z:AC,4,FALSE)&VLOOKUP(H13,'引用数据库'!N:P,3,FALSE)&VLOOKUP(I13,'引用数据库'!S:U,3,FALSE)&TEXT(F13,"00")) | E13: 野望 | F13: 4 | G13: =G12 | H13: 武士刀 | I13: 热能 | J13: 手动 | K13: =K12 | M13: =M12 | N13: 170 | O13: 120 | P13: =P12 | Q13: =Q12 | R13: =R12 | S13: 0 | T13: =SUM(P13:S13) | U13: =2*T13/(15*(1+(5-BD13)*0.1)) | W13: N/A | X13: N/A | Y13: N/A | Z13: N/A | AD13: N/A | AE13: N/A | AJ13: =AJ12 | AK13: 1.15 | AL13: 0.2 | AM13: =IFS(AJ13 > 1.25, "S", AJ13 > 1, "A", AJ13 > 0.75, "B", AJ13 > 0.5, "C", AJ13 > 0.25, "D", AJ13 > 0, "E", TRUE, "-") | AN13: =IFS(AK13 > 1.25, "S", AK13 > 1, "A", AK13 > 0.75, "B", AK13 > 0.5, "C", AK13 > 0.25, "D", AK13 > 0, "E", TRUE, "-") | AO13: =IFS(AL13 > 1.25, "S", AL13 > 1, "A", AL13 > 0.75, "B", AL13 > 0.5, "C", AL13 > 0.25, "D", AL13 > 0, "E", TRUE, "-") | AP13: 10 | AQ13: 10 | AR13: 10 | AV13: =IF(SUM(AJ13:AL13)=0, 0, (1 + F13 * 0.1) * (0.75 + 0.25 * MAX(0, MIN(1, IF(MAX(AJ13:AL13)=0, 0, (3*MAX(AJ13:AL13)-SUM(AJ13:AL13)) / (2*MAX(AJ13:AL13))))))) | AW13: =MAX(AJ13:AL13) | AX13: =IF(AW13=0, "", AW13 / ((1 + 0.1*N(F13)))) | AY13: =IF(SUM(AJ13:AL13)=0, 0, (1 + F13 * 0.1) * (1 + ((SUM(AJ13:AL13) - MAX(AJ13:AL13)) / (2 * MAX(AJ13:AL13))) * (1/0.75 - 1))) | AZ13: =AJ13+AK13+AL13 | BA13: =IF(AZ13=0, "", AZ13 / ((1 + 0.1*N(F13))/0.75)) | BB13: 0.1 | BD13: =BD12 | BE13: =BE12 | BH13: =BH12 | BL13: =BL12 | BN13: N/A | BO13: N/A | BQ13: =BQ12 | BR13: =IFERROR(BQ13*100/CP13,"N/A") | BS13: 1 | BT13: 1 | BW13: =BW12 | BX13: =CP13/BW13 | BY13: =BW13/T13 | CA13: =CA12+10 | CB13: =CA13*BB13*(AP13*AJ13+AQ13*AK13+AR13*AL13) | CC13: =CA13+CB13 | CK13: =CK12 | CN13: =CK13*CC13 | CP13: =CN13*BS13*BT13 | CQ13: =CP13/T13 | CR13: =100/CP13 | CS13: =100/CQ13 | CT13: =CQ13-CQ12 | CU13: =(CQ13-CQ12)/CQ12 | CV13: =BL13/T13 | CW13: =100/CV13 | DC13: 完成 | DD13: 完成
A14: AsFire | B14: 若火 | D14: =IF($A14="","","WPN"&VLOOKUP(E14,'引用数据库'!Z:AC,4,FALSE)&VLOOKUP(H14,'引用数据库'!N:P,3,FALSE)&VLOOKUP(I14,'引用数据库'!S:U,3,FALSE)&TEXT(F14,"00")) | E14: 野望 | F14: 5 | G14: =G13 | H14: 武士刀 | I14: 热能 | J14: 手动 | K14: =K13 | M14: =M13 | N14: 170 | O14: 120 | P14: =P13 | Q14: =Q13 | R14: =R13 | S14: 0 | T14: =SUM(P14:S14) | U14: =2*T14/(15*(1+(5-BD14)*0.1)) | W14: N/A | X14: N/A | Y14: N/A | Z14: N/A | AD14: N/A | AE14: N/A | AJ14: 0.2 | AK14: 1.15 | AL14: 0.25 | AM14: =IFS(AJ14 > 1.25, "S", AJ14 > 1, "A", AJ14 > 0.75, "B", AJ14 > 0.5, "C", AJ14 > 0.25, "D", AJ14 > 0, "E", TRUE, "-") | AN14: =IFS(AK14 > 1.25, "S", AK14 > 1, "A", AK14 > 0.75, "B", AK14 > 0.5, "C", AK14 > 0.25, "D", AK14 > 0, "E", TRUE, "-") | AO14: =IFS(AL14 > 1.25, "S", AL14 > 1, "A", AL14 > 0.75, "B", AL14 > 0.5, "C", AL14 > 0.25, "D", AL14 > 0, "E", TRUE, "-") | AP14: 10 | AQ14: 10 | AR14: 10 | AV14: =IF(SUM(AJ14:AL14)=0, 0, (1 + F14 * 0.1) * (0.75 + 0.25 * MAX(0, MIN(1, IF(MAX(AJ14:AL14)=0, 0, (3*MAX(AJ14:AL14)-SUM(AJ14:AL14)) / (2*MAX(AJ14:AL14))))))) | AW14: =MAX(AJ14:AL14) | AX14: =IF(AW14=0, "", AW14 / ((1 + 0.1*N(F14)))) | AY14: =IF(SUM(AJ14:AL14)=0, 0, (1 + F14 * 0.1) * (1 + ((SUM(AJ14:AL14) - MAX(AJ14:AL14)) / (2 * MAX(AJ14:AL14))) * (1/0.75 - 1))) | AZ14: =AJ14+AK14+AL14 | BA14: =IF(AZ14=0, "", AZ14 / ((1 + 0.1*N(F14))/0.75)) | BB14: 0.1 | BD14: =BD13 | BE14: =BE13 | BH14: =BH13 | BL14: =BL13 | BN14: N/A | BO14: N/A | BQ14: =BQ13 | BR14: =IFERROR(BQ14*100/CP14,"N/A") | BS14: 1 | BT14: 1 | BW14: =BW13 | BX14: =CP14/BW14 | BY14: =BW14/T14 | CA14: =CA13+10 | CB14: =CA14*BB14*(AP14*AJ14+AQ14*AK14+AR14*AL14) | CC14: =CA14+CB14 | CK14: =CK13 | CN14: =CK14*CC14 | CP14: =CN14*BS14*BT14 | CQ14: =CP14/T14 | CR14: =100/CP14 | CS14: =100/CQ14 | CT14: =CQ14-CQ13 | CU14: =(CQ14-CQ13)/CQ13 | CV14: =BL14/T14 | CW14: =100/CV14 | DC14: 完成 | DD14: 完成
A15: MagneticWrench | B15: 磁阻扳手 | D15: =IF($A15="","","WPN"&VLOOKUP(E15,'引用数据库'!Z:AC,4,FALSE)&VLOOKUP(H15,'引用数据库'!N:P,3,FALSE)&VLOOKUP(I15,'引用数据库'!S:U,3,FALSE)&TEXT(F15,"00")) | E15: 劳旅 | F15: 0 | G15: 近战 | H15: 锤 | I15: 电磁 | J15: 手动 | K15: 2 | M15: 1 | N15: 140 | O15: 90 | P15: 0.251 | Q15: 0.05 | R15: 0.299 | S15: 0 | T15: =SUM(P15:S15) | U15: =2*T15/(15*(1+(5-BD15)*0.1)) | W15: N/A | X15: N/A | Y15: N/A | Z15: N/A | AD15: N/A | AE15: N/A | AJ15: 0.64 | AK15: 0.3 | AL15: 0.2 | AM15: =IFS(AJ15 > 1.25, "S", AJ15 > 1, "A", AJ15 > 0.75, "B", AJ15 > 0.5, "C", AJ15 > 0.25, "D", AJ15 > 0, "E", TRUE, "-") | AN15: =IFS(AK15 > 1.25, "S", AK15 > 1, "A", AK15 > 0.75, "B", AK15 > 0.5, "C", AK15 > 0.25, "D", AK15 > 0, "E", TRUE, "-") | AO15: =IFS(AL15 > 1.25, "S", AL15 > 1, "A", AL15 > 0.75, "B", AL15 > 0.5, "C", AL15 > 0.25, "D", AL15 > 0, "E", TRUE, "-") | AP15: 10 | AQ15: 10 | AR15: 10 | AV15: =IF(SUM(AJ15:AL15)=0, 0, (1 + F15 * 0.1) * (0.75 + 0.25 * MAX(0, MIN(1, IF(MAX(AJ15:AL15)=0, 0, (3*MAX(AJ15:AL15)-SUM(AJ15:AL15)) / (2*MAX(AJ15:AL15))))))) | AW15: =MAX(AJ15:AL15) | AX15: =IF(AW15=0, "", AW15 / ((1 + 0.1*N(F15)))) | AY15: =IF(SUM(AJ15:AL15)=0, 0, (1 + F15 * 0.1) * (1 + ((SUM(AJ15:AL15) - MAX(AJ15:AL15)) / (2 * MAX(AJ15:AL15))) * (1/0.75 - 1))) | AZ15: =AJ15+AK15+AL15 | BA15: =IF(AZ15=0, "", AZ15 / ((1 + 0.1*N(F15))/0.75)) | BB15: 0.1 | BD15: 2 | BE15: 2 | BF15: 2 | BG15: =T15*20*(16 * BF15) / (15 + 20 * BF15 - 3 * POWER(BF15, 2))/BT15/BS15 | BH15: =BG15 | BJ15: 4 | BK15: =T15*33*(16 * BJ15) / (15 + 20 * BJ15 - 3 * POWER(BJ15, 2))/BT15/BS15 | BL15: =BK15 | BN15: N/A | BO15: N/A | BP15: 0 | BQ15: 0 | BR15: =IFERROR(BQ15*100/CP15,"N/A") | BS15: 1 | BT15: 1 | BV15: =CP15/1.5 | BW15: =ROUND(BV15) | BX15: =CP15/BW15 | BY15: =BW15/T15 | CA15: 10 | CB15: =CA15*BB15*(AP15*AJ15+AQ15*AK15+AR15*AL15) | CC15: =CA15+CB15 | CD15: =T15 * 2 / BS15 / BT15 * (0.9 + 0.2 * IF(G15="近战", EXP(-64 * (T15 - 0.75)^2), EXP(-400 * (T15 - 0.15)^2))) | CE15: =0.9 + 0.2 / (1 + (N15/600)^1) | CF15: =LET( k, K15, be, BS15, bf, BT15, m, N15, n, O15, v, X15, vEff, IF(ISNUMBER(v), v, 0), angle, IF( ISNUMBER(n), IF(n>0, n, IF(ISNUMBER(v), IF(v>0, v, 0), 0 ) ), IF(ISNUMBER(v), IF(v>0, v, 0), 0 ) ), T, IF(k=1, be * bf * 20 / MAX(vEff, 1), IF(k=2, (m/150)^2 * (angle/120), IF(k=3, be * (MIN(bf, 99)/99) * (m/1000), be * bf * (m/1000) * (n/200)^2 ))), b, 0.8, c, 1.2, r, (c-1)/(1-b), k_s, 1, b + (c-b) / (1 + r * EXP(-k_s*(1-T)))) | CG15: =IF(T15<=0,1, (0.9 + 0.2 / (1 + EXP(-0.8 * (5 - BD15)))) * (0.9 + 0.2 / (1 + EXP(-1 * (3.5 - BE15)))) * (0.9 + 0.2 / (1 + EXP(-0.6 * (20 - BS15*BH15/T15))))) | CH15: =IF(T15<=0, 1, 0.9 + 0.2 / (1 + EXP(0.1 * (BL15*BS15*BT15/T15 - 33)))) | CI15: =LET( x_val, X15, bq_val, BS15, Check_Fail, OR(NOT(ISNUMBER(x_val)), bq_val <= 1), IF(Check_Fail, 1, LET( Ratio, x_val / bq_val, calc_A, 2.5 / (1 + EXP(-0.23105 * (Ratio - 3))), calc_B, 2.5 / (1 + EXP(-0.008664 * (x_val - 20))), calc_A + calc_B ) )) | CJ15: =CD15*CE15*CF15*CG15*CH15*CI15 | CK15: =CJ15 | CL15: =T15 * 2 / BS15 / BT15 | CM15: =CK15/CL15 | CN15: =CK15*CC15 | CP15: =CN15*BS15*BT15 | CQ15: =CP15/T15 | CR15: =100/CP15 | CS15: =100/CQ15 | CV15: =BL15/T15 | CW15: =100/CV15 | CY15: 通过磁阻牵引目标，实现非接触安装的电动扳手。 能让一般工人达到接近全自动机械的装配精度， 并且在械斗中也颇为趁手。 | DA15: =TEXTJOIN("、", TRUE, FILTER('武器技能'!B:B, '武器技能'!E:E = H15)) | DC15: 完成 | DD15: 完成
A16: MagneticWrench | B16: 磁阻扳手 | D16: =IF($A16="","","WPN"&VLOOKUP(E16,'引用数据库'!Z:AC,4,FALSE)&VLOOKUP(H16,'引用数据库'!N:P,3,FALSE)&VLOOKUP(I16,'引用数据库'!S:U,3,FALSE)&TEXT(F16,"00")) | E16: 劳旅 | F16: 1 | G16: =G15 | H16: =H15 | I16: =I15 | J16: =J15 | K16: =K15 | M16: =M15 | N16: 140 | O16: =O15 | P16: =P15 | Q16: =Q15 | R16: =R15 | S16: 0 | T16: =SUM(P16:S16) | U16: =2*T16/(15*(1+(5-BD16)*0.1)) | W16: N/A | X16: N/A | Y16: N/A | Z16: N/A | AD16: N/A | AE16: N/A | AJ16: =AJ15+0.1 | AK16: =AK15 | AL16: 0.2 | AM16: =IFS(AJ16 > 1.25, "S", AJ16 > 1, "A", AJ16 > 0.75, "B", AJ16 > 0.5, "C", AJ16 > 0.25, "D", AJ16 > 0, "E", TRUE, "-") | AN16: =IFS(AK16 > 1.25, "S", AK16 > 1, "A", AK16 > 0.75, "B", AK16 > 0.5, "C", AK16 > 0.25, "D", AK16 > 0, "E", TRUE, "-") | AO16: =IFS(AL16 > 1.25, "S", AL16 > 1, "A", AL16 > 0.75, "B", AL16 > 0.5, "C", AL16 > 0.25, "D", AL16 > 0, "E", TRUE, "-") | AP16: 10 | AQ16: 10 | AR16: 10 | AV16: =IF(SUM(AJ16:AL16)=0, 0, (1 + F16 * 0.1) * (0.75 + 0.25 * MAX(0, MIN(1, IF(MAX(AJ16:AL16)=0, 0, (3*MAX(AJ16:AL16)-SUM(AJ16:AL16)) / (2*MAX(AJ16:AL16))))))) | AW16: =MAX(AJ16:AL16) | AX16: =IF(AW16=0, "", AW16 / ((1 + 0.1*N(F16)))) | AY16: =IF(SUM(AJ16:AL16)=0, 0, (1 + F16 * 0.1) * (1 + ((SUM(AJ16:AL16) - MAX(AJ16:AL16)) / (2 * MAX(AJ16:AL16))) * (1/0.75 - 1))) | AZ16: =AJ16+AK16+AL16 | BA16: =IF(AZ16=0, "", AZ16 / ((1 + 0.1*N(F16))/0.75)) | BB16: 0.1 | BD16: =BD15 | BE16: =BE15 | BH16: =BH15 | BL16: =BL15 | BN16: N/A | BO16: N/A | BQ16: =BQ15 | BR16: =IFERROR(BQ16*100/CP16,"N/A") | BS16: 1 | BT16: 1 | BW16: =BW15 | BX16: =CP16/BW16 | BY16: =BW16/T16 | CA16: =CA15+20 | CB16: =CA16*BB16*(AP16*AJ16+AQ16*AK16+AR16*AL16) | CC16: =CA16+CB16 | CK16: =CK15 | CN16: =CK16*CC16 | CP16: =CN16*BS16*BT16 | CQ16: =CP16/T16 | CR16: =100/CP16 | CS16: =100/CQ16 | CT16: =CQ16-CQ15 | CU16: =(CQ16-CQ15)/CQ15 | CV16: =BL16/T16 | CW16: =100/CV16 | DC16: 完成 | DD16: 完成
A17: MagneticWrench | B17: 磁阻扳手 | D17: =IF($A17="","","WPN"&VLOOKUP(E17,'引用数据库'!Z:AC,4,FALSE)&VLOOKUP(H17,'引用数据库'!N:P,3,FALSE)&VLOOKUP(I17,'引用数据库'!S:U,3,FALSE)&TEXT(F17,"00")) | E17: 劳旅 | F17: 2 | G17: =G16 | H17: =H16 | I17: =I16 | J17: =J16 | K17: =K16 | M17: =M16 | N17: 140 | O17: =O16 | P17: =P16 | Q17: =Q16 | R17: =R16 | S17: 0 | T17: =SUM(P17:S17) | U17: =2*T17/(15*(1+(5-BD17)*0.1)) | W17: N/A | X17: N/A | Y17: N/A | Z17: N/A | AD17: N/A | AE17: N/A | AJ17: =AJ16+0.1 | AK17: =AK16 | AL17: =AL16 | AM17: =IFS(AJ17 > 1.25, "S", AJ17 > 1, "A", AJ17 > 0.75, "B", AJ17 > 0.5, "C", AJ17 > 0.25, "D", AJ17 > 0, "E", TRUE, "-") | AN17: =IFS(AK17 > 1.25, "S", AK17 > 1, "A", AK17 > 0.75, "B", AK17 > 0.5, "C", AK17 > 0.25, "D", AK17 > 0, "E", TRUE, "-") | AO17: =IFS(AL17 > 1.25, "S", AL17 > 1, "A", AL17 > 0.75, "B", AL17 > 0.5, "C", AL17 > 0.25, "D", AL17 > 0, "E", TRUE, "-") | AP17: 10 | AQ17: 10 | AR17: 10 | AV17: =IF(SUM(AJ17:AL17)=0, 0, (1 + F17 * 0.1) * (0.75 + 0.25 * MAX(0, MIN(1, IF(MAX(AJ17:AL17)=0, 0, (3*MAX(AJ17:AL17)-SUM(AJ17:AL17)) / (2*MAX(AJ17:AL17))))))) | AW17: =MAX(AJ17:AL17) | AX17: =IF(AW17=0, "", AW17 / ((1 + 0.1*N(F17)))) | AY17: =IF(SUM(AJ17:AL17)=0, 0, (1 + F17 * 0.1) * (1 + ((SUM(AJ17:AL17) - MAX(AJ17:AL17)) / (2 * MAX(AJ17:AL17))) * (1/0.75 - 1))) | AZ17: =AJ17+AK17+AL17 | BA17: =IF(AZ17=0, "", AZ17 / ((1 + 0.1*N(F17))/0.75)) | BB17: 0.1 | BD17: =BD16 | BE17: =BE16 | BH17: =BH16 | BL17: =BL16 | BN17: N/A | BO17: N/A | BQ17: =BQ16 | BR17: =IFERROR(BQ17*100/CP17,"N/A") | BS17: 1 | BT17: 1 | BW17: =BW16 | BX17: =CP17/BW17 | BY17: =BW17/T17 | CA17: =CA16+10 | CB17: =CA17*BB17*(AP17*AJ17+AQ17*AK17+AR17*AL17) | CC17: =CA17+CB17 | CK17: =CK16 | CN17: =CK17*CC17 | CP17: =CN17*BS17*BT17 | CQ17: =CP17/T17 | CR17: =100/CP17 | CS17: =100/CQ17 | CT17: =CQ17-CQ16 | CU17: =(CQ17-CQ16)/CQ16 | CV17: =BL17/T17 | CW17: =100/CV17 | DC17: 完成 | DD17: 完成
A18: MagneticWrench | B18: 磁阻扳手 | D18: =IF($A18="","","WPN"&VLOOKUP(E18,'引用数据库'!Z:AC,4,FALSE)&VLOOKUP(H18,'引用数据库'!N:P,3,FALSE)&VLOOKUP(I18,'引用数据库'!S:U,3,FALSE)&TEXT(F18,"00")) | E18: 劳旅 | F18: 3 | G18: =G17 | H18: =H17 | I18: =I17 | J18: =J17 | K18: =K17 | M18: =M17 | N18: 140 | O18: =O17 | P18: =P17 | Q18: =Q17 | R18: =R17 | S18: 0 | T18: =SUM(P18:S18) | U18: =2*T18/(15*(1+(5-BD18)*0.1)) | W18: N/A | X18: N/A | Y18: N/A | Z18: N/A | AD18: N/A | AE18: N/A | AJ18: =AJ17+0.1 | AK18: =AK17 | AL18: =AL17 | AM18: =IFS(AJ18 > 1.25, "S", AJ18 > 1, "A", AJ18 > 0.75, "B", AJ18 > 0.5, "C", AJ18 > 0.25, "D", AJ18 > 0, "E", TRUE, "-") | AN18: =IFS(AK18 > 1.25, "S", AK18 > 1, "A", AK18 > 0.75, "B", AK18 > 0.5, "C", AK18 > 0.25, "D", AK18 > 0, "E", TRUE, "-") | AO18: =IFS(AL18 > 1.25, "S", AL18 > 1, "A", AL18 > 0.75, "B", AL18 > 0.5, "C", AL18 > 0.25, "D", AL18 > 0, "E", TRUE, "-") | AP18: 10 | AQ18: 10 | AR18: 10 | AV18: =IF(SUM(AJ18:AL18)=0, 0, (1 + F18 * 0.1) * (0.75 + 0.25 * MAX(0, MIN(1, IF(MAX(AJ18:AL18)=0, 0, (3*MAX(AJ18:AL18)-SUM(AJ18:AL18)) / (2*MAX(AJ18:AL18))))))) | AW18: =MAX(AJ18:AL18) | AX18: =IF(AW18=0, "", AW18 / ((1 + 0.1*N(F18)))) | AY18: =IF(SUM(AJ18:AL18)=0, 0, (1 + F18 * 0.1) * (1 + ((SUM(AJ18:AL18) - MAX(AJ18:AL18)) / (2 * MAX(AJ18:AL18))) * (1/0.75 - 1))) | AZ18: =AJ18+AK18+AL18 | BA18: =IF(AZ18=0, "", AZ18 / ((1 + 0.1*N(F18))/0.75)) | BB18: 0.1 | BD18: =BD17 | BE18: =BE17 | BH18: =BH17 | BL18: =BL17 | BN18: N/A | BO18: N/A | BQ18: =BQ17 | BR18: =IFERROR(BQ18*100/CP18,"N/A") | BS18: 1 | BT18: 1 | BW18: =BW17 | BX18: =CP18/BW18 | BY18: =BW18/T18 | CA18: =CA17+10 | CB18: =CA18*BB18*(AP18*AJ18+AQ18*AK18+AR18*AL18) | CC18: =CA18+CB18 | CK18: =CK17 | CN18: =CK18*CC18 | CP18: =CN18*BS18*BT18 | CQ18: =CP18/T18 | CR18: =100/CP18 | CS18: =100/CQ18 | CT18: =CQ18-CQ17 | CU18: =(CQ18-CQ17)/CQ17 | CV18: =BL18/T18 | CW18: =100/CV18 | DC18: 完成 | DD18: 完成
A19: MagneticWrench | B19: 磁阻扳手 | D19: =IF($A19="","","WPN"&VLOOKUP(E19,'引用数据库'!Z:AC,4,FALSE)&VLOOKUP(H19,'引用数据库'!N:P,3,FALSE)&VLOOKUP(I19,'引用数据库'!S:U,3,FALSE)&TEXT(F19,"00")) | E19: 劳旅 | F19: 4 | G19: =G18 | H19: =H18 | I19: =I18 | J19: =J18 | K19: =K18 | M19: =M18 | N19: 140 | O19: =O18 | P19: =P18 | Q19: =Q18 | R19: =R18 | S19: 0 | T19: =SUM(P19:S19) | U19: =2*T19/(15*(1+(5-BD19)*0.1)) | W19: N/A | X19: N/A | Y19: N/A | Z19: N/A | AD19: N/A | AE19: N/A | AJ19: =AJ18+0.1 | AK19: =AK18 | AL19: =AL18 | AM19: =IFS(AJ19 > 1.25, "S", AJ19 > 1, "A", AJ19 > 0.75, "B", AJ19 > 0.5, "C", AJ19 > 0.25, "D", AJ19 > 0, "E", TRUE, "-") | AN19: =IFS(AK19 > 1.25, "S", AK19 > 1, "A", AK19 > 0.75, "B", AK19 > 0.5, "C", AK19 > 0.25, "D", AK19 > 0, "E", TRUE, "-") | AO19: =IFS(AL19 > 1.25, "S", AL19 > 1, "A", AL19 > 0.75, "B", AL19 > 0.5, "C", AL19 > 0.25, "D", AL19 > 0, "E", TRUE, "-") | AP19: 10 | AQ19: 10 | AR19: 10 | AV19: =IF(SUM(AJ19:AL19)=0, 0, (1 + F19 * 0.1) * (0.75 + 0.25 * MAX(0, MIN(1, IF(MAX(AJ19:AL19)=0, 0, (3*MAX(AJ19:AL19)-SUM(AJ19:AL19)) / (2*MAX(AJ19:AL19))))))) | AW19: =MAX(AJ19:AL19) | AX19: =IF(AW19=0, "", AW19 / ((1 + 0.1*N(F19)))) | AY19: =IF(SUM(AJ19:AL19)=0, 0, (1 + F19 * 0.1) * (1 + ((SUM(AJ19:AL19) - MAX(AJ19:AL19)) / (2 * MAX(AJ19:AL19))) * (1/0.75 - 1))) | AZ19: =AJ19+AK19+AL19 | BA19: =IF(AZ19=0, "", AZ19 / ((1 + 0.1*N(F19))/0.75)) | BB19: 0.1 | BD19: =BD18 | BE19: =BE18 | BH19: =BH18 | BL19: =BL18 | BN19: N/A | BO19: N/A | BQ19: =BQ18 | BR19: =IFERROR(BQ19*100/CP19,"N/A") | BS19: 1 | BT19: 1 | BW19: =BW18 | BX19: =CP19/BW19 | BY19: =BW19/T19 | CA19: =CA18+10 | CB19: =CA19*BB19*(AP19*AJ19+AQ19*AK19+AR19*AL19) | CC19: =CA19+CB19 | CK19: =CK18 | CN19: =CK19*CC19 | CP19: =CN19*BS19*BT19 | CQ19: =CP19/T19 | CR19: =100/CP19 | CS19: =100/CQ19 | CT19: =CQ19-CQ18 | CU19: =(CQ19-CQ18)/CQ18 | CV19: =BL19/T19 | CW19: =100/CV19 | DC19: 完成 | DD19: 完成
A20: MagneticWrench | B20: 磁阻扳手 | D20: =IF($A20="","","WPN"&VLOOKUP(E20,'引用数据库'!Z:AC,4,FALSE)&VLOOKUP(H20,'引用数据库'!N:P,3,FALSE)&VLOOKUP(I20,'引用数据库'!S:U,3,FALSE)&TEXT(F20,"00")) | E20: 劳旅 | F20: 5 | G20: =G19 | H20: =H19 | I20: =I19 | J20: =J19 | K20: =K19 | M20: =M19 | N20: 140 | O20: =O19 | P20: =P19 | Q20: =Q19 | R20: =R19 | S20: 0 | T20: =SUM(P20:S20) | U20: =2*T20/(15*(1+(5-BD20)*0.1)) | W20: N/A | X20: N/A | Y20: N/A | Z20: N/A | AD20: N/A | AE20: N/A | AJ20: =AJ19+0.1 | AK20: =AK19 | AL20: =AL19 | AM20: =IFS(AJ20 > 1.25, "S", AJ20 > 1, "A", AJ20 > 0.75, "B", AJ20 > 0.5, "C", AJ20 > 0.25, "D", AJ20 > 0, "E", TRUE, "-") | AN20: =IFS(AK20 > 1.25, "S", AK20 > 1, "A", AK20 > 0.75, "B", AK20 > 0.5, "C", AK20 > 0.25, "D", AK20 > 0, "E", TRUE, "-") | AO20: =IFS(AL20 > 1.25, "S", AL20 > 1, "A", AL20 > 0.75, "B", AL20 > 0.5, "C", AL20 > 0.25, "D", AL20 > 0, "E", TRUE, "-") | AP20: 10 | AQ20: 10 | AR20: 10 | AV20: =IF(SUM(AJ20:AL20)=0, 0, (1 + F20 * 0.1) * (0.75 + 0.25 * MAX(0, MIN(1, IF(MAX(AJ20:AL20)=0, 0, (3*MAX(AJ20:AL20)-SUM(AJ20:AL20)) / (2*MAX(AJ20:AL20))))))) | AW20: =MAX(AJ20:AL20) | AX20: =IF(AW20=0, "", AW20 / ((1 + 0.1*N(F20)))) | AY20: =IF(SUM(AJ20:AL20)=0, 0, (1 + F20 * 0.1) * (1 + ((SUM(AJ20:AL20) - MAX(AJ20:AL20)) / (2 * MAX(AJ20:AL20))) * (1/0.75 - 1))) | AZ20: =AJ20+AK20+AL20 | BA20: =IF(AZ20=0, "", AZ20 / ((1 + 0.1*N(F20))/0.75)) | BB20: 0.1 | BD20: =BD19 | BE20: =BE19 | BH20: =BH19 | BL20: =BL19 | BN20: N/A | BO20: N/A | BQ20: =BQ19 | BR20: =IFERROR(BQ20*100/CP20,"N/A") | BS20: 1 | BT20: 1 | BW20: =BW19 | BX20: =CP20/BW20 | BY20: =BW20/T20 | CA20: =CA19+10 | CB20: =CA20*BB20*(AP20*AJ20+AQ20*AK20+AR20*AL20) | CC20: =CA20+CB20 | CK20: =CK19 | CN20: =CK20*CC20 | CP20: =CN20*BS20*BT20 | CQ20: =CP20/T20 | CR20: =100/CP20 | CS20: =100/CQ20 | CT20: =CQ20-CQ19 | CU20: =(CQ20-CQ19)/CQ19 | CV20: =BL20/T20 | CW20: =100/CV20 | DC20: 完成 | DD20: 完成
A21: AR47 | B21: AR47 | D21: =IF($A21="","","WPN"&VLOOKUP(E21,'引用数据库'!Z:AC,4,FALSE)&VLOOKUP(H21,'引用数据库'!N:P,3,FALSE)&VLOOKUP(I21,'引用数据库'!S:U,3,FALSE)&TEXT(F21,"00")) | E21: 纪念碑 | F21: 0 | G21: 远程 | H21: 步枪 | I21: 动能 | J21: 自动 | K21: 1 | M21: =0.4 + (T21 / (T21 + 0.2)) * 0.4 | N21: 1400 | O21: N/A | P21: 0 | Q21: 0 | R21: 0.15 | S21: 0 | T21: 0.15 | U21: =2*T21/(15*(1+(5-BD21)*0.1)) | W21: 0 | X21: 12 | Y21: 0.05 | Z21: 0.2 | AA21: 0.5 | AB21: 5 | AC21: 1.5 | AD21: =(W21+AB21)*AC21 | AE21: =(X21+AB21)*AC21 | AJ21: 0.44 | AK21: 0.44 | AL21: 0.44 | AM21: =IFS(AJ21 > 1.25, "S", AJ21 > 1, "A", AJ21 > 0.75, "B", AJ21 > 0.5, "C", AJ21 > 0.25, "D", AJ21 > 0, "E", TRUE, "-") | AN21: =IFS(AK21 > 1.25, "S", AK21 > 1, "A", AK21 > 0.75, "B", AK21 > 0.5, "C", AK21 > 0.25, "D", AK21 > 0, "E", TRUE, "-") | AO21: =IFS(AL21 > 1.25, "S", AL21 > 1, "A", AL21 > 0.75, "B", AL21 > 0.5, "C", AL21 > 0.25, "D", AL21 > 0, "E", TRUE, "-") | AP21: 10 | AQ21: 10 | AR21: 10 | AV21: =IF(SUM(AJ21:AL21)=0, 0, (1 + F21 * 0.1) * (0.75 + 0.25 * MAX(0, MIN(1, IF(MAX(AJ21:AL21)=0, 0, (3*MAX(AJ21:AL21)-SUM(AJ21:AL21)) / (2*MAX(AJ21:AL21))))))) | AW21: =MAX(AJ21:AL21) | AX21: =IF(AW21=0, "", AW21 / ((1 + 0.1*N(F21)))) | AY21: =IF(SUM(AJ21:AL21)=0, 0, (1 + F21 * 0.1) * (1 + ((SUM(AJ21:AL21) - MAX(AJ21:AL21)) / (2 * MAX(AJ21:AL21))) * (1/0.75 - 1))) | AZ21: =AJ21+AK21+AL21 | BA21: =IF(AZ21=0, "", AZ21 / ((1 + 0.1*N(F21))/0.75)) | BB21: 0.1 | BD21: 2 | BE21: 1 | BF21: 2 | BG21: =T21*20*(16 * BF21) / (15 + 20 * BF21 - 3 * POWER(BF21, 2))/BT21/BS21 | BH21: =BG21 | BJ21: 2 | BK21: =T21*33*(16 * BJ21) / (15 + 20 * BJ21 - 3 * POWER(BJ21, 2))/BT21/BS21 | BL21: =BK21 | BN21: 30 | BO21: 2.5 | BP21: =ROUND(CP21/10,2) | BQ21: 0.5 | BR21: =IFERROR(BQ21*100/CP21,"N/A") | BS21: 1 | BT21: 1 | BV21: =CP21/1.5 | BW21: =ROUND(BV21) | BX21: =CP21/BW21 | BY21: =BW21/T21 | CA21: 10 | CB21: =CA21*BB21*(AP21*AJ21+AQ21*AK21+AR21*AL21) | CC21: =CA21+CB21 | CD21: =T21 * 2 / BS21 / BT21 * (0.9 + 0.2 * IF(G21="近战", EXP(-64 * (T21 - 0.75)^2), EXP(-400 * (T21 - 0.15)^2))) | CE21: =0.9 + 0.2 / (1 + (N21/600)^1) | CF21: =LET( k, K21, be, BS21, bf, BT21, m, N21, n, O21, v, X21, vEff, IF(ISNUMBER(v), v, 0), angle, IF( ISNUMBER(n), IF(n>0, n, IF(ISNUMBER(v), IF(v>0, v, 0), 0 ) ), IF(ISNUMBER(v), IF(v>0, v, 0), 0 ) ), T, IF(k=1, be * bf * 20 / MAX(vEff, 1), IF(k=2, (m/150)^2 * (angle/120), IF(k=3, be * (MIN(bf, 99)/99) * (m/1000), be * bf * (m/1000) * (n/200)^2 ))), b, 0.8, c, 1.2, r, (c-1)/(1-b), k_s, 1, b + (c-b) / (1 + r * EXP(-k_s*(1-T)))) | CG21: =IF(T21<=0,1, (0.9 + 0.2 / (1 + EXP(-0.8 * (5 - BD21)))) * (0.9 + 0.2 / (1 + EXP(-1 * (3.5 - BE21)))) * (0.9 + 0.2 / (1 + EXP(-0.6 * (20 - BS21*BH21/T21))))) | CH21: =IF(T21<=0, 1, 0.9 + 0.2 / (1 + EXP(0.1 * (BL21*BS21*BT21/T21 - 33)))) | CI21: =LET( x_val, X21, bq_val, BS21, Check_Fail, OR(NOT(ISNUMBER(x_val)), bq_val <= 1), IF(Check_Fail, 1, LET( Ratio, x_val / bq_val, calc_A, 2.5 / (1 + EXP(-0.23105 * (Ratio - 3))), calc_B, 2.5 / (1 + EXP(-0.008664 * (x_val - 20))), calc_A + calc_B ) )) | CJ21: =CD21*CE21*CF21*CG21*CH21*CI21 | CK21: 0.3 | CL21: =T21 * 2 / BS21 / BT21 | CM21: =CK21/CL21 | CN21: =CK21*CC21 | CP21: =CN21*BS21*BT21 | CQ21: =CP21/T21 | CR21: =100/CP21 | CS21: =100/CQ21 | CV21: =BL21/T21 | CW21: =100/CV21 | CY21: 结合了人类历史上最经典的两款武器设计， 制作而成的制式步枪，性能设计得非常平衡。 若企业未为武装雇员配发此装备， 不少人也会自行购入并按规定登记使用。 | DA21: =TEXTJOIN("、", TRUE, FILTER('武器技能'!B:B, '武器技能'!E:E = H21)) | DC21: 完成 | DD21: 完成
A22: AR47 | B22: AR47 | D22: =IF($A22="","","WPN"&VLOOKUP(E22,'引用数据库'!Z:AC,4,FALSE)&VLOOKUP(H22,'引用数据库'!N:P,3,FALSE)&VLOOKUP(I22,'引用数据库'!S:U,3,FALSE)&TEXT(F22,"00")) | E22: 纪念碑 | F22: 1 | G22: =G21 | H22: =H21 | I22: =I21 | J22: 自动 | K22: =K21 | M22: =M21 | N22: 1400 | O22: N/A | P22: 0 | Q22: 0 | R22: 0.15 | S22: 0 | T22: =SUM(P22:S22) | U22: =2*T22/(15*(1+(5-BD22)*0.1)) | W22: =W21 | X22: =X21 | Y22: =Y21 | Z22: =Z21 | AA22: =AA21 | AB22: =AB21 | AC22: =AC21 | AD22: =AD21 | AE22: =AE21 | AJ22: =AJ21+0.05 | AK22: =AK21+0.05 | AL22: =AL21+0.05 | AM22: =IFS(AJ22 > 1.25, "S", AJ22 > 1, "A", AJ22 > 0.75, "B", AJ22 > 0.5, "C", AJ22 > 0.25, "D", AJ22 > 0, "E", TRUE, "-") | AN22: =IFS(AK22 > 1.25, "S", AK22 > 1, "A", AK22 > 0.75, "B", AK22 > 0.5, "C", AK22 > 0.25, "D", AK22 > 0, "E", TRUE, "-") | AO22: =IFS(AL22 > 1.25, "S", AL22 > 1, "A", AL22 > 0.75, "B", AL22 > 0.5, "C", AL22 > 0.25, "D", AL22 > 0, "E", TRUE, "-") | AP22: 10 | AQ22: 10 | AR22: 10 | AV22: =IF(SUM(AJ22:AL22)=0, 0, (1 + F22 * 0.1) * (0.75 + 0.25 * MAX(0, MIN(1, IF(MAX(AJ22:AL22)=0, 0, (3*MAX(AJ22:AL22)-SUM(AJ22:AL22)) / (2*MAX(AJ22:AL22))))))) | AW22: =MAX(AJ22:AL22) | AX22: =IF(AW22=0, "", AW22 / ((1 + 0.1*N(F22)))) | AY22: =IF(SUM(AJ22:AL22)=0, 0, (1 + F22 * 0.1) * (1 + ((SUM(AJ22:AL22) - MAX(AJ22:AL22)) / (2 * MAX(AJ22:AL22))) * (1/0.75 - 1))) | AZ22: =AJ22+AK22+AL22 | BA22: =IF(AZ22=0, "", AZ22 / ((1 + 0.1*N(F22))/0.75)) | BB22: 0.1 | BD22: =BD21 | BE22: =BE21 | BH22: =BH21 | BL22: =BL21 | BN22: 30 | BO22: 2.5 | BQ22: =BQ21 | BR22: =IFERROR(BQ22*100/CP22,"N/A") | BS22: 1 | BT22: 1 | BW22: =BW21 | BX22: =CP22/BW22 | BY22: =BW22/T22 | CA22: =CA21+20 | CB22: =CA22*BB22*(AP22*AJ22+AQ22*AK22+AR22*AL22) | CC22: =CA22+CB22 | CK22: =CK21 | CN22: =CK22*CC22 | CP22: =CN22*BS22*BT22 | CQ22: =CP22/T22 | CR22: =100/CP22 | CS22: =100/CQ22 | CT22: =CQ22-CQ21 | CU22: =(CQ22-CQ21)/CQ21 | CV22: =BL22/T22 | CW22: =100/CV22 | DC22: 完成 | DD22: 完成
A23: AR47 | B23: AR47 | D23: =IF($A23="","","WPN"&VLOOKUP(E23,'引用数据库'!Z:AC,4,FALSE)&VLOOKUP(H23,'引用数据库'!N:P,3,FALSE)&VLOOKUP(I23,'引用数据库'!S:U,3,FALSE)&TEXT(F23,"00")) | E23: 纪念碑 | F23: 2 | G23: =G22 | H23: =H22 | I23: =I22 | J23: 自动 | K23: =K22 | M23: =M22 | N23: 1400 | O23: N/A | P23: 0 | Q23: 0 | R23: 0.15 | S23: 0 | T23: =SUM(P23:S23) | U23: =2*T23/(15*(1+(5-BD23)*0.1)) | W23: =W22 | X23: =X22 | Y23: =Y22 | Z23: =Z22 | AA23: =AA22 | AB23: =AB22 | AC23: =AC22 | AD23: =AD22 | AE23: =AE22 | AJ23: 0.53 | AK23: 0.53 | AL23: 0.53 | AM23: =IFS(AJ23 > 1.25, "S", AJ23 > 1, "A", AJ23 > 0.75, "B", AJ23 > 0.5, "C", AJ23 > 0.25, "D", AJ23 > 0, "E", TRUE, "-") | AN23: =IFS(AK23 > 1.25, "S", AK23 > 1, "A", AK23 > 0.75, "B", AK23 > 0.5, "C", AK23 > 0.25, "D", AK23 > 0, "E", TRUE, "-") | AO23: =IFS(AL23 > 1.25, "S", AL23 > 1, "A", AL23 > 0.75, "B", AL23 > 0.5, "C", AL23 > 0.25, "D", AL23 > 0, "E", TRUE, "-") | AP23: 10 | AQ23: 10 | AR23: 10 | AV23: =IF(SUM(AJ23:AL23)=0, 0, (1 + F23 * 0.1) * (0.75 + 0.25 * MAX(0, MIN(1, IF(MAX(AJ23:AL23)=0, 0, (3*MAX(AJ23:AL23)-SUM(AJ23:AL23)) / (2*MAX(AJ23:AL23))))))) | AW23: =MAX(AJ23:AL23) | AX23: =IF(AW23=0, "", AW23 / ((1 + 0.1*N(F23)))) | AY23: =IF(SUM(AJ23:AL23)=0, 0, (1 + F23 * 0.1) * (1 + ((SUM(AJ23:AL23) - MAX(AJ23:AL23)) / (2 * MAX(AJ23:AL23))) * (1/0.75 - 1))) | AZ23: =AJ23+AK23+AL23 | BA23: =IF(AZ23=0, "", AZ23 / ((1 + 0.1*N(F23))/0.75)) | BB23: 0.1 | BD23: =BD22 | BE23: =BE22 | BH23: =BH22 | BL23: =BL22 | BN23: 30 | BO23: 2.5 | BQ23: =BQ22 | BR23: =IFERROR(BQ23*100/CP23,"N/A") | BS23: 1 | BT23: 1 | BW23: =BW22 | BX23: =CP23/BW23 | BY23: =BW23/T23 | CA23: =CA22+10 | CB23: =CA23*BB23*(AP23*AJ23+AQ23*AK23+AR23*AL23) | CC23: =CA23+CB23 | CK23: =CK22 | CN23: =CK23*CC23 | CP23: =CN23*BS23*BT23 | CQ23: =CP23/T23 | CR23: =100/CP23 | CS23: =100/CQ23 | CT23: =CQ23-CQ22 | CU23: =(CQ23-CQ22)/CQ22 | CV23: =BL23/T23 | CW23: =100/CV23 | DC23: 完成 | DD23: 完成
A24: AR47 | B24: AR47 | D24: =IF($A24="","","WPN"&VLOOKUP(E24,'引用数据库'!Z:AC,4,FALSE)&VLOOKUP(H24,'引用数据库'!N:P,3,FALSE)&VLOOKUP(I24,'引用数据库'!S:U,3,FALSE)&TEXT(F24,"00")) | E24: 纪念碑 | F24: 3 | G24: =G23 | H24: =H23 | I24: =I23 | J24: 自动 | K24: =K23 | M24: =M23 | N24: 1400 | O24: N/A | P24: 0 | Q24: 0 | R24: 0.15 | S24: 0 | T24: =SUM(P24:S24) | U24: =2*T24/(15*(1+(5-BD24)*0.1)) | W24: =W23 | X24: =X23 | Y24: =Y23 | Z24: =Z23 | AA24: =AA23 | AB24: =AB23 | AC24: =AC23 | AD24: =AD23 | AE24: =AE23 | AJ24: =AJ23+0.05 | AK24: =AK23+0.05 | AL24: =AL23+0.05 | AM24: =IFS(AJ24 > 1.25, "S", AJ24 > 1, "A", AJ24 > 0.75, "B", AJ24 > 0.5, "C", AJ24 > 0.25, "D", AJ24 > 0, "E", TRUE, "-") | AN24: =IFS(AK24 > 1.25, "S", AK24 > 1, "A", AK24 > 0.75, "B", AK24 > 0.5, "C", AK24 > 0.25, "D", AK24 > 0, "E", TRUE, "-") | AO24: =IFS(AL24 > 1.25, "S", AL24 > 1, "A", AL24 > 0.75, "B", AL24 > 0.5, "C", AL24 > 0.25, "D", AL24 > 0, "E", TRUE, "-") | AP24: 10 | AQ24: 10 | AR24: 10 | AV24: =IF(SUM(AJ24:AL24)=0, 0, (1 + F24 * 0.1) * (0.75 + 0.25 * MAX(0, MIN(1, IF(MAX(AJ24:AL24)=0, 0, (3*MAX(AJ24:AL24)-SUM(AJ24:AL24)) / (2*MAX(AJ24:AL24))))))) | AW24: =MAX(AJ24:AL24) | AX24: =IF(AW24=0, "", AW24 / ((1 + 0.1*N(F24)))) | AY24: =IF(SUM(AJ24:AL24)=0, 0, (1 + F24 * 0.1) * (1 + ((SUM(AJ24:AL24) - MAX(AJ24:AL24)) / (2 * MAX(AJ24:AL24))) * (1/0.75 - 1))) | AZ24: =AJ24+AK24+AL24 | BA24: =IF(AZ24=0, "", AZ24 / ((1 + 0.1*N(F24))/0.75)) | BB24: 0.1 | BD24: =BD23 | BE24: =BE23 | BH24: =BH23 | BL24: =BL23 | BN24: 30 | BO24: 2.5 | BQ24: =BQ23 | BR24: =IFERROR(BQ24*100/CP24,"N/A") | BS24: 1 | BT24: 1 | BW24: =BW23 | BX24: =CP24/BW24 | BY24: =BW24/T24 | CA24: =CA23+10 | CB24: =CA24*BB24*(AP24*AJ24+AQ24*AK24+AR24*AL24) | CC24: =CA24+CB24 | CK24: =CK23 | CN24: =CK24*CC24 | CP24: =CN24*BS24*BT24 | CQ24: =CP24/T24 | CR24: =100/CP24 | CS24: =100/CQ24 | CT24: =CQ24-CQ23 | CU24: =(CQ24-CQ23)/CQ23 | CV24: =BL24/T24 | CW24: =100/CV24 | DC24: 完成 | DD24: 完成
A25: AR47 | B25: AR47 | D25: =IF($A25="","","WPN"&VLOOKUP(E25,'引用数据库'!Z:AC,4,FALSE)&VLOOKUP(H25,'引用数据库'!N:P,3,FALSE)&VLOOKUP(I25,'引用数据库'!S:U,3,FALSE)&TEXT(F25,"00")) | E25: 纪念碑 | F25: 4 | G25: =G24 | H25: =H24 | I25: =I24 | J25: 自动 | K25: =K24 | M25: =M24 | N25: 1400 | O25: N/A | P25: 0 | Q25: 0 | R25: 0.15 | S25: 0 | T25: =SUM(P25:S25) | U25: =2*T25/(15*(1+(5-BD25)*0.1)) | W25: =W24 | X25: =X24 | Y25: =Y24 | Z25: =Z24 | AA25: =AA24 | AB25: =AB24 | AC25: =AC24 | AD25: =AD24 | AE25: =AE24 | AJ25: =AJ24+0.05 | AK25: =AK24+0.05 | AL25: =AL24+0.05 | AM25: =IFS(AJ25 > 1.25, "S", AJ25 > 1, "A", AJ25 > 0.75, "B", AJ25 > 0.5, "C", AJ25 > 0.25, "D", AJ25 > 0, "E", TRUE, "-") | AN25: =IFS(AK25 > 1.25, "S", AK25 > 1, "A", AK25 > 0.75, "B", AK25 > 0.5, "C", AK25 > 0.25, "D", AK25 > 0, "E", TRUE, "-") | AO25: =IFS(AL25 > 1.25, "S", AL25 > 1, "A", AL25 > 0.75, "B", AL25 > 0.5, "C", AL25 > 0.25, "D", AL25 > 0, "E", TRUE, "-") | AP25: 10 | AQ25: 10 | AR25: 10 | AV25: =IF(SUM(AJ25:AL25)=0, 0, (1 + F25 * 0.1) * (0.75 + 0.25 * MAX(0, MIN(1, IF(MAX(AJ25:AL25)=0, 0, (3*MAX(AJ25:AL25)-SUM(AJ25:AL25)) / (2*MAX(AJ25:AL25))))))) | AW25: =MAX(AJ25:AL25) | AX25: =IF(AW25=0, "", AW25 / ((1 + 0.1*N(F25)))) | AY25: =IF(SUM(AJ25:AL25)=0, 0, (1 + F25 * 0.1) * (1 + ((SUM(AJ25:AL25) - MAX(AJ25:AL25)) / (2 * MAX(AJ25:AL25))) * (1/0.75 - 1))) | AZ25: =AJ25+AK25+AL25 | BA25: =IF(AZ25=0, "", AZ25 / ((1 + 0.1*N(F25))/0.75)) | BB25: 0.1 | BD25: =BD24 | BE25: =BE24 | BH25: =BH24 | BL25: =BL24 | BN25: 30 | BO25: 2.5 | BQ25: =BQ24 | BR25: =IFERROR(BQ25*100/CP25,"N/A") | BS25: 1 | BT25: 1 | BW25: =BW24 | BX25: =CP25/BW25 | BY25: =BW25/T25 | CA25: =CA24+10 | CB25: =CA25*BB25*(AP25*AJ25+AQ25*AK25+AR25*AL25) | CC25: =CA25+CB25 | CK25: =CK24 | CN25: =CK25*CC25 | CP25: =CN25*BS25*BT25 | CQ25: =CP25/T25 | CR25: =100/CP25 | CS25: =100/CQ25 | CT25: =CQ25-CQ24 | CU25: =(CQ25-CQ24)/CQ24 | CV25: =BL25/T25 | CW25: =100/CV25 | DC25: 完成 | DD25: 完成
A26: AR47 | B26: AR47 | D26: =IF($A26="","","WPN"&VLOOKUP(E26,'引用数据库'!Z:AC,4,FALSE)&VLOOKUP(H26,'引用数据库'!N:P,3,FALSE)&VLOOKUP(I26,'引用数据库'!S:U,3,FALSE)&TEXT(F26,"00")) | E26: 纪念碑 | F26: 5 | G26: =G25 | H26: =H25 | I26: =I25 | J26: 自动 | K26: =K25 | M26: =M25 | N26: 1400 | O26: N/A | P26: 0 | Q26: 0 | R26: 0.15 | S26: 0 | T26: =SUM(P26:S26) | U26: =2*T26/(15*(1+(5-BD26)*0.1)) | W26: =W25 | X26: =X25 | Y26: =Y25 | Z26: =Z25 | AA26: =AA25 | AB26: =AB25 | AC26: =AC25 | AD26: =AD25 | AE26: =AE25 | AJ26: 0.66 | AK26: 0.67 | AL26: 0.67 | AM26: =IFS(AJ26 > 1.25, "S", AJ26 > 1, "A", AJ26 > 0.75, "B", AJ26 > 0.5, "C", AJ26 > 0.25, "D", AJ26 > 0, "E", TRUE, "-") | AN26: =IFS(AK26 > 1.25, "S", AK26 > 1, "A", AK26 > 0.75, "B", AK26 > 0.5, "C", AK26 > 0.25, "D", AK26 > 0, "E", TRUE, "-") | AO26: =IFS(AL26 > 1.25, "S", AL26 > 1, "A", AL26 > 0.75, "B", AL26 > 0.5, "C", AL26 > 0.25, "D", AL26 > 0, "E", TRUE, "-") | AP26: 10 | AQ26: 10 | AR26: 10 | AV26: =IF(SUM(AJ26:AL26)=0, 0, (1 + F26 * 0.1) * (0.75 + 0.25 * MAX(0, MIN(1, IF(MAX(AJ26:AL26)=0, 0, (3*MAX(AJ26:AL26)-SUM(AJ26:AL26)) / (2*MAX(AJ26:AL26))))))) | AW26: =MAX(AJ26:AL26) | AX26: =IF(AW26=0, "", AW26 / ((1 + 0.1*N(F26)))) | AY26: =IF(SUM(AJ26:AL26)=0, 0, (1 + F26 * 0.1) * (1 + ((SUM(AJ26:AL26) - MAX(AJ26:AL26)) / (2 * MAX(AJ26:AL26))) * (1/0.75 - 1))) | AZ26: =AJ26+AK26+AL26 | BA26: =IF(AZ26=0, "", AZ26 / ((1 + 0.1*N(F26))/0.75)) | BB26: 0.1 | BD26: =BD25 | BE26: =BE25 | BH26: =BH25 | BL26: =BL25 | BN26: 30 | BO26: 2.5 | BQ26: =BQ25 | BR26: =IFERROR(BQ26*100/CP26,"N/A") | BS26: 1 | BT26: 1 | BW26: =BW25 | BX26: =CP26/BW26 | BY26: =BW26/T26 | CA26: =CA25+10 | CB26: =CA26*BB26*(AP26*AJ26+AQ26*AK26+AR26*AL26) | CC26: =CA26+CB26 | CK26: =CK25 | CN26: =CK26*CC26 | CP26: =CN26*BS26*BT26 | CQ26: =CP26/T26 | CR26: =100/CP26 | CS26: =100/CQ26 | CT26: =CQ26-CQ25 | CU26: =(CQ26-CQ25)/CQ25 | CV26: =BL26/T26 | CW26: =100/CV26 | DC26: 完成 | DD26: 完成
A27: SpitFire | B27: 火舌 | D27: =IF($A27="","","WPN"&VLOOKUP(E27,'引用数据库'!Z:AC,4,FALSE)&VLOOKUP(H27,'引用数据库'!N:P,3,FALSE)&VLOOKUP(I27,'引用数据库'!S:U,3,FALSE)&TEXT(F27,"00")) | E27: 野望 | F27: 0 | G27: 远程 | H27: 冲锋枪 | I27: 热能 | J27: 自动 | K27: 1 | M27: =0.4 + (T27 / (T27 + 0.2)) * 0.4 | N27: 1000 | O27: N/A | P27: 0 | Q27: 0 | R27: 0.08 | S27: 0 | T27: =SUM(P27:S27) | U27: =2*T27/(15*(1+(5-BD27)*0.1)) | W27: 2 | X27: 20 | Y27: 0.03 | Z27: 0.125 | AA27: 0.5 | AB27: 0 | AC27: 1.2 | AD27: =(W27+AB27)*AC27 | AE27: =(X27+AB27)*AC27 | AJ27: 0.5 | AK27: 0.6 | AL27: 0 | AM27: =IFS(AJ27 > 1.25, "S", AJ27 > 1, "A", AJ27 > 0.75, "B", AJ27 > 0.5, "C", AJ27 > 0.25, "D", AJ27 > 0, "E", TRUE, "-") | AN27: =IFS(AK27 > 1.25, "S", AK27 > 1, "A", AK27 > 0.75, "B", AK27 > 0.5, "C", AK27 > 0.25, "D", AK27 > 0, "E", TRUE, "-") | AO27: =IFS(AL27 > 1.25, "S", AL27 > 1, "A", AL27 > 0.75, "B", AL27 > 0.5, "C", AL27 > 0.25, "D", AL27 > 0, "E", TRUE, "-") | AP27: 10 | AQ27: 10 | AR27: 10 | AV27: =IF(SUM(AJ27:AL27)=0, 0, (1 + F27 * 0.1) * (0.75 + 0.25 * MAX(0, MIN(1, IF(MAX(AJ27:AL27)=0, 0, (3*MAX(AJ27:AL27)-SUM(AJ27:AL27)) / (2*MAX(AJ27:AL27))))))) | AW27: =MAX(AJ27:AL27) | AX27: =IF(AW27=0, "", AW27 / ((1 + 0.1*N(F27)))) | AY27: =IF(SUM(AJ27:AL27)=0, 0, (1 + F27 * 0.1) * (1 + ((SUM(AJ27:AL27) - MAX(AJ27:AL27)) / (2 * MAX(AJ27:AL27))) * (1/0.75 - 1))) | AZ27: =AJ27+AK27+AL27 | BA27: =IF(AZ27=0, "", AZ27 / ((1 + 0.1*N(F27))/0.75)) | BB27: 0.1 | BD27: 1 | BE27: 1 | BF27: 1 | BG27: =T27*20*(16 * BF27) / (15 + 20 * BF27 - 3 * POWER(BF27, 2))/BT27/BS27 | BH27: =BG27 | BJ27: 5 | BK27: =T27*33*(16 * BJ27) / (15 + 20 * BJ27 - 3 * POWER(BJ27, 2))/BT27/BS27 | BL27: =BK27 | BN27: 45 | BO27: 2 | BP27: =ROUND(CP27/10,2) | BQ27: 0.2 | BR27: =IFERROR(BQ27*100/CP27,"N/A") | BS27: 1 | BT27: 1 | BV27: =CP27/1.5 | BW27: =ROUND(BV27) | BX27: =CP27/BW27 | BY27: =BW27/T27 | CA27: 10 | CB27: =CA27*BB27*(AP27*AJ27+AQ27*AK27+AR27*AL27) | CC27: =CA27+CB27 | CD27: =T27 * 2 / BS27 / BT27 * (0.9 + 0.2 * IF(G27="近战", EXP(-64 * (T27 - 0.75)^2), EXP(-400 * (T27 - 0.15)^2))) | CE27: =0.9 + 0.2 / (1 + (N27/600)^1) | CF27: =LET( k, K27, be, BS27, bf, BT27, m, N27, n, O27, v, X27, vEff, IF(ISNUMBER(v), v, 0), angle, IF( ISNUMBER(n), IF(n>0, n, IF(ISNUMBER(v), IF(v>0, v, 0), 0 ) ), IF(ISNUMBER(v), IF(v>0, v, 0), 0 ) ), T, IF(k=1, be * bf * 20 / MAX(vEff, 1), IF(k=2, (m/150)^2 * (angle/120), IF(k=3, be * (MIN(bf, 99)/99) * (m/1000), be * bf * (m/1000) * (n/200)^2 ))), b, 0.8, c, 1.2, r, (c-1)/(1-b), k_s, 1, b + (c-b) / (1 + r * EXP(-k_s*(1-T)))) | CG27: =IF(T27<=0,1, (0.9 + 0.2 / (1 + EXP(-0.8 * (5 - BD27)))) * (0.9 + 0.2 / (1 + EXP(-1 * (3.5 - BE27)))) * (0.9 + 0.2 / (1 + EXP(-0.6 * (20 - BS27*BH27/T27))))) | CH27: =IF(T27<=0, 1, 0.9 + 0.2 / (1 + EXP(0.1 * (BL27*BS27*BT27/T27 - 33)))) | CI27: =LET( x_val, X27, bq_val, BS27, Check_Fail, OR(NOT(ISNUMBER(x_val)), bq_val <= 1), IF(Check_Fail, 1, LET( Ratio, x_val / bq_val, calc_A, 2.5 / (1 + EXP(-0.23105 * (Ratio - 3))), calc_B, 2.5 / (1 + EXP(-0.008664 * (x_val - 20))), calc_A + calc_B ) )) | CJ27: =CD27*CE27*CF27*CG27*CH27*CI27 | CK27: =CJ27 | CL27: =T27 * 2 / BS27 / BT27 | CM27: =CK27/CL27 | CN27: =CK27*CC27 | CP27: =CN27*BS27*BT27 | CQ27: =CP27/T27 | CR27: =100/CP27 | CS27: =100/CQ27 | CV27: =BL27/T27 | CW27: =100/CV27 | CY27: 使用热熔无壳弹的改装冲锋枪。 有着令人满意的性价比、射速和弹容量， 唯一的缺点是散热性能时好时坏。 | DA27: =TEXTJOIN("、", TRUE, FILTER('武器技能'!B:B, '武器技能'!E:E = H27)) | DC27: 完成 | DD27: 完成
A28: SpitFire | B28: 火舌 | D28: =IF($A28="","","WPN"&VLOOKUP(E28,'引用数据库'!Z:AC,4,FALSE)&VLOOKUP(H28,'引用数据库'!N:P,3,FALSE)&VLOOKUP(I28,'引用数据库'!S:U,3,FALSE)&TEXT(F28,"00")) | E28: 野望 | F28: 1 | G28: =G27 | H28: =H27 | I28: =I27 | J28: 自动 | K28: =K27 | M28: =M27 | N28: 1000 | O28: N/A | P28: 0 | Q28: 0 | R28: 0.08 | S28: 0 | T28: =SUM(P28:S28) | U28: =2*T28/(15*(1+(5-BD28)*0.1)) | W28: =W27 | X28: =X27 | Y28: 0.03 | Z28: 0.125 | AA28: =AA27 | AB28: =AB27 | AC28: =AC27 | AD28: =(W28+AB28)*AC28 | AE28: =(X28+AB28)*AC28 | AJ28: 0.54 | AK28: =AK27+0.1 | AL28: 0 | AM28: =IFS(AJ28 > 1.25, "S", AJ28 > 1, "A", AJ28 > 0.75, "B", AJ28 > 0.5, "C", AJ28 > 0.25, "D", AJ28 > 0, "E", TRUE, "-") | AN28: =IFS(AK28 > 1.25, "S", AK28 > 1, "A", AK28 > 0.75, "B", AK28 > 0.5, "C", AK28 > 0.25, "D", AK28 > 0, "E", TRUE, "-") | AO28: =IFS(AL28 > 1.25, "S", AL28 > 1, "A", AL28 > 0.75, "B", AL28 > 0.5, "C", AL28 > 0.25, "D", AL28 > 0, "E", TRUE, "-") | AP28: 10 | AQ28: 10 | AR28: 10 | AV28: =IF(SUM(AJ28:AL28)=0, 0, (1 + F28 * 0.1) * (0.75 + 0.25 * MAX(0, MIN(1, IF(MAX(AJ28:AL28)=0, 0, (3*MAX(AJ28:AL28)-SUM(AJ28:AL28)) / (2*MAX(AJ28:AL28))))))) | AW28: =MAX(AJ28:AL28) | AX28: =IF(AW28=0, "", AW28 / ((1 + 0.1*N(F28)))) | AY28: =IF(SUM(AJ28:AL28)=0, 0, (1 + F28 * 0.1) * (1 + ((SUM(AJ28:AL28) - MAX(AJ28:AL28)) / (2 * MAX(AJ28:AL28))) * (1/0.75 - 1))) | AZ28: =AJ28+AK28+AL28 | BA28: =IF(AZ28=0, "", AZ28 / ((1 + 0.1*N(F28))/0.75)) | BB28: 0.1 | BD28: 1 | BE28: =BE27 | BH28: =BH27 | BL28: =BL27 | BN28: 45 | BO28: 2 | BQ28: =BQ27 | BR28: =IFERROR(BQ28*100/CP28,"N/A") | BS28: 1 | BT28: 1 | BW28: =BW27 | BX28: =CP28/BW28 | BY28: =BW28/T28 | CA28: =CA27+20 | CB28: =CA28*BB28*(AP28*AJ28+AQ28*AK28+AR28*AL28) | CC28: =CA28+CB28 | CK28: =CK27 | CN28: =CK28*CC28 | CP28: =CN28*BS28*BT28 | CQ28: =CP28/T28 | CR28: =100/CP28 | CS28: =100/CQ28 | CT28: =CQ28-CQ27 | CU28: =(CQ28-CQ27)/CQ27 | CV28: =BL28/T28 | CW28: =100/CV28 | DC28: 完成 | DD28: 完成
A29: SpitFire | B29: 火舌 | D29: =IF($A29="","","WPN"&VLOOKUP(E29,'引用数据库'!Z:AC,4,FALSE)&VLOOKUP(H29,'引用数据库'!N:P,3,FALSE)&VLOOKUP(I29,'引用数据库'!S:U,3,FALSE)&TEXT(F29,"00")) | E29: 野望 | F29: 2 | G29: =G28 | H29: =H28 | I29: =I28 | J29: 自动 | K29: =K28 | M29: =M28 | N29: 1000 | O29: N/A | P29: 0 | Q29: 0 | R29: 0.08 | S29: 0 | T29: =SUM(P29:S29) | U29: =2*T29/(15*(1+(5-BD29)*0.1)) | W29: =W28 | X29: =X28 | Y29: 0.03 | Z29: 0.125 | AA29: =AA28 | AB29: =AB28 | AC29: =AC28 | AD29: =(W29+AB29)*AC29 | AE29: =(X29+AB29)*AC29 | AJ29: 0.54 | AK29: 0.75 | AL29: 0.07 | AM29: =IFS(AJ29 > 1.25, "S", AJ29 > 1, "A", AJ29 > 0.75, "B", AJ29 > 0.5, "C", AJ29 > 0.25, "D", AJ29 > 0, "E", TRUE, "-") | AN29: =IFS(AK29 > 1.25, "S", AK29 > 1, "A", AK29 > 0.75, "B", AK29 > 0.5, "C", AK29 > 0.25, "D", AK29 > 0, "E", TRUE, "-") | AO29: =IFS(AL29 > 1.25, "S", AL29 > 1, "A", AL29 > 0.75, "B", AL29 > 0.5, "C", AL29 > 0.25, "D", AL29 > 0, "E", TRUE, "-") | AP29: 10 | AQ29: 10 | AR29: 10 | AV29: =IF(SUM(AJ29:AL29)=0, 0, (1 + F29 * 0.1) * (0.75 + 0.25 * MAX(0, MIN(1, IF(MAX(AJ29:AL29)=0, 0, (3*MAX(AJ29:AL29)-SUM(AJ29:AL29)) / (2*MAX(AJ29:AL29))))))) | AW29: =MAX(AJ29:AL29) | AX29: =IF(AW29=0, "", AW29 / ((1 + 0.1*N(F29)))) | AY29: =IF(SUM(AJ29:AL29)=0, 0, (1 + F29 * 0.1) * (1 + ((SUM(AJ29:AL29) - MAX(AJ29:AL29)) / (2 * MAX(AJ29:AL29))) * (1/0.75 - 1))) | AZ29: =AJ29+AK29+AL29 | BA29: =IF(AZ29=0, "", AZ29 / ((1 + 0.1*N(F29))/0.75)) | BB29: 0.1 | BD29: 1 | BE29: =BE28 | BH29: =BH28 | BL29: =BL28 | BN29: 45 | BO29: 2 | BQ29: =BQ28 | BR29: =IFERROR(BQ29*100/CP29,"N/A") | BS29: 1 | BT29: 1 | BW29: =BW28 | BX29: =CP29/BW29 | BY29: =BW29/T29 | CA29: =CA28+10 | CB29: =CA29*BB29*(AP29*AJ29+AQ29*AK29+AR29*AL29) | CC29: =CA29+CB29 | CK29: =CK28 | CN29: =CK29*CC29 | CP29: =CN29*BS29*BT29 | CQ29: =CP29/T29 | CR29: =100/CP29 | CS29: =100/CQ29 | CT29: =CQ29-CQ28 | CU29: =(CQ29-CQ28)/CQ28 | CV29: =BL29/T29 | CW29: =100/CV29 | DC29: 完成 | DD29: 完成
A30: SpitFire | B30: 火舌 | D30: =IF($A30="","","WPN"&VLOOKUP(E30,'引用数据库'!Z:AC,4,FALSE)&VLOOKUP(H30,'引用数据库'!N:P,3,FALSE)&VLOOKUP(I30,'引用数据库'!S:U,3,FALSE)&TEXT(F30,"00")) | E30: 野望 | F30: 3 | G30: =G29 | H30: =H29 | I30: =I29 | J30: 自动 | K30: =K29 | M30: =M29 | N30: 1000 | O30: N/A | P30: 0 | Q30: 0 | R30: 0.08 | S30: 0 | T30: =SUM(P30:S30) | U30: =2*T30/(15*(1+(5-BD30)*0.1)) | W30: =W29 | X30: =X29 | Y30: 0.03 | Z30: 0.125 | AA30: =AA29 | AB30: =AB29 | AC30: =AC29 | AD30: =(W30+AB30)*AC30 | AE30: =(X30+AB30)*AC30 | AJ30: =AJ29 | AK30: =AK29+0.1 | AL30: =AL29 | AM30: =IFS(AJ30 > 1.25, "S", AJ30 > 1, "A", AJ30 > 0.75, "B", AJ30 > 0.5, "C", AJ30 > 0.25, "D", AJ30 > 0, "E", TRUE, "-") | AN30: =IFS(AK30 > 1.25, "S", AK30 > 1, "A", AK30 > 0.75, "B", AK30 > 0.5, "C", AK30 > 0.25, "D", AK30 > 0, "E", TRUE, "-") | AO30: =IFS(AL30 > 1.25, "S", AL30 > 1, "A", AL30 > 0.75, "B", AL30 > 0.5, "C", AL30 > 0.25, "D", AL30 > 0, "E", TRUE, "-") | AP30: 10 | AQ30: 10 | AR30: 10 | AV30: =IF(SUM(AJ30:AL30)=0, 0, (1 + F30 * 0.1) * (0.75 + 0.25 * MAX(0, MIN(1, IF(MAX(AJ30:AL30)=0, 0, (3*MAX(AJ30:AL30)-SUM(AJ30:AL30)) / (2*MAX(AJ30:AL30))))))) | AW30: =MAX(AJ30:AL30) | AX30: =IF(AW30=0, "", AW30 / ((1 + 0.1*N(F30)))) | AY30: =IF(SUM(AJ30:AL30)=0, 0, (1 + F30 * 0.1) * (1 + ((SUM(AJ30:AL30) - MAX(AJ30:AL30)) / (2 * MAX(AJ30:AL30))) * (1/0.75 - 1))) | AZ30: =AJ30+AK30+AL30 | BA30: =IF(AZ30=0, "", AZ30 / ((1 + 0.1*N(F30))/0.75)) | BB30: 0.1 | BD30: 1 | BE30: =BE29 | BH30: =BH29 | BL30: =BL29 | BN30: 45 | BO30: 2 | BQ30: =BQ29 | BR30: =IFERROR(BQ30*100/CP30,"N/A") | BS30: 1 | BT30: 1 | BW30: =BW29 | BX30: =CP30/BW30 | BY30: =BW30/T30 | CA30: =CA29+10 | CB30: =CA30*BB30*(AP30*AJ30+AQ30*AK30+AR30*AL30) | CC30: =CA30+CB30 | CK30: =CK29 | CN30: =CK30*CC30 | CP30: =CN30*BS30*BT30 | CQ30: =CP30/T30 | CR30: =100/CP30 | CS30: =100/CQ30 | CT30: =CQ30-CQ29 | CU30: =(CQ30-CQ29)/CQ29 | CV30: =BL30/T30 | CW30: =100/CV30 | DC30: 完成 | DD30: 完成
A31: SpitFire | B31: 火舌 | D31: =IF($A31="","","WPN"&VLOOKUP(E31,'引用数据库'!Z:AC,4,FALSE)&VLOOKUP(H31,'引用数据库'!N:P,3,FALSE)&VLOOKUP(I31,'引用数据库'!S:U,3,FALSE)&TEXT(F31,"00")) | E31: 野望 | F31: 4 | G31: =G30 | H31: =H30 | I31: =I30 | J31: 自动 | K31: =K30 | M31: =M30 | N31: 1000 | O31: N/A | P31: 0 | Q31: 0 | R31: 0.08 | S31: 0 | T31: =SUM(P31:S31) | U31: =2*T31/(15*(1+(5-BD31)*0.1)) | W31: =W30 | X31: =X30 | Y31: 0.03 | Z31: 0.125 | AA31: =AA30 | AB31: =AB30 | AC31: =AC30 | AD31: =(W31+AB31)*AC31 | AE31: =(X31+AB31)*AC31 | AJ31: =AJ30 | AK31: =AK30+0.1 | AL31: =AL30 | AM31: =IFS(AJ31 > 1.25, "S", AJ31 > 1, "A", AJ31 > 0.75, "B", AJ31 > 0.5, "C", AJ31 > 0.25, "D", AJ31 > 0, "E", TRUE, "-") | AN31: =IFS(AK31 > 1.25, "S", AK31 > 1, "A", AK31 > 0.75, "B", AK31 > 0.5, "C", AK31 > 0.25, "D", AK31 > 0, "E", TRUE, "-") | AO31: =IFS(AL31 > 1.25, "S", AL31 > 1, "A", AL31 > 0.75, "B", AL31 > 0.5, "C", AL31 > 0.25, "D", AL31 > 0, "E", TRUE, "-") | AP31: 10 | AQ31: 10 | AR31: 10 | AV31: =IF(SUM(AJ31:AL31)=0, 0, (1 + F31 * 0.1) * (0.75 + 0.25 * MAX(0, MIN(1, IF(MAX(AJ31:AL31)=0, 0, (3*MAX(AJ31:AL31)-SUM(AJ31:AL31)) / (2*MAX(AJ31:AL31))))))) | AW31: =MAX(AJ31:AL31) | AX31: =IF(AW31=0, "", AW31 / ((1 + 0.1*N(F31)))) | AY31: =IF(SUM(AJ31:AL31)=0, 0, (1 + F31 * 0.1) * (1 + ((SUM(AJ31:AL31) - MAX(AJ31:AL31)) / (2 * MAX(AJ31:AL31))) * (1/0.75 - 1))) | AZ31: =AJ31+AK31+AL31 | BA31: =IF(AZ31=0, "", AZ31 / ((1 + 0.1*N(F31))/0.75)) | BB31: 0.1 | BD31: 1 | BE31: =BE30 | BH31: =BH30 | BL31: =BL30 | BN31: 45 | BO31: 2 | BQ31: =BQ30 | BR31: =IFERROR(BQ31*100/CP31,"N/A") | BS31: 1 | BT31: 1 | BW31: =BW30 | BX31: =CP31/BW31 | BY31: =BW31/T31 | CA31: =CA30+10 | CB31: =CA31*BB31*(AP31*AJ31+AQ31*AK31+AR31*AL31) | CC31: =CA31+CB31 | CK31: =CK30 | CN31: =CK31*CC31 | CP31: =CN31*BS31*BT31 | CQ31: =CP31/T31 | CR31: =100/CP31 | CS31: =100/CQ31 | CT31: =CQ31-CQ30 | CU31: =(CQ31-CQ30)/CQ30 | CV31: =BL31/T31 | CW31: =100/CV31 | DC31: 完成 | DD31: 完成
A32: SpitFire | B32: 火舌 | D32: =IF($A32="","","WPN"&VLOOKUP(E32,'引用数据库'!Z:AC,4,FALSE)&VLOOKUP(H32,'引用数据库'!N:P,3,FALSE)&VLOOKUP(I32,'引用数据库'!S:U,3,FALSE)&TEXT(F32,"00")) | E32: 野望 | F32: 5 | G32: =G31 | H32: =H31 | I32: =I31 | J32: 自动 | K32: =K31 | M32: =M31 | N32: 1000 | O32: N/A | P32: 0 | Q32: 0 | R32: 0.08 | S32: 0 | T32: =SUM(P32:S32) | U32: =2*T32/(15*(1+(5-BD32)*0.1)) | W32: =W31 | X32: =X31 | Y32: 0.03 | Z32: 0.125 | AA32: =AA31 | AB32: =AB31 | AC32: =AC31 | AD32: =(W32+AB32)*AC32 | AE32: =(X32+AB32)*AC32 | AJ32: =AJ31 | AK32: =AK31+0.1 | AL32: =AL31 | AM32: =IFS(AJ32 > 1.25, "S", AJ32 > 1, "A", AJ32 > 0.75, "B", AJ32 > 0.5, "C", AJ32 > 0.25, "D", AJ32 > 0, "E", TRUE, "-") | AN32: =IFS(AK32 > 1.25, "S", AK32 > 1, "A", AK32 > 0.75, "B", AK32 > 0.5, "C", AK32 > 0.25, "D", AK32 > 0, "E", TRUE, "-") | AO32: =IFS(AL32 > 1.25, "S", AL32 > 1, "A", AL32 > 0.75, "B", AL32 > 0.5, "C", AL32 > 0.25, "D", AL32 > 0, "E", TRUE, "-") | AP32: 10 | AQ32: 10 | AR32: 10 | AV32: =IF(SUM(AJ32:AL32)=0, 0, (1 + F32 * 0.1) * (0.75 + 0.25 * MAX(0, MIN(1, IF(MAX(AJ32:AL32)=0, 0, (3*MAX(AJ32:AL32)-SUM(AJ32:AL32)) / (2*MAX(AJ32:AL32))))))) | AW32: =MAX(AJ32:AL32) | AX32: =IF(AW32=0, "", AW32 / ((1 + 0.1*N(F32)))) | AY32: =IF(SUM(AJ32:AL32)=0, 0, (1 + F32 * 0.1) * (1 + ((SUM(AJ32:AL32) - MAX(AJ32:AL32)) / (2 * MAX(AJ32:AL32))) * (1/0.75 - 1))) | AZ32: =AJ32+AK32+AL32 | BA32: =IF(AZ32=0, "", AZ32 / ((1 + 0.1*N(F32))/0.75)) | BB32: 0.1 | BD32: 1 | BE32: =BE31 | BH32: =BH31 | BL32: =BL31 | BN32: 45 | BO32: 2 | BQ32: =BQ31 | BR32: =IFERROR(BQ32*100/CP32,"N/A") | BS32: 1 | BT32: 1 | BW32: =BW31 | BX32: =CP32/BW32 | BY32: =BW32/T32 | CA32: =CA31+10 | CB32: =CA32*BB32*(AP32*AJ32+AQ32*AK32+AR32*AL32) | CC32: =CA32+CB32 | CK32: =CK31 | CN32: =CK32*CC32 | CP32: =CN32*BS32*BT32 | CQ32: =CP32/T32 | CR32: =100/CP32 | CS32: =100/CQ32 | CT32: =CQ32-CQ31 | CU32: =(CQ32-CQ31)/CQ31 | CV32: =BL32/T32 | CW32: =100/CV32 | DC32: 完成 | DD32: 完成
A33: RocketHammer | B33: 火箭锤 | D33: =IF($A33="","","WPN"&VLOOKUP(E33,'引用数据库'!Z:AC,4,FALSE)&VLOOKUP(H33,'引用数据库'!N:P,3,FALSE)&VLOOKUP(I33,'引用数据库'!S:U,3,FALSE)&TEXT(F33,"00")) | E33: 劳旅 | F33: 0 | G33: 近战 | H33: 巨锤 | I33: 动能 | J33: 手动 | K33: 2 | M33: 1 | N33: 200 | O33: 135 | P33: 0.418 | Q33: 0.1 | R33: 0.482 | S33: 0 | T33: =SUM(P33:S33) | U33: =2*T33/(15*(1+(5-BD33)*0.1)) | W33: N/A | X33: N/A | Y33: N/A | Z33: N/A | AA33: N/A | AB33: N/A | AC33: N/A | AD33: N/A | AE33: N/A | AJ33: 1 | AK33: 0 | AL33: 0 | AM33: =IFS(AJ33 > 1.25, "S", AJ33 > 1, "A", AJ33 > 0.75, "B", AJ33 > 0.5, "C", AJ33 > 0.25, "D", AJ33 > 0, "E", TRUE, "-") | AN33: =IFS(AK33 > 1.25, "S", AK33 > 1, "A", AK33 > 0.75, "B", AK33 > 0.5, "C", AK33 > 0.25, "D", AK33 > 0, "E", TRUE, "-") | AO33: =IFS(AL33 > 1.25, "S", AL33 > 1, "A", AL33 > 0.75, "B", AL33 > 0.5, "C", AL33 > 0.25, "D", AL33 > 0, "E", TRUE, "-") | AP33: 10 | AQ33: 10 | AR33: 10 | AV33: =IF(SUM(AJ33:AL33)=0, 0, (1 + F33 * 0.1) * (0.75 + 0.25 * MAX(0, MIN(1, IF(MAX(AJ33:AL33)=0, 0, (3*MAX(AJ33:AL33)-SUM(AJ33:AL33)) / (2*MAX(AJ33:AL33))))))) | AW33: =MAX(AJ33:AL33) | AX33: =IF(AW33=0, "", AW33 / ((1 + 0.1*N(F33)))) | AY33: =IF(SUM(AJ33:AL33)=0, 0, (1 + F33 * 0.1) * (1 + ((SUM(AJ33:AL33) - MAX(AJ33:AL33)) / (2 * MAX(AJ33:AL33))) * (1/0.75 - 1))) | AZ33: =AJ33+AK33+AL33 | BA33: =IF(AZ33=0, "", AZ33 / ((1 + 0.1*N(F33))/0.75)) | BB33: 0.1 | BD33: 3 | BE33: 4 | BF33: 5 | BG33: =T33*20*(16 * BF33) / (15 + 20 * BF33 - 3 * POWER(BF33, 2))/BT33/BS33 | BH33: =BG33 | BJ33: 3 | BK33: =T33*33*(16 * BJ33) / (15 + 20 * BJ33 - 3 * POWER(BJ33, 2))/BT33/BS33 | BL33: =BK33 | BN33: N/A | BO33: N/A | BP33: 0 | BQ33: 0 | BR33: =IFERROR(BQ33*100/CP33,"N/A") | BS33: 1 | BT33: 1 | BV33: =CP33/1.5 | BW33: 24 | BX33: =CP33/BW33 | BY33: =BW33/T33 | CA33: 10 | CB33: =CA33*BB33*(AP33*AJ33+AQ33*AK33+AR33*AL33) | CC33: =CA33+CB33 | CD33: =T33 * 2 / BS33 / BT33 * (0.9 + 0.2 * IF(G33="近战", EXP(-64 * (T33 - 0.75)^2), EXP(-400 * (T33 - 0.15)^2))) | CE33: =0.9 + 0.2 / (1 + (N33/600)^1) | CF33: =LET( k, K33, be, BS33, bf, BT33, m, N33, n, O33, v, X33, vEff, IF(ISNUMBER(v), v, 0), angle, IF( ISNUMBER(n), IF(n>0, n, IF(ISNUMBER(v), IF(v>0, v, 0), 0 ) ), IF(ISNUMBER(v), IF(v>0, v, 0), 0 ) ), T, IF(k=1, be * bf * 20 / MAX(vEff, 1), IF(k=2, (m/150)^2 * (angle/120), IF(k=3, be * (MIN(bf, 99)/99) * (m/1000), be * bf * (m/1000) * (n/200)^2 ))), b, 0.8, c, 1.2, r, (c-1)/(1-b), k_s, 1, b + (c-b) / (1 + r * EXP(-k_s*(1-T)))) | CG33: =IF(T33<=0,1, (0.9 + 0.2 / (1 + EXP(-0.8 * (5 - BD33)))) * (0.9 + 0.2 / (1 + EXP(-1 * (3.5 - BE33)))) * (0.9 + 0.2 / (1 + EXP(-0.6 * (20 - BS33*BH33/T33))))) | CH33: =IF(T33<=0, 1, 0.9 + 0.2 / (1 + EXP(0.1 * (BL33*BS33*BT33/T33 - 33)))) | CI33: =LET( x_val, W33, bq_val, BS33, Check_Fail, OR(NOT(ISNUMBER(x_val)), bq_val <= 1), IF(Check_Fail, 1, LET( Ratio, x_val / bq_val, calc_A, 2.2 / (1 + EXP(-0.276 * (Ratio - 0.66))), calc_B, 2.2 / (1 + EXP(-0.0138 * (x_val - 13.2))), calc_A + calc_B ) )) | CJ33: =CD33*CE33*CF33*CG33*CH33*CI33 | CK33: =CJ33 | CL33: =T33 * 2 / BS33 / BT33 | CM33: =CK33/CL33 | CN33: =CK33*CC33 | CP33: =CN33*BS33*BT33 | CQ33: =CP33/T33 | CR33: =100/CP33 | CS33: =100/CQ33 | CV33: =BL33/T33 | CW33: =100/CV33 | CY33: 主要用于拆卸工程的火箭锤， 只要使用者体力充足就能连续工作。 内置的高压冲击装置甚至能带着使用者移动， 因此也偶有高空作业误操作导致的失事报道。 | DA33: =TEXTJOIN("、", TRUE, FILTER('武器技能'!B:B, '武器技能'!E:E = H33)) | DC33: 完成 | DD33: 完成
A34: RocketHammer | B34: 火箭锤 | D34: =IF($A34="","","WPN"&VLOOKUP(E34,'引用数据库'!Z:AC,4,FALSE)&VLOOKUP(H34,'引用数据库'!N:P,3,FALSE)&VLOOKUP(I34,'引用数据库'!S:U,3,FALSE)&TEXT(F34,"00")) | E34: 劳旅 | F34: 1 | G34: =G33 | H34: =H33 | I34: =I33 | J34: 手动 | K34: =K33 | M34: =M33 | N34: 200 | O34: 135 | P34: =P33 | Q34: =Q33 | R34: =R33 | S34: 0 | T34: =SUM(P34:S34) | U34: =2*T34/(15*(1+(5-BD34)*0.1)) | W34: N/A | X34: N/A | Y34: N/A | Z34: N/A | AA34: N/A | AB34: N/A | AC34: N/A | AD34: N/A | AE34: N/A | AJ34: =AJ33+0.1 | AK34: 0 | AL34: 0 | AM34: =IFS(AJ34 > 1.25, "S", AJ34 > 1, "A", AJ34 > 0.75, "B", AJ34 > 0.5, "C", AJ34 > 0.25, "D", AJ34 > 0, "E", TRUE, "-") | AN34: =IFS(AK34 > 1.25, "S", AK34 > 1, "A", AK34 > 0.75, "B", AK34 > 0.5, "C", AK34 > 0.25, "D", AK34 > 0, "E", TRUE, "-") | AO34: =IFS(AL34 > 1.25, "S", AL34 > 1, "A", AL34 > 0.75, "B", AL34 > 0.5, "C", AL34 > 0.25, "D", AL34 > 0, "E", TRUE, "-") | AP34: 10 | AQ34: 10 | AR34: 10 | AV34: =IF(SUM(AJ34:AL34)=0, 0, (1 + F34 * 0.1) * (0.75 + 0.25 * MAX(0, MIN(1, IF(MAX(AJ34:AL34)=0, 0, (3*MAX(AJ34:AL34)-SUM(AJ34:AL34)) / (2*MAX(AJ34:AL34))))))) | AW34: =MAX(AJ34:AL34) | AX34: =IF(AW34=0, "", AW34 / ((1 + 0.1*N(F34)))) | AY34: =IF(SUM(AJ34:AL34)=0, 0, (1 + F34 * 0.1) * (1 + ((SUM(AJ34:AL34) - MAX(AJ34:AL34)) / (2 * MAX(AJ34:AL34))) * (1/0.75 - 1))) | AZ34: =AJ34+AK34+AL34 | BA34: =IF(AZ34=0, "", AZ34 / ((1 + 0.1*N(F34))/0.75)) | BB34: 0.1 | BD34: =BD33 | BE34: =BE33 | BH34: =T34*15/0.5 | BL34: =BL33 | BN34: N/A | BO34: N/A | BQ34: 0 | BR34: =IFERROR(BQ34*100/CP34,"N/A") | BS34: 1 | BT34: 1 | BW34: =BW33 | BX34: =CP34/BW34 | BY34: =BW34/T34 | CA34: =CA33+20 | CB34: =CA34*BB34*(AP34*AJ34+AQ34*AK34+AR34*AL34) | CC34: =CA34+CB34 | CK34: =CK33 | CN34: =CK34*CC34 | CP34: =CN34*BS34*BT34 | CQ34: =CP34/T34 | CR34: =100/CP34 | CS34: =100/CQ34 | CT34: =CQ34-CQ33 | CU34: =(CQ34-CQ33)/CQ33 | CV34: =BL34/T34 | CW34: =100/CV34 | DC34: 完成 | DD34: 完成
A35: RocketHammer | B35: 火箭锤 | D35: =IF($A35="","","WPN"&VLOOKUP(E35,'引用数据库'!Z:AC,4,FALSE)&VLOOKUP(H35,'引用数据库'!N:P,3,FALSE)&VLOOKUP(I35,'引用数据库'!S:U,3,FALSE)&TEXT(F35,"00")) | E35: 劳旅 | F35: 2 | G35: =G34 | H35: =H34 | I35: =I34 | J35: 手动 | K35: =K34 | M35: =M34 | N35: 200 | O35: 135 | P35: =P34 | Q35: =Q34 | R35: =R34 | S35: 0 | T35: =SUM(P35:S35) | U35: =2*T35/(15*(1+(5-BD35)*0.1)) | W35: N/A | X35: N/A | Y35: N/A | Z35: N/A | AA35: N/A | AB35: N/A | AC35: N/A | AD35: N/A | AE35: N/A | AJ35: =AJ34+0.1 | AK35: 0 | AL35: 0 | AM35: =IFS(AJ35 > 1.25, "S", AJ35 > 1, "A", AJ35 > 0.75, "B", AJ35 > 0.5, "C", AJ35 > 0.25, "D", AJ35 > 0, "E", TRUE, "-") | AN35: =IFS(AK35 > 1.25, "S", AK35 > 1, "A", AK35 > 0.75, "B", AK35 > 0.5, "C", AK35 > 0.25, "D", AK35 > 0, "E", TRUE, "-") | AO35: =IFS(AL35 > 1.25, "S", AL35 > 1, "A", AL35 > 0.75, "B", AL35 > 0.5, "C", AL35 > 0.25, "D", AL35 > 0, "E", TRUE, "-") | AP35: 10 | AQ35: 10 | AR35: 10 | AV35: =IF(SUM(AJ35:AL35)=0, 0, (1 + F35 * 0.1) * (0.75 + 0.25 * MAX(0, MIN(1, IF(MAX(AJ35:AL35)=0, 0, (3*MAX(AJ35:AL35)-SUM(AJ35:AL35)) / (2*MAX(AJ35:AL35))))))) | AW35: =MAX(AJ35:AL35) | AX35: =IF(AW35=0, "", AW35 / ((1 + 0.1*N(F35)))) | AY35: =IF(SUM(AJ35:AL35)=0, 0, (1 + F35 * 0.1) * (1 + ((SUM(AJ35:AL35) - MAX(AJ35:AL35)) / (2 * MAX(AJ35:AL35))) * (1/0.75 - 1))) | AZ35: =AJ35+AK35+AL35 | BA35: =IF(AZ35=0, "", AZ35 / ((1 + 0.1*N(F35))/0.75)) | BB35: 0.1 | BD35: =BD34 | BE35: =BE34 | BH35: =BH34 | BL35: =BL34 | BN35: N/A | BO35: N/A | BQ35: 0 | BR35: =IFERROR(BQ35*100/CP35,"N/A") | BS35: 1 | BT35: 1 | BW35: =BW34 | BX35: =CP35/BW35 | BY35: =BW35/T35 | CA35: =CA34+10 | CB35: =CA35*BB35*(AP35*AJ35+AQ35*AK35+AR35*AL35) | CC35: =CA35+CB35 | CK35: =CK34 | CN35: =CK35*CC35 | CP35: =CN35*BS35*BT35 | CQ35: =CP35/T35 | CR35: =100/CP35 | CS35: =100/CQ35 | CT35: =CQ35-CQ34 | CU35: =(CQ35-CQ34)/CQ34 | CV35: =BL35/T35 | CW35: =100/CV35 | DC35: 完成 | DD35: 完成
A36: RocketHammer | B36: 火箭锤 | D36: =IF($A36="","","WPN"&VLOOKUP(E36,'引用数据库'!Z:AC,4,FALSE)&VLOOKUP(H36,'引用数据库'!N:P,3,FALSE)&VLOOKUP(I36,'引用数据库'!S:U,3,FALSE)&TEXT(F36,"00")) | E36: 劳旅 | F36: 3 | G36: =G35 | H36: =H35 | I36: =I35 | J36: 手动 | K36: =K35 | M36: =M35 | N36: 200 | O36: 135 | P36: =P35 | Q36: =Q35 | R36: =R35 | S36: 0 | T36: =SUM(P36:S36) | U36: =2*T36/(15*(1+(5-BD36)*0.1)) | W36: N/A | X36: N/A | Y36: N/A | Z36: N/A | AA36: N/A | AB36: N/A | AC36: N/A | AD36: N/A | AE36: N/A | AJ36: =AJ35+0.1 | AK36: 0 | AL36: 0 | AM36: =IFS(AJ36 > 1.25, "S", AJ36 > 1, "A", AJ36 > 0.75, "B", AJ36 > 0.5, "C", AJ36 > 0.25, "D", AJ36 > 0, "E", TRUE, "-") | AN36: =IFS(AK36 > 1.25, "S", AK36 > 1, "A", AK36 > 0.75, "B", AK36 > 0.5, "C", AK36 > 0.25, "D", AK36 > 0, "E", TRUE, "-") | AO36: =IFS(AL36 > 1.25, "S", AL36 > 1, "A", AL36 > 0.75, "B", AL36 > 0.5, "C", AL36 > 0.25, "D", AL36 > 0, "E", TRUE, "-") | AP36: 10 | AQ36: 10 | AR36: 10 | AV36: =IF(SUM(AJ36:AL36)=0, 0, (1 + F36 * 0.1) * (0.75 + 0.25 * MAX(0, MIN(1, IF(MAX(AJ36:AL36)=0, 0, (3*MAX(AJ36:AL36)-SUM(AJ36:AL36)) / (2*MAX(AJ36:AL36))))))) | AW36: =MAX(AJ36:AL36) | AX36: =IF(AW36=0, "", AW36 / ((1 + 0.1*N(F36)))) | AY36: =IF(SUM(AJ36:AL36)=0, 0, (1 + F36 * 0.1) * (1 + ((SUM(AJ36:AL36) - MAX(AJ36:AL36)) / (2 * MAX(AJ36:AL36))) * (1/0.75 - 1))) | AZ36: =AJ36+AK36+AL36 | BA36: =IF(AZ36=0, "", AZ36 / ((1 + 0.1*N(F36))/0.75)) | BB36: 0.1 | BD36: =BD35 | BE36: =BE35 | BH36: =BH35 | BL36: =BL35 | BN36: N/A | BO36: N/A | BQ36: 0 | BR36: =IFERROR(BQ36*100/CP36,"N/A") | BS36: 1 | BT36: 1 | BW36: =BW35 | BX36: =CP36/BW36 | BY36: =BW36/T36 | CA36: =CA35+10 | CB36: =CA36*BB36*(AP36*AJ36+AQ36*AK36+AR36*AL36) | CC36: =CA36+CB36 | CK36: =CK35 | CN36: =CK36*CC36 | CP36: =CN36*BS36*BT36 | CQ36: =CP36/T36 | CR36: =100/CP36 | CS36: =100/CQ36 | CT36: =CQ36-CQ35 | CU36: =(CQ36-CQ35)/CQ35 | CV36: =BL36/T36 | CW36: =100/CV36 | DC36: 完成 | DD36: 完成
A37: RocketHammer | B37: 火箭锤 | D37: =IF($A37="","","WPN"&VLOOKUP(E37,'引用数据库'!Z:AC,4,FALSE)&VLOOKUP(H37,'引用数据库'!N:P,3,FALSE)&VLOOKUP(I37,'引用数据库'!S:U,3,FALSE)&TEXT(F37,"00")) | E37: 劳旅 | F37: 4 | G37: =G36 | H37: =H36 | I37: =I36 | J37: 手动 | K37: =K36 | M37: =M36 | N37: 200 | O37: 135 | P37: =P36 | Q37: =Q36 | R37: =R36 | S37: 0 | T37: =SUM(P37:S37) | U37: =2*T37/(15*(1+(5-BD37)*0.1)) | W37: N/A | X37: N/A | Y37: N/A | Z37: N/A | AA37: N/A | AB37: N/A | AC37: N/A | AD37: N/A | AE37: N/A | AJ37: =AJ36+0.1 | AK37: 0 | AL37: 0 | AM37: =IFS(AJ37 > 1.25, "S", AJ37 > 1, "A", AJ37 > 0.75, "B", AJ37 > 0.5, "C", AJ37 > 0.25, "D", AJ37 > 0, "E", TRUE, "-") | AN37: =IFS(AK37 > 1.25, "S", AK37 > 1, "A", AK37 > 0.75, "B", AK37 > 0.5, "C", AK37 > 0.25, "D", AK37 > 0, "E", TRUE, "-") | AO37: =IFS(AL37 > 1.25, "S", AL37 > 1, "A", AL37 > 0.75, "B", AL37 > 0.5, "C", AL37 > 0.25, "D", AL37 > 0, "E", TRUE, "-") | AP37: 10 | AQ37: 10 | AR37: 10 | AV37: =IF(SUM(AJ37:AL37)=0, 0, (1 + F37 * 0.1) * (0.75 + 0.25 * MAX(0, MIN(1, IF(MAX(AJ37:AL37)=0, 0, (3*MAX(AJ37:AL37)-SUM(AJ37:AL37)) / (2*MAX(AJ37:AL37))))))) | AW37: =MAX(AJ37:AL37) | AX37: =IF(AW37=0, "", AW37 / ((1 + 0.1*N(F37)))) | AY37: =IF(SUM(AJ37:AL37)=0, 0, (1 + F37 * 0.1) * (1 + ((SUM(AJ37:AL37) - MAX(AJ37:AL37)) / (2 * MAX(AJ37:AL37))) * (1/0.75 - 1))) | AZ37: =AJ37+AK37+AL37 | BA37: =IF(AZ37=0, "", AZ37 / ((1 + 0.1*N(F37))/0.75)) | BB37: 0.1 | BD37: =BD36 | BE37: =BE36 | BH37: =BH36 | BL37: =BL36 | BN37: N/A | BO37: N/A | BQ37: 0 | BR37: =IFERROR(BQ37*100/CP37,"N/A") | BS37: 1 | BT37: 1 | BW37: =BW36 | BX37: =CP37/BW37 | BY37: =BW37/T37 | CA37: =CA36+10 | CB37: =CA37*BB37*(AP37*AJ37+AQ37*AK37+AR37*AL37) | CC37: =CA37+CB37 | CK37: =CK36 | CN37: =CK37*CC37 | CP37: =CN37*BS37*BT37 | CQ37: =CP37/T37 | CR37: =100/CP37 | CS37: =100/CQ37 | CT37: =CQ37-CQ36 | CU37: =(CQ37-CQ36)/CQ36 | CV37: =BL37/T37 | CW37: =100/CV37 | DC37: 完成 | DD37: 完成
A38: RocketHammer | B38: 火箭锤 | D38: =IF($A38="","","WPN"&VLOOKUP(E38,'引用数据库'!Z:AC,4,FALSE)&VLOOKUP(H38,'引用数据库'!N:P,3,FALSE)&VLOOKUP(I38,'引用数据库'!S:U,3,FALSE)&TEXT(F38,"00")) | E38: 劳旅 | F38: 5 | G38: =G37 | H38: =H37 | I38: =I37 | J38: 手动 | K38: =K37 | M38: =M37 | N38: 200 | O38: 135 | P38: =P37 | Q38: =Q37 | R38: =R37 | S38: 0 | T38: =SUM(P38:S38) | U38: =2*T38/(15*(1+(5-BD38)*0.1)) | W38: N/A | X38: N/A | Y38: N/A | Z38: N/A | AA38: N/A | AB38: N/A | AC38: N/A | AD38: N/A | AE38: N/A | AJ38: =AJ37+0.1 | AK38: 0 | AL38: 0 | AM38: =IFS(AJ38 > 1.25, "S", AJ38 > 1, "A", AJ38 > 0.75, "B", AJ38 > 0.5, "C", AJ38 > 0.25, "D", AJ38 > 0, "E", TRUE, "-") | AN38: =IFS(AK38 > 1.25, "S", AK38 > 1, "A", AK38 > 0.75, "B", AK38 > 0.5, "C", AK38 > 0.25, "D", AK38 > 0, "E", TRUE, "-") | AO38: =IFS(AL38 > 1.25, "S", AL38 > 1, "A", AL38 > 0.75, "B", AL38 > 0.5, "C", AL38 > 0.25, "D", AL38 > 0, "E", TRUE, "-") | AP38: 10 | AQ38: 10 | AR38: 10 | AV38: =IF(SUM(AJ38:AL38)=0, 0, (1 + F38 * 0.1) * (0.75 + 0.25 * MAX(0, MIN(1, IF(MAX(AJ38:AL38)=0, 0, (3*MAX(AJ38:AL38)-SUM(AJ38:AL38)) / (2*MAX(AJ38:AL38))))))) | AW38: =MAX(AJ38:AL38) | AX38: =IF(AW38=0, "", AW38 / ((1 + 0.1*N(F38)))) | AY38: =IF(SUM(AJ38:AL38)=0, 0, (1 + F38 * 0.1) * (1 + ((SUM(AJ38:AL38) - MAX(AJ38:AL38)) / (2 * MAX(AJ38:AL38))) * (1/0.75 - 1))) | AZ38: =AJ38+AK38+AL38 | BA38: =IF(AZ38=0, "", AZ38 / ((1 + 0.1*N(F38))/0.75)) | BB38: 0.1 | BD38: =BD37 | BE38: =BE37 | BH38: =BH37 | BL38: =BL37 | BN38: N/A | BO38: N/A | BQ38: 0 | BR38: =IFERROR(BQ38*100/CP38,"N/A") | BS38: 1 | BT38: 1 | BW38: =BW37 | BX38: =CP38/BW38 | BY38: =BW38/T38 | CA38: =CA37+10 | CB38: =CA38*BB38*(AP38*AJ38+AQ38*AK38+AR38*AL38) | CC38: =CA38+CB38 | CK38: =CK37 | CN38: =CK38*CC38 | CP38: =CN38*BS38*BT38 | CQ38: =CP38/T38 | CR38: =100/CP38 | CS38: =100/CQ38 | CT38: =CQ38-CQ37 | CU38: =(CQ38-CQ37)/CQ37 | CV38: =BL38/T38 | CW38: =100/CV38 | DC38: 完成 | DD38: 完成
A39: ClusterCapacitor | B39: 幸运39 | D39: =IF($A39="","","WPN"&VLOOKUP(E39,'引用数据库'!Z:AC,4,FALSE)&VLOOKUP(H39,'引用数据库'!N:P,3,FALSE)&VLOOKUP(I39,'引用数据库'!S:U,3,FALSE)&TEXT(F39,"00")) | E39: 劳旅 | F39: 0 | G39: 远程 | H39: 霰弹枪 | I39: 电磁 | J39: 手动 | K39: 1 | M39: 1 | N39: 800 | O39: N/A | P39: 0 | Q39: 0 | R39: 0.3 | S39: 0 | T39: =SUM(P39:S39) | U39: =2*T39/(15*(1+(5-BD39)*0.1)) | W39: 40 | X39: 45 | Y39: 0.25 | Z39: 0.25 | AA39: 0 | AB39: 0 | AC39: 1 | AD39: =(W39+AB39)*AC39 | AE39: =(X39+AB39)*AC39 | AJ39: 0.3 | AK39: 0.58 | AL39: 0.3 | AM39: =IFS(AJ39 > 1.25, "S", AJ39 > 1, "A", AJ39 > 0.75, "B", AJ39 > 0.5, "C", AJ39 > 0.25, "D", AJ39 > 0, "E", TRUE, "-") | AN39: =IFS(AK39 > 1.25, "S", AK39 > 1, "A", AK39 > 0.75, "B", AK39 > 0.5, "C", AK39 > 0.25, "D", AK39 > 0, "E", TRUE, "-") | AO39: =IFS(AL39 > 1.25, "S", AL39 > 1, "A", AL39 > 0.75, "B", AL39 > 0.5, "C", AL39 > 0.25, "D", AL39 > 0, "E", TRUE, "-") | AP39: 10 | AQ39: 10 | AR39: 10 | AV39: =IF(SUM(AJ39:AL39)=0, 0, (1 + F39 * 0.1) * (0.75 + 0.25 * MAX(0, MIN(1, IF(MAX(AJ39:AL39)=0, 0, (3*MAX(AJ39:AL39)-SUM(AJ39:AL39)) / (2*MAX(AJ39:AL39))))))) | AW39: =MAX(AJ39:AL39) | AX39: =IF(AW39=0, "", AW39 / ((1 + 0.1*N(F39)))) | AY39: =IF(SUM(AJ39:AL39)=0, 0, (1 + F39 * 0.1) * (1 + ((SUM(AJ39:AL39) - MAX(AJ39:AL39)) / (2 * MAX(AJ39:AL39))) * (1/0.75 - 1))) | AZ39: =AJ39+AK39+AL39 | BA39: =IF(AZ39=0, "", AZ39 / ((1 + 0.1*N(F39))/0.75)) | BB39: 0.1 | BD39: 4 | BE39: 3 | BF39: 4 | BG39: =T39*20*(16 * BF39) / (15 + 20 * BF39 - 3 * POWER(BF39, 2))/BT39/BS39 | BH39: =BG39 | BJ39: 3 | BK39: =T39*33*(16 * BJ39) / (15 + 20 * BJ39 - 3 * POWER(BJ39, 2))/BT39/BS39 | BL39: =BK39 | BN39: 3 | BO39: 2 | BP39: =ROUND(CP39/10,2) | BQ39: 1 | BR39: =IFERROR(BQ39*100/CP39,"N/A") | BS39: =X39/5 | BT39: 1 | BV39: =CP39/1.5 | BW39: =ROUND(BV39) | BX39: =CP39/BW39 | BY39: =BW39/T39 | CA39: 10 | CB39: =CA39*BB39*(AP39*AJ39+AQ39*AK39+AR39*AL39) | CC39: =CA39+CB39 | CD39: =T39 * 2 / BS39 / BT39 * (0.9 + 0.2 * IF(G39="近战", EXP(-64 * (T39 - 0.75)^2), EXP(-400 * (T39 - 0.15)^2))) | CE39: =0.9 + 0.2 / (1 + (N39/600)^1) | CF39: =LET( k, K39, be, BS39, bf, BT39, m, N39, n, O39, v, X39, vEff, IF(ISNUMBER(v), v, 0), angle, IF( ISNUMBER(n), IF(n>0, n, IF(ISNUMBER(v), IF(v>0, v, 0), 0 ) ), IF(ISNUMBER(v), IF(v>0, v, 0), 0 ) ), T, IF(k=1, be * bf * 20 / MAX(vEff, 1), IF(k=2, (m/150)^2 * (angle/120), IF(k=3, be * (MIN(bf, 99)/99) * (m/1000), be * bf * (m/1000) * (n/200)^2 ))), b, 0.8, c, 1.2, r, (c-1)/(1-b), k_s, 1, b + (c-b) / (1 + r * EXP(-k_s*(1-T)))) | CG39: =IF(T39<=0,1, (0.9 + 0.2 / (1 + EXP(-0.8 * (5 - BD39)))) * (0.9 + 0.2 / (1 + EXP(-1 * (3.5 - BE39)))) * (0.9 + 0.2 / (1 + EXP(-0.6 * (20 - BS39*BH39/T39))))) | CH39: =IF(T39<=0, 1, 0.9 + 0.2 / (1 + EXP(0.1 * (BL39*BS39*BT39/T39 - 33)))) | CI39: =LET( x_val, W39, bq_val, BS39, Check_Fail, OR(NOT(ISNUMBER(x_val)), bq_val <= 1), IF(Check_Fail, 1, LET( Ratio, x_val / bq_val, calc_A, 2.2 / (1 + EXP(-0.276 * (Ratio - 0.66))), calc_B, 2.2 / (1 + EXP(-0.0138 * (x_val - 13.2))), calc_A + calc_B ) )) | CJ39: =CD39*CE39*CF39*CG39*CH39*CI39 | CK39: =CJ39 | CL39: =T39 * 2 / BS39 / BT39 | CM39: =CK39/CL39 | CN39: =CK39*CC39 | CP39: =CN39*BS39*BT39 | CQ39: =CP39/T39 | CR39: =100/CP39 | CS39: =100/CQ39 | CV39: =BL39/T39 | CW39: =100/CV39 | CY39: 外形酷似儿童玩具的霰弹枪， 将高压电容器捆绑并连接到稳压电源即可工作。 枪身上打印着“幸运39”的字样， 据说是炸膛导致的最高伤亡人数。 | DA39: =TEXTJOIN("、", TRUE, FILTER('武器技能'!B:B, '武器技能'!E:E = H39)) | DC39: 完成 | DD39: 完成
A40: =A39 | B40: =B39 | D40: =IF($A40="","","WPN"&VLOOKUP(E40,'引用数据库'!Z:AC,4,FALSE)&VLOOKUP(H40,'引用数据库'!N:P,3,FALSE)&VLOOKUP(I40,'引用数据库'!S:U,3,FALSE)&TEXT(F40,"00")) | E40: 劳旅 | F40: 1 | G40: =G39 | H40: =H39 | I40: =I39 | J40: 手动 | K40: =K39 | M40: =M39 | N40: 800 | O40: N/A | P40: 0 | Q40: 0 | R40: 0.3 | S40: 0 | T40: =SUM(P40:S40) | U40: =2*T40/(15*(1+(5-BD40)*0.1)) | W40: =W39 | X40: =X39 | Y40: 0.25 | Z40: 0.25 | AA40: 0 | AB40: 0 | AC40: 1 | AD40: =(W40+AB40)*AC40 | AE40: =(X40+AB40)*AC40 | AJ40: 0.3 | AK40: 0.67 | AL40: =AL39 | AM40: =IFS(AJ40 > 1.25, "S", AJ40 > 1, "A", AJ40 > 0.75, "B", AJ40 > 0.5, "C", AJ40 > 0.25, "D", AJ40 > 0, "E", TRUE, "-") | AN40: =IFS(AK40 > 1.25, "S", AK40 > 1, "A", AK40 > 0.75, "B", AK40 > 0.5, "C", AK40 > 0.25, "D", AK40 > 0, "E", TRUE, "-") | AO40: =IFS(AL40 > 1.25, "S", AL40 > 1, "A", AL40 > 0.75, "B", AL40 > 0.5, "C", AL40 > 0.25, "D", AL40 > 0, "E", TRUE, "-") | AP40: 10 | AQ40: 10 | AR40: 10 | AV40: =IF(SUM(AJ40:AL40)=0, 0, (1 + F40 * 0.1) * (0.75 + 0.25 * MAX(0, MIN(1, IF(MAX(AJ40:AL40)=0, 0, (3*MAX(AJ40:AL40)-SUM(AJ40:AL40)) / (2*MAX(AJ40:AL40))))))) | AW40: =MAX(AJ40:AL40) | AX40: =IF(AW40=0, "", AW40 / ((1 + 0.1*N(F40)))) | AY40: =IF(SUM(AJ40:AL40)=0, 0, (1 + F40 * 0.1) * (1 + ((SUM(AJ40:AL40) - MAX(AJ40:AL40)) / (2 * MAX(AJ40:AL40))) * (1/0.75 - 1))) | AZ40: =AJ40+AK40+AL40 | BA40: =IF(AZ40=0, "", AZ40 / ((1 + 0.1*N(F40))/0.75)) | BB40: 0.1 | BD40: =BD39 | BE40: =BE39 | BH40: =BH39 | BL40: =BL39 | BN40: =BN39 | BO40: 2 | BQ40: =BQ39 | BR40: =IFERROR(BQ40*100/CP40,"N/A") | BS40: =BS39 | BT40: =BT39 | BW40: =BW39 | BX40: =CP40/BW40 | BY40: =BW40/T40 | CA40: =CA39+20 | CB40: =CA40*BB40*(AP40*AJ40+AQ40*AK40+AR40*AL40) | CC40: =CA40+CB40 | CK40: =CK39 | CN40: =CK40*CC40 | CP40: =CN40*BS40*BT40 | CQ40: =CP40/T40 | CR40: =100/CP40 | CS40: =100/CQ40 | CT40: =CQ40-CQ39 | CU40: =(CQ40-CQ39)/CQ39 | CV40: =BL40/T40 | CW40: =100/CV40 | DC40: 完成 | DD40: 完成
A41: =A40 | B41: =B40 | D41: =IF($A41="","","WPN"&VLOOKUP(E41,'引用数据库'!Z:AC,4,FALSE)&VLOOKUP(H41,'引用数据库'!N:P,3,FALSE)&VLOOKUP(I41,'引用数据库'!S:U,3,FALSE)&TEXT(F41,"00")) | E41: 劳旅 | F41: 2 | G41: =G40 | H41: =H40 | I41: =I40 | J41: 手动 | K41: =K40 | M41: =M40 | N41: 800 | O41: N/A | P41: 0 | Q41: 0 | R41: 0.3 | S41: 0 | T41: =SUM(P41:S41) | U41: =2*T41/(15*(1+(5-BD41)*0.1)) | W41: =W40 | X41: =X40 | Y41: 0.25 | Z41: 0.25 | AA41: 0 | AB41: 0 | AC41: 1 | AD41: =(W41+AB41)*AC41 | AE41: =(X41+AB41)*AC41 | AJ41: =AJ40+0.05 | AK41: =AK40+0.05 | AL41: =AL40 | AM41: =IFS(AJ41 > 1.25, "S", AJ41 > 1, "A", AJ41 > 0.75, "B", AJ41 > 0.5, "C", AJ41 > 0.25, "D", AJ41 > 0, "E", TRUE, "-") | AN41: =IFS(AK41 > 1.25, "S", AK41 > 1, "A", AK41 > 0.75, "B", AK41 > 0.5, "C", AK41 > 0.25, "D", AK41 > 0, "E", TRUE, "-") | AO41: =IFS(AL41 > 1.25, "S", AL41 > 1, "A", AL41 > 0.75, "B", AL41 > 0.5, "C", AL41 > 0.25, "D", AL41 > 0, "E", TRUE, "-") | AP41: 10 | AQ41: 10 | AR41: 10 | AV41: =IF(SUM(AJ41:AL41)=0, 0, (1 + F41 * 0.1) * (0.75 + 0.25 * MAX(0, MIN(1, IF(MAX(AJ41:AL41)=0, 0, (3*MAX(AJ41:AL41)-SUM(AJ41:AL41)) / (2*MAX(AJ41:AL41))))))) | AW41: =MAX(AJ41:AL41) | AX41: =IF(AW41=0, "", AW41 / ((1 + 0.1*N(F41)))) | AY41: =IF(SUM(AJ41:AL41)=0, 0, (1 + F41 * 0.1) * (1 + ((SUM(AJ41:AL41) - MAX(AJ41:AL41)) / (2 * MAX(AJ41:AL41))) * (1/0.75 - 1))) | AZ41: =AJ41+AK41+AL41 | BA41: =IF(AZ41=0, "", AZ41 / ((1 + 0.1*N(F41))/0.75)) | BB41: 0.1 | BD41: =BD40 | BE41: =BE40 | BH41: =BH40 | BL41: =BL40 | BN41: =BN40 | BO41: 2 | BQ41: =BQ40 | BR41: =IFERROR(BQ41*100/CP41,"N/A") | BS41: =BS40 | BT41: =BT40 | BW41: =BW40 | BX41: =CP41/BW41 | BY41: =BW41/T41 | CA41: =CA40+10 | CB41: =CA41*BB41*(AP41*AJ41+AQ41*AK41+AR41*AL41) | CC41: =CA41+CB41 | CK41: =CK40 | CN41: =CK41*CC41 | CP41: =CN41*BS41*BT41 | CQ41: =CP41/T41 | CR41: =100/CP41 | CS41: =100/CQ41 | CT41: =CQ41-CQ40 | CU41: =(CQ41-CQ40)/CQ40 | CV41: =BL41/T41 | CW41: =100/CV41 | DC41: 完成 | DD41: 完成
A42: =A41 | B42: =B41 | D42: =IF($A42="","","WPN"&VLOOKUP(E42,'引用数据库'!Z:AC,4,FALSE)&VLOOKUP(H42,'引用数据库'!N:P,3,FALSE)&VLOOKUP(I42,'引用数据库'!S:U,3,FALSE)&TEXT(F42,"00")) | E42: 劳旅 | F42: 3 | G42: =G41 | H42: =H41 | I42: =I41 | J42: 手动 | K42: =K41 | M42: =M41 | N42: 800 | O42: N/A | P42: 0 | Q42: 0 | R42: 0.3 | S42: 0 | T42: =SUM(P42:S42) | U42: =2*T42/(15*(1+(5-BD42)*0.1)) | W42: =W41 | X42: =X41 | Y42: 0.25 | Z42: 0.25 | AA42: 0 | AB42: 0 | AC42: 1 | AD42: =(W42+AB42)*AC42 | AE42: =(X42+AB42)*AC42 | AJ42: 0.35 | AK42: =AK41+0.1 | AL42: =AL41 | AM42: =IFS(AJ42 > 1.25, "S", AJ42 > 1, "A", AJ42 > 0.75, "B", AJ42 > 0.5, "C", AJ42 > 0.25, "D", AJ42 > 0, "E", TRUE, "-") | AN42: =IFS(AK42 > 1.25, "S", AK42 > 1, "A", AK42 > 0.75, "B", AK42 > 0.5, "C", AK42 > 0.25, "D", AK42 > 0, "E", TRUE, "-") | AO42: =IFS(AL42 > 1.25, "S", AL42 > 1, "A", AL42 > 0.75, "B", AL42 > 0.5, "C", AL42 > 0.25, "D", AL42 > 0, "E", TRUE, "-") | AP42: 10 | AQ42: 10 | AR42: 10 | AV42: =IF(SUM(AJ42:AL42)=0, 0, (1 + F42 * 0.1) * (0.75 + 0.25 * MAX(0, MIN(1, IF(MAX(AJ42:AL42)=0, 0, (3*MAX(AJ42:AL42)-SUM(AJ42:AL42)) / (2*MAX(AJ42:AL42))))))) | AW42: =MAX(AJ42:AL42) | AX42: =IF(AW42=0, "", AW42 / ((1 + 0.1*N(F42)))) | AY42: =IF(SUM(AJ42:AL42)=0, 0, (1 + F42 * 0.1) * (1 + ((SUM(AJ42:AL42) - MAX(AJ42:AL42)) / (2 * MAX(AJ42:AL42))) * (1/0.75 - 1))) | AZ42: =AJ42+AK42+AL42 | BA42: =IF(AZ42=0, "", AZ42 / ((1 + 0.1*N(F42))/0.75)) | BB42: 0.1 | BD42: =BD41 | BE42: =BE41 | BH42: =BH41 | BL42: =BL41 | BN42: =BN41 | BO42: 2 | BQ42: =BQ41 | BR42: =IFERROR(BQ42*100/CP42,"N/A") | BS42: =BS41 | BT42: =BT41 | BW42: =BW41 | BX42: =CP42/BW42 | BY42: =BW42/T42 | CA42: =CA41+10 | CB42: =CA42*BB42*(AP42*AJ42+AQ42*AK42+AR42*AL42) | CC42: =CA42+CB42 | CK42: =CK41 | CN42: =CK42*CC42 | CP42: =CN42*BS42*BT42 | CQ42: =CP42/T42 | CR42: =100/CP42 | CS42: =100/CQ42 | CT42: =CQ42-CQ41 | CU42: =(CQ42-CQ41)/CQ41 | CV42: =BL42/T42 | CW42: =100/CV42 | DC42: 完成 | DD42: 完成
A43: =A42 | B43: =B42 | D43: =IF($A43="","","WPN"&VLOOKUP(E43,'引用数据库'!Z:AC,4,FALSE)&VLOOKUP(H43,'引用数据库'!N:P,3,FALSE)&VLOOKUP(I43,'引用数据库'!S:U,3,FALSE)&TEXT(F43,"00")) | E43: 劳旅 | F43: 4 | G43: =G42 | H43: =H42 | I43: =I42 | J43: 手动 | K43: =K42 | M43: =M42 | N43: 800 | O43: N/A | P43: 0 | Q43: 0 | R43: 0.3 | S43: 0 | T43: =SUM(P43:S43) | U43: =2*T43/(15*(1+(5-BD43)*0.1)) | W43: =W42 | X43: =X42 | Y43: 0.25 | Z43: 0.25 | AA43: 0 | AB43: 0 | AC43: 1 | AD43: =(W43+AB43)*AC43 | AE43: =(X43+AB43)*AC43 | AJ43: 0.35 | AK43: =AK42+0.1 | AL43: =AL42 | AM43: =IFS(AJ43 > 1.25, "S", AJ43 > 1, "A", AJ43 > 0.75, "B", AJ43 > 0.5, "C", AJ43 > 0.25, "D", AJ43 > 0, "E", TRUE, "-") | AN43: =IFS(AK43 > 1.25, "S", AK43 > 1, "A", AK43 > 0.75, "B", AK43 > 0.5, "C", AK43 > 0.25, "D", AK43 > 0, "E", TRUE, "-") | AO43: =IFS(AL43 > 1.25, "S", AL43 > 1, "A", AL43 > 0.75, "B", AL43 > 0.5, "C", AL43 > 0.25, "D", AL43 > 0, "E", TRUE, "-") | AP43: 10 | AQ43: 10 | AR43: 10 | AV43: =IF(SUM(AJ43:AL43)=0, 0, (1 + F43 * 0.1) * (0.75 + 0.25 * MAX(0, MIN(1, IF(MAX(AJ43:AL43)=0, 0, (3*MAX(AJ43:AL43)-SUM(AJ43:AL43)) / (2*MAX(AJ43:AL43))))))) | AW43: =MAX(AJ43:AL43) | AX43: =IF(AW43=0, "", AW43 / ((1 + 0.1*N(F43)))) | AY43: =IF(SUM(AJ43:AL43)=0, 0, (1 + F43 * 0.1) * (1 + ((SUM(AJ43:AL43) - MAX(AJ43:AL43)) / (2 * MAX(AJ43:AL43))) * (1/0.75 - 1))) | AZ43: =AJ43+AK43+AL43 | BA43: =IF(AZ43=0, "", AZ43 / ((1 + 0.1*N(F43))/0.75)) | BB43: 0.1 | BD43: =BD42 | BE43: =BE42 | BH43: =BH42 | BL43: =BL42 | BN43: =BN42 | BO43: 2 | BQ43: =BQ42 | BR43: =IFERROR(BQ43*100/CP43,"N/A") | BS43: =BS42 | BT43: =BT42 | BW43: =BW42 | BX43: =CP43/BW43 | BY43: =BW43/T43 | CA43: =CA42+10 | CB43: =CA43*BB43*(AP43*AJ43+AQ43*AK43+AR43*AL43) | CC43: =CA43+CB43 | CK43: =CK42 | CN43: =CK43*CC43 | CP43: =CN43*BS43*BT43 | CQ43: =CP43/T43 | CR43: =100/CP43 | CS43: =100/CQ43 | CT43: =CQ43-CQ42 | CU43: =(CQ43-CQ42)/CQ42 | CV43: =BL43/T43 | CW43: =100/CV43 | DC43: 完成 | DD43: 完成
A44: =A43 | B44: =B43 | D44: =IF($A44="","","WPN"&VLOOKUP(E44,'引用数据库'!Z:AC,4,FALSE)&VLOOKUP(H44,'引用数据库'!N:P,3,FALSE)&VLOOKUP(I44,'引用数据库'!S:U,3,FALSE)&TEXT(F44,"00")) | E44: 劳旅 | F44: 5 | G44: =G43 | H44: =H43 | I44: =I43 | J44: 手动 | K44: =K43 | M44: =M43 | N44: 800 | O44: N/A | P44: 0 | Q44: 0 | R44: 0.3 | S44: 0 | T44: =SUM(P44:S44) | U44: =2*T44/(15*(1+(5-BD44)*0.1)) | W44: =W43 | X44: =X43 | Y44: 0.25 | Z44: 0.25 | AA44: 0 | AB44: 0 | AC44: 1 | AD44: =(W44+AB44)*AC44 | AE44: =(X44+AB44)*AC44 | AJ44: 0.35 | AK44: 1 | AL44: =AL43 | AM44: =IFS(AJ44 > 1.25, "S", AJ44 > 1, "A", AJ44 > 0.75, "B", AJ44 > 0.5, "C", AJ44 > 0.25, "D", AJ44 > 0, "E", TRUE, "-") | AN44: =IFS(AK44 > 1.25, "S", AK44 > 1, "A", AK44 > 0.75, "B", AK44 > 0.5, "C", AK44 > 0.25, "D", AK44 > 0, "E", TRUE, "-") | AO44: =IFS(AL44 > 1.25, "S", AL44 > 1, "A", AL44 > 0.75, "B", AL44 > 0.5, "C", AL44 > 0.25, "D", AL44 > 0, "E", TRUE, "-") | AP44: 10 | AQ44: 10 | AR44: 10 | AV44: =IF(SUM(AJ44:AL44)=0, 0, (1 + F44 * 0.1) * (0.75 + 0.25 * MAX(0, MIN(1, IF(MAX(AJ44:AL44)=0, 0, (3*MAX(AJ44:AL44)-SUM(AJ44:AL44)) / (2*MAX(AJ44:AL44))))))) | AW44: =MAX(AJ44:AL44) | AX44: =IF(AW44=0, "", AW44 / ((1 + 0.1*N(F44)))) | AY44: =IF(SUM(AJ44:AL44)=0, 0, (1 + F44 * 0.1) * (1 + ((SUM(AJ44:AL44) - MAX(AJ44:AL44)) / (2 * MAX(AJ44:AL44))) * (1/0.75 - 1))) | AZ44: =AJ44+AK44+AL44 | BA44: =IF(AZ44=0, "", AZ44 / ((1 + 0.1*N(F44))/0.75)) | BB44: 0.1 | BD44: =BD43 | BE44: =BE43 | BH44: =BH43 | BL44: =BL43 | BN44: =BN43 | BO44: 2 | BQ44: =BQ43 | BR44: =IFERROR(BQ44*100/CP44,"N/A") | BS44: =BS43 | BT44: =BT43 | BW44: =BW43 | BX44: =CP44/BW44 | BY44: =BW44/T44 | CA44: =CA43+10 | CB44: =CA44*BB44*(AP44*AJ44+AQ44*AK44+AR44*AL44) | CC44: =CA44+CB44 | CK44: =CK43 | CN44: =CK44*CC44 | CP44: =CN44*BS44*BT44 | CQ44: =CP44/T44 | CR44: =100/CP44 | CS44: =100/CQ44 | CT44: =CQ44-CQ43 | CU44: =(CQ44-CQ43)/CQ43 | CV44: =BL44/T44 | CW44: =100/CV44 | DC44: 完成 | DD44: 完成
A45: NailGun | B45: 盲孔开颅器 | D45: =IF($A45="","","WPN"&VLOOKUP(E45,'引用数据库'!Z:AC,4,FALSE)&VLOOKUP(H45,'引用数据库'!N:P,3,FALSE)&VLOOKUP(I45,'引用数据库'!S:U,3,FALSE)&TEXT(F45,"00")) | E45: 劳旅 | F45: 0 | G45: 远程 | H45: 手枪 | I45: 动能 | J45: 手动 | K45: 1 | M45: 1 | N45: =N46 | O45: N/A | P45: 0 | Q45: 0 | R45: 0.25 | S45: 0 | T45: =SUM(P45:S45) | U45: =2*T45/(15*(1+(5-BD45)*0.1)) | W45: 0 | X45: 10 | Y45: 0.16 | Z45: 0.08 | AB45: 5 | AC45: 1.5 | AD45: =(W45+AB45)*AC45 | AE45: =(X45+AB45)*AC45 | AJ45: 0 | AK45: 0.75 | AL45: 0.3 | AM45: =IFS(AJ45 > 1.25, "S", AJ45 > 1, "A", AJ45 > 0.75, "B", AJ45 > 0.5, "C", AJ45 > 0.25, "D", AJ45 > 0, "E", TRUE, "-") | AN45: =IFS(AK45 > 1.25, "S", AK45 > 1, "A", AK45 > 0.75, "B", AK45 > 0.5, "C", AK45 > 0.25, "D", AK45 > 0, "E", TRUE, "-") | AO45: =IFS(AL45 > 1.25, "S", AL45 > 1, "A", AL45 > 0.75, "B", AL45 > 0.5, "C", AL45 > 0.25, "D", AL45 > 0, "E", TRUE, "-") | AP45: 10 | AQ45: 10 | AR45: 10 | AV45: =IF(SUM(AJ45:AL45)=0, 0, (1 + F45 * 0.1) * (0.75 + 0.25 * MAX(0, MIN(1, IF(MAX(AJ45:AL45)=0, 0, (3*MAX(AJ45:AL45)-SUM(AJ45:AL45)) / (2*MAX(AJ45:AL45))))))) | AW45: =MAX(AJ45:AL45) | AX45: =IF(AW45=0, "", AW45 / ((1 + 0.1*N(F45)))) | AY45: =IF(SUM(AJ45:AL45)=0, 0, (1 + F45 * 0.1) * (1 + ((SUM(AJ45:AL45) - MAX(AJ45:AL45)) / (2 * MAX(AJ45:AL45))) * (1/0.75 - 1))) | AZ45: =AJ45+AK45+AL45 | BA45: =IF(AZ45=0, "", AZ45 / ((1 + 0.1*N(F45))/0.75)) | BB45: 0.1 | BD45: 1 | BE45: 1 | BF45: 2 | BG45: =T45 * 4 * BF45 / BT45 / BS45 | BH45: =BG45 | BJ45: 2 | BK45: =T45*33*(16 * BJ45) / (15 + 20 * BJ45 - 3 * POWER(BJ45, 2))/BT45 | BL45: =BK45 | BN45: 30 | BO45: 3 | BP45: =ROUND(CP45/10,2) | BQ45: 0.5 | BR45: =IFERROR(BQ45*100/CP45,"N/A") | BS45: 1 | BT45: 1 | BV45: =CP45/1.5 | BW45: =ROUND(BV45) | BX45: =CP45/BW45 | BY45: =BW45/T45 | CA45: 10 | CB45: =CA45*BB45*(AP45*AJ45+AQ45*AK45+AR45*AL45) | CC45: =CA45+CB45 | CD45: =T45 * 2 / BS45 / BT45 * (0.9 + 0.2 * IF(G45="近战", EXP(-64 * (T45 - 0.75)^2), EXP(-400 * (T45 - 0.15)^2))) | CE45: =0.9 + 0.2 / (1 + (N45/600)^1) | CF45: =LET( k, K45, be, BS45, bf, BT45, m, N45, n, O45, v, X45, vEff, IF(ISNUMBER(v), v, 0), angle, IF( ISNUMBER(n), IF(n>0, n, IF(ISNUMBER(v), IF(v>0, v, 0), 0 ) ), IF(ISNUMBER(v), IF(v>0, v, 0), 0 ) ), T, IF(k=1, be * bf * 20 / MAX(vEff, 1), IF(k=2, (m/150)^2 * (angle/120), IF(k=3, be * (MIN(bf, 99)/99) * (m/1000), be * bf * (m/1000) * (n/200)^2 ))), b, 0.8, c, 1.2, r, (c-1)/(1-b), k_s, 1, b + (c-b) / (1 + r * EXP(-k_s*(1-T)))) | CG45: =IF(T45<=0,1, (0.9 + 0.2 / (1 + EXP(-0.8 * (5 - BD45)))) * (0.9 + 0.2 / (1 + EXP(-1 * (3.5 - BE45)))) * (0.9 + 0.2 / (1 + EXP(-0.6 * (20 - BS45*BH45/T45))))) | CH45: =IF(T45<=0, 1, 0.9 + 0.2 / (1 + EXP(0.1 * (BL45*BS45*BT45/T45 - 33)))) | CI45: =LET( x_val, W45, bq_val, BS45, Check_Fail, OR(NOT(ISNUMBER(x_val)), bq_val <= 1), IF(Check_Fail, 1, LET( Ratio, x_val / bq_val, calc_A, 2.2 / (1 + EXP(-0.276 * (Ratio - 0.66))), calc_B, 2.2 / (1 + EXP(-0.0138 * (x_val - 13.2))), calc_A + calc_B ) )) | CJ45: =CD45*CE45*CF45*CG45*CH45*CI45 | CK45: =CJ45 | CL45: =T45 * 2 / BS45 / BT45 | CM45: =CK45/CL45 | CN45: =CK45*CC45 | CP45: =CN45*BS45*BT45 | CQ45: =CP45/T45 | CR45: =100/CP45 | CS45: =100/CQ45 | CV45: =BL45/T45 | CW45: =100/CV45 | CY45: 主要靠磁力进行驱动的射钉枪， 在模块化纤维大厦盛行的都市上层几乎绝迹。 由于贫民窟中临时住宅对钉接的旺盛需求， 加上当做武器时在街头械斗中的优异表现， 导致其在都市下层依旧拥有超高人气。 | DA45: =TEXTJOIN("、", TRUE, FILTER('武器技能'!B:B, '武器技能'!E:E = H45)) | DC45: 完成 | DD45: 完成
A46: NailGun | B46: 盲孔开颅器 | D46: =IF($A46="","","WPN"&VLOOKUP(E46,'引用数据库'!Z:AC,4,FALSE)&VLOOKUP(H46,'引用数据库'!N:P,3,FALSE)&VLOOKUP(I46,'引用数据库'!S:U,3,FALSE)&TEXT(F46,"00")) | E46: 劳旅 | F46: 1 | G46: =G45 | H46: =H45 | I46: =I45 | J46: 手动 | K46: =K45 | M46: =M45 | N46: 800 | O46: N/A | P46: 0 | Q46: 0 | R46: 0.25 | S46: 0 | T46: =SUM(P46:S46) | U46: =2*T46/(15*(1+(5-BD46)*0.1)) | W46: 0 | X46: 10 | Y46: 0.16 | Z46: 0.08 | AB46: 5 | AC46: 1.5 | AD46: =(W46+AB46)*AC46 | AE46: =(X46+AB46)*AC46 | AJ46: 0.1 | AK46: 0.8 | AL46: =AL45 | AM46: =IFS(AJ46 > 1.25, "S", AJ46 > 1, "A", AJ46 > 0.75, "B", AJ46 > 0.5, "C", AJ46 > 0.25, "D", AJ46 > 0, "E", TRUE, "-") | AN46: =IFS(AK46 > 1.25, "S", AK46 > 1, "A", AK46 > 0.75, "B", AK46 > 0.5, "C", AK46 > 0.25, "D", AK46 > 0, "E", TRUE, "-") | AO46: =IFS(AL46 > 1.25, "S", AL46 > 1, "A", AL46 > 0.75, "B", AL46 > 0.5, "C", AL46 > 0.25, "D", AL46 > 0, "E", TRUE, "-") | AP46: 10 | AQ46: 10 | AR46: 10 | AV46: =IF(SUM(AJ46:AL46)=0, 0, (1 + F46 * 0.1) * (0.75 + 0.25 * MAX(0, MIN(1, IF(MAX(AJ46:AL46)=0, 0, (3*MAX(AJ46:AL46)-SUM(AJ46:AL46)) / (2*MAX(AJ46:AL46))))))) | AW46: =MAX(AJ46:AL46) | AX46: =IF(AW46=0, "", AW46 / ((1 + 0.1*N(F46)))) | AY46: =IF(SUM(AJ46:AL46)=0, 0, (1 + F46 * 0.1) * (1 + ((SUM(AJ46:AL46) - MAX(AJ46:AL46)) / (2 * MAX(AJ46:AL46))) * (1/0.75 - 1))) | AZ46: =AJ46+AK46+AL46 | BA46: =IF(AZ46=0, "", AZ46 / ((1 + 0.1*N(F46))/0.75)) | BB46: 0.1 | BD46: =BD45 | BE46: =BE45 | BF46: 参考值 | BH46: =BH45 | BL46: =BL45 | BN46: 30 | BO46: 3 | BQ46: =BQ45 | BR46: =IFERROR(BQ46*100/CP46,"N/A") | BS46: 1 | BT46: 1 | BW46: =BW45 | BX46: =CP46/BW46 | BY46: =BW46/T46 | CA46: =CA45+20 | CB46: =CA46*BB46*(AP46*AJ46+AQ46*AK46+AR46*AL46) | CC46: =CA46+CB46 | CK46: =CK45 | CN46: =CK46*CC46 | CP46: =CN46*BS46*BT46 | CQ46: =CP46/T46 | CR46: =100/CP46 | CS46: =100/CQ46 | CT46: =CQ46-CQ45 | CU46: =(CQ46-CQ45)/CQ45 | CV46: =BL46/T46 | CW46: =100/CV46 | DC46: 完成 | DD46: 完成
A47: NailGun | B47: 盲孔开颅器 | D47: =IF($A47="","","WPN"&VLOOKUP(E47,'引用数据库'!Z:AC,4,FALSE)&VLOOKUP(H47,'引用数据库'!N:P,3,FALSE)&VLOOKUP(I47,'引用数据库'!S:U,3,FALSE)&TEXT(F47,"00")) | E47: 劳旅 | F47: 2 | G47: =G46 | H47: =H46 | I47: =I46 | J47: 手动 | K47: =K46 | M47: =M46 | N47: =N46 | O47: N/A | P47: 0 | Q47: 0 | R47: 0.25 | S47: 0 | T47: =SUM(P47:S47) | U47: =2*T47/(15*(1+(5-BD47)*0.1)) | W47: 0 | X47: 10 | Y47: 0.16 | Z47: 0.08 | AB47: 5 | AC47: 1.5 | AD47: =(W47+AB47)*AC47 | AE47: =(X47+AB47)*AC47 | AJ47: =AJ46 | AK47: =AK46+0.05 | AL47: =AL46 | AM47: =IFS(AJ47 > 1.25, "S", AJ47 > 1, "A", AJ47 > 0.75, "B", AJ47 > 0.5, "C", AJ47 > 0.25, "D", AJ47 > 0, "E", TRUE, "-") | AN47: =IFS(AK47 > 1.25, "S", AK47 > 1, "A", AK47 > 0.75, "B", AK47 > 0.5, "C", AK47 > 0.25, "D", AK47 > 0, "E", TRUE, "-") | AO47: =IFS(AL47 > 1.25, "S", AL47 > 1, "A", AL47 > 0.75, "B", AL47 > 0.5, "C", AL47 > 0.25, "D", AL47 > 0, "E", TRUE, "-") | AP47: 10 | AQ47: 10 | AR47: 10 | AV47: =IF(SUM(AJ47:AL47)=0, 0, (1 + F47 * 0.1) * (0.75 + 0.25 * MAX(0, MIN(1, IF(MAX(AJ47:AL47)=0, 0, (3*MAX(AJ47:AL47)-SUM(AJ47:AL47)) / (2*MAX(AJ47:AL47))))))) | AW47: =MAX(AJ47:AL47) | AX47: =IF(AW47=0, "", AW47 / ((1 + 0.1*N(F47)))) | AY47: =IF(SUM(AJ47:AL47)=0, 0, (1 + F47 * 0.1) * (1 + ((SUM(AJ47:AL47) - MAX(AJ47:AL47)) / (2 * MAX(AJ47:AL47))) * (1/0.75 - 1))) | AZ47: =AJ47+AK47+AL47 | BA47: =IF(AZ47=0, "", AZ47 / ((1 + 0.1*N(F47))/0.75)) | BB47: 0.1 | BD47: =BD46 | BE47: =BE46 | BF47: 性价比 | BH47: =BH46 | BL47: =BL46 | BN47: 30 | BO47: 3 | BQ47: =BQ46 | BR47: =IFERROR(BQ47*100/CP47,"N/A") | BS47: 1 | BT47: 1 | BW47: =BW46 | BX47: =CP47/BW47 | BY47: =BW47/T47 | CA47: =CA46+10 | CB47: =CA47*BB47*(AP47*AJ47+AQ47*AK47+AR47*AL47) | CC47: =CA47+CB47 | CK47: =CK46 | CN47: =CK47*CC47 | CP47: =CN47*BS47*BT47 | CQ47: =CP47/T47 | CR47: =100/CP47 | CS47: =100/CQ47 | CT47: =CQ47-CQ46 | CU47: =(CQ47-CQ46)/CQ46 | CV47: =BL47/T47 | CW47: =100/CV47 | DC47: 完成 | DD47: 完成
A48: NailGun | B48: 盲孔开颅器 | D48: =IF($A48="","","WPN"&VLOOKUP(E48,'引用数据库'!Z:AC,4,FALSE)&VLOOKUP(H48,'引用数据库'!N:P,3,FALSE)&VLOOKUP(I48,'引用数据库'!S:U,3,FALSE)&TEXT(F48,"00")) | E48: 劳旅 | F48: 3 | G48: =G47 | H48: =H47 | I48: =I47 | J48: 手动 | K48: =K47 | M48: =M47 | N48: =N47 | O48: N/A | P48: 0 | Q48: 0 | R48: 0.25 | S48: 0 | T48: =SUM(P48:S48) | U48: =2*T48/(15*(1+(5-BD48)*0.1)) | W48: 0 | X48: 10 | Y48: 0.16 | Z48: 0.08 | AB48: 5 | AC48: 1.5 | AD48: =(W48+AB48)*AC48 | AE48: =(X48+AB48)*AC48 | AJ48: =AJ47 | AK48: =AK47+0.05 | AL48: 0.4 | AM48: =IFS(AJ48 > 1.25, "S", AJ48 > 1, "A", AJ48 > 0.75, "B", AJ48 > 0.5, "C", AJ48 > 0.25, "D", AJ48 > 0, "E", TRUE, "-") | AN48: =IFS(AK48 > 1.25, "S", AK48 > 1, "A", AK48 > 0.75, "B", AK48 > 0.5, "C", AK48 > 0.25, "D", AK48 > 0, "E", TRUE, "-") | AO48: =IFS(AL48 > 1.25, "S", AL48 > 1, "A", AL48 > 0.75, "B", AL48 > 0.5, "C", AL48 > 0.25, "D", AL48 > 0, "E", TRUE, "-") | AP48: 10 | AQ48: 10 | AR48: 10 | AV48: =IF(SUM(AJ48:AL48)=0, 0, (1 + F48 * 0.1) * (0.75 + 0.25 * MAX(0, MIN(1, IF(MAX(AJ48:AL48)=0, 0, (3*MAX(AJ48:AL48)-SUM(AJ48:AL48)) / (2*MAX(AJ48:AL48))))))) | AW48: =MAX(AJ48:AL48) | AX48: =IF(AW48=0, "", AW48 / ((1 + 0.1*N(F48)))) | AY48: =IF(SUM(AJ48:AL48)=0, 0, (1 + F48 * 0.1) * (1 + ((SUM(AJ48:AL48) - MAX(AJ48:AL48)) / (2 * MAX(AJ48:AL48))) * (1/0.75 - 1))) | AZ48: =AJ48+AK48+AL48 | BA48: =IF(AZ48=0, "", AZ48 / ((1 + 0.1*N(F48))/0.75)) | BB48: 0.1 | BD48: =BD47 | BE48: =BE47 | BH48: =BH47 | BL48: =BL47 | BN48: 30 | BO48: 3 | BQ48: =BQ47 | BR48: =IFERROR(BQ48*100/CP48,"N/A") | BS48: 1 | BT48: 1 | BW48: =BW47 | BX48: =CP48/BW48 | BY48: =BW48/T48 | CA48: =CA47+10 | CB48: =CA48*BB48*(AP48*AJ48+AQ48*AK48+AR48*AL48) | CC48: =CA48+CB48 | CK48: =CK47 | CN48: =CK48*CC48 | CP48: =CN48*BS48*BT48 | CQ48: =CP48/T48 | CR48: =100/CP48 | CS48: =100/CQ48 | CT48: =CQ48-CQ47 | CU48: =(CQ48-CQ47)/CQ47 | CV48: =BL48/T48 | CW48: =100/CV48 | DC48: 完成 | DD48: 完成
A49: NailGun | B49: 盲孔开颅器 | D49: =IF($A49="","","WPN"&VLOOKUP(E49,'引用数据库'!Z:AC,4,FALSE)&VLOOKUP(H49,'引用数据库'!N:P,3,FALSE)&VLOOKUP(I49,'引用数据库'!S:U,3,FALSE)&TEXT(F49,"00")) | E49: 劳旅 | F49: 4 | G49: =G48 | H49: =H48 | I49: =I48 | J49: 手动 | K49: =K48 | M49: =M48 | N49: =N48 | O49: N/A | P49: 0 | Q49: 0 | R49: 0.25 | S49: 0 | T49: =SUM(P49:S49) | U49: =2*T49/(15*(1+(5-BD49)*0.1)) | W49: 0 | X49: 10 | Y49: 0.16 | Z49: 0.08 | AB49: 5 | AC49: 1.5 | AD49: =(W49+AB49)*AC49 | AE49: =(X49+AB49)*AC49 | AJ49: =AJ48 | AK49: 1 | AL49: 0.42 | AM49: =IFS(AJ49 > 1.25, "S", AJ49 > 1, "A", AJ49 > 0.75, "B", AJ49 > 0.5, "C", AJ49 > 0.25, "D", AJ49 > 0, "E", TRUE, "-") | AN49: =IFS(AK49 > 1.25, "S", AK49 > 1, "A", AK49 > 0.75, "B", AK49 > 0.5, "C", AK49 > 0.25, "D", AK49 > 0, "E", TRUE, "-") | AO49: =IFS(AL49 > 1.25, "S", AL49 > 1, "A", AL49 > 0.75, "B", AL49 > 0.5, "C", AL49 > 0.25, "D", AL49 > 0, "E", TRUE, "-") | AP49: 10 | AQ49: 10 | AR49: 10 | AV49: =IF(SUM(AJ49:AL49)=0, 0, (1 + F49 * 0.1) * (0.75 + 0.25 * MAX(0, MIN(1, IF(MAX(AJ49:AL49)=0, 0, (3*MAX(AJ49:AL49)-SUM(AJ49:AL49)) / (2*MAX(AJ49:AL49))))))) | AW49: =MAX(AJ49:AL49) | AX49: =IF(AW49=0, "", AW49 / ((1 + 0.1*N(F49)))) | AY49: =IF(SUM(AJ49:AL49)=0, 0, (1 + F49 * 0.1) * (1 + ((SUM(AJ49:AL49) - MAX(AJ49:AL49)) / (2 * MAX(AJ49:AL49))) * (1/0.75 - 1))) | AZ49: =AJ49+AK49+AL49 | BA49: =IF(AZ49=0, "", AZ49 / ((1 + 0.1*N(F49))/0.75)) | BB49: 0.1 | BD49: =BD48 | BE49: =BE48 | BH49: =BH48 | BL49: =BL48 | BN49: 30 | BO49: 3 | BQ49: =BQ48 | BR49: =IFERROR(BQ49*100/CP49,"N/A") | BS49: 1 | BT49: 1 | BW49: =BW48 | BX49: =CP49/BW49 | BY49: =BW49/T49 | CA49: =CA48+10 | CB49: =CA49*BB49*(AP49*AJ49+AQ49*AK49+AR49*AL49) | CC49: =CA49+CB49 | CK49: =CK48 | CN49: =CK49*CC49 | CP49: =CN49*BS49*BT49 | CQ49: =CP49/T49 | CR49: =100/CP49 | CS49: =100/CQ49 | CT49: =CQ49-CQ48 | CU49: =(CQ49-CQ48)/CQ48 | CV49: =BL49/T49 | CW49: =100/CV49 | DC49: 完成 | DD49: 完成
A50: NailGun | B50: 盲孔开颅器 | D50: =IF($A50="","","WPN"&VLOOKUP(E50,'引用数据库'!Z:AC,4,FALSE)&VLOOKUP(H50,'引用数据库'!N:P,3,FALSE)&VLOOKUP(I50,'引用数据库'!S:U,3,FALSE)&TEXT(F50,"00")) | E50: 劳旅 | F50: 5 | G50: =G49 | H50: =H49 | I50: =I49 | J50: 手动 | K50: =K49 | M50: =M49 | N50: =N49 | O50: N/A | P50: 0 | Q50: 0 | R50: 0.25 | S50: 0 | T50: =SUM(P50:S50) | U50: =2*T50/(15*(1+(5-BD50)*0.1)) | W50: 0 | X50: 10 | Y50: 0.16 | Z50: 0.08 | AB50: 5 | AC50: 1.5 | AD50: =(W50+AB50)*AC50 | AE50: =(X50+AB50)*AC50 | AJ50: =AJ49 | AK50: 1.1 | AL50: =AL49 | AM50: =IFS(AJ50 > 1.25, "S", AJ50 > 1, "A", AJ50 > 0.75, "B", AJ50 > 0.5, "C", AJ50 > 0.25, "D", AJ50 > 0, "E", TRUE, "-") | AN50: =IFS(AK50 > 1.25, "S", AK50 > 1, "A", AK50 > 0.75, "B", AK50 > 0.5, "C", AK50 > 0.25, "D", AK50 > 0, "E", TRUE, "-") | AO50: =IFS(AL50 > 1.25, "S", AL50 > 1, "A", AL50 > 0.75, "B", AL50 > 0.5, "C", AL50 > 0.25, "D", AL50 > 0, "E", TRUE, "-") | AP50: 10 | AQ50: 10 | AR50: 10 | AV50: =IF(SUM(AJ50:AL50)=0, 0, (1 + F50 * 0.1) * (0.75 + 0.25 * MAX(0, MIN(1, IF(MAX(AJ50:AL50)=0, 0, (3*MAX(AJ50:AL50)-SUM(AJ50:AL50)) / (2*MAX(AJ50:AL50))))))) | AW50: =MAX(AJ50:AL50) | AX50: =IF(AW50=0, "", AW50 / ((1 + 0.1*N(F50)))) | AY50: =IF(SUM(AJ50:AL50)=0, 0, (1 + F50 * 0.1) * (1 + ((SUM(AJ50:AL50) - MAX(AJ50:AL50)) / (2 * MAX(AJ50:AL50))) * (1/0.75 - 1))) | AZ50: =AJ50+AK50+AL50 | BA50: =IF(AZ50=0, "", AZ50 / ((1 + 0.1*N(F50))/0.75)) | BB50: 0.1 | BD50: =BD49 | BE50: =BE49 | BH50: =BH49 | BL50: =BL49 | BN50: 30 | BO50: 3 | BQ50: =BQ49 | BR50: =IFERROR(BQ50*100/CP50,"N/A") | BS50: 1 | BT50: 1 | BW50: =BW49 | BX50: =CP50/BW50 | BY50: =BW50/T50 | CA50: =CA49+10 | CB50: =CA50*BB50*(AP50*AJ50+AQ50*AK50+AR50*AL50) | CC50: =CA50+CB50 | CK50: =CK49 | CN50: =CK50*CC50 | CP50: =CN50*BS50*BT50 | CQ50: =CP50/T50 | CR50: =100/CP50 | CS50: =100/CQ50 | CT50: =CQ50-CQ49 | CU50: =(CQ50-CQ49)/CQ49 | CV50: =BL50/T50 | CW50: =100/CV50 | DC50: 完成 | DD50: 完成
A51: Injection King | B51: 加注王 | D51: =IF($A51="","","WPN"&VLOOKUP(E51,'引用数据库'!Z:AC,4,FALSE)&VLOOKUP(H51,'引用数据库'!N:P,3,FALSE)&VLOOKUP(I51,'引用数据库'!S:U,3,FALSE)&TEXT(F51,"00")) | E51: 劳旅 | F51: 0 | G51: 远程 | H51: 喷射器 | I51: 热能 | J51: 手动 | K51: 2 | M51: =0.4 + (T51 / (T51 + 0.2)) * 0.4 | N51: 400 | O51: N/A | P51: 0 | Q51: 0.05 | R51: 0 | S51: 0 | T51: =SUM(P51:S51) | U51: =2*T51/(15*(1+(5-BD51)*0.1)) | W51: 120 | X51: 120 | Y51: 0 | Z51: 0 | AB51: 0 | AC51: 1 | AD51: =(W51+AB51)*AC51 | AE51: =(X51+AB51)*AC51 | AJ51: 0 | AK51: 0.2 | AL51: 0.84 | AM51: =IFS(AJ51 > 1.25, "S", AJ51 > 1, "A", AJ51 > 0.75, "B", AJ51 > 0.5, "C", AJ51 > 0.25, "D", AJ51 > 0, "E", TRUE, "-") | AN51: =IFS(AK51 > 1.25, "S", AK51 > 1, "A", AK51 > 0.75, "B", AK51 > 0.5, "C", AK51 > 0.25, "D", AK51 > 0, "E", TRUE, "-") | AO51: =IFS(AL51 > 1.25, "S", AL51 > 1, "A", AL51 > 0.75, "B", AL51 > 0.5, "C", AL51 > 0.25, "D", AL51 > 0, "E", TRUE, "-") | AP51: 10 | AQ51: 10 | AR51: 10 | AV51: ='武器列表'!CC39'武器列表'!U51 | AW51: =MAX(AJ51:AL51) | AX51: =IF(AW51=0, "", AW51 / ((1 + 0.1*N(F51)))) | AY51: =IF(SUM(AJ51:AL51)=0, 0, (1 + F51 * 0.1) * (1 + ((SUM(AJ51:AL51) - MAX(AJ51:AL51)) / (2 * MAX(AJ51:AL51))) * (1/0.75 - 1))) | AZ51: =AJ51+AK51+AL51 | BA51: =IF(AZ51=0, "", AZ51 / ((1 + 0.1*N(F51))/0.75)) | BB51: 0.1 | BD51: 0 | BE51: 0 | BF51: 1 | BG51: =T51*20*(16 * BF51) / (15 + 20 * BF51 - 3 * POWER(BF51, 2))/BT51/BS51 | BH51: =BG51 | BJ51: 4 | BK51: =T51*33*(16 * BJ51) / (15 + 20 * BJ51 - 3 * POWER(BJ51, 2))/BT51 | BL51: =BK51 | BN51: 100 | BO51: 3 | BP51: =ROUND(CP51/10,2) | BQ51: 0.1 | BR51: =IFERROR(BQ51*100/CP51,"N/A") | BS51: 1 | BT51: 1 | BV51: =CP51/1.5 | BW51: =ROUND(BV51) | BX51: =CP51/BW51 | BY51: =BW51/T51 | CA51: 10 | CB51: =CA51*BB51*(AP51*AJ51+AQ51*AK51+AR51*AL51) | CC51: =CA51+CB51 | CD51: =T51 * 2 / BS51 / BT51 * (0.9 + 0.2 * IF(G51="近战", EXP(-64 * (T51 - 0.75)^2), EXP(-400 * (T51 - 0.15)^2))) | CE51: =0.9 + 0.2 / (1 + (N51/600)^1) | CF51: =LET( k, K51, be, BS51, bf, BT51, m, N51, n, O51, v, X51, vEff, IF(ISNUMBER(v), v, 0), angle, IF( ISNUMBER(n), IF(n>0, n, IF(ISNUMBER(v), IF(v>0, v, 0), 0 ) ), IF(ISNUMBER(v), IF(v>0, v, 0), 0 ) ), T, IF(k=1, be * bf * 20 / MAX(vEff, 1), IF(k=2, (m/150)^2 * (angle/120), IF(k=3, be * (MIN(bf, 99)/99) * (m/1000), be * bf * (m/1000) * (n/200)^2 ))), b, 0.8, c, 1.2, r, (c-1)/(1-b), k_s, 1, b + (c-b) / (1 + r * EXP(-k_s*(1-T)))) | CG51: =IF(T51<=0,1, (0.9 + 0.2 / (1 + EXP(-0.8 * (5 - BD51)))) * (0.9 + 0.2 / (1 + EXP(-1 * (3.5 - BE51)))) * (0.9 + 0.2 / (1 + EXP(-0.6 * (20 - BS51*BH51/T51))))) | CH51: =IF(T51<=0, 1, 0.9 + 0.2 / (1 + EXP(0.1 * (BL51*BS51*BT51/T51 - 33)))) | CI51: =LET( x_val, W51, bq_val, BS51, Check_Fail, OR(NOT(ISNUMBER(x_val)), bq_val <= 1), IF(Check_Fail, 1, LET( Ratio, x_val / bq_val, calc_A, 2.2 / (1 + EXP(-0.276 * (Ratio - 0.66))), calc_B, 2.2 / (1 + EXP(-0.0138 * (x_val - 13.2))), calc_A + calc_B ) )) | CJ51: =CD51*CE51*CF51*CG51*CH51*CI51 | CK51: =CJ51 | CL51: =T51 * 2 / BS51 / BT51 | CM51: =CK51/CL51 | CN51: =CK51*CC51 | CP51: =CN51*BS51*BT51 | CQ51: =CP51/T51 | CR51: =100/CP51 | CS51: =100/CQ51 | CV51: =BL51/T51 | CW51: =100/CV51 | CY51: 管线散热液加注设备， 几乎可以适配任何类型的高压流体喷注需求。 得益于其令人担忧的稳定性， 似乎在街头混战中也颇有威慑力。 | DA51: =TEXTJOIN("、", TRUE, FILTER('武器技能'!B:B, '武器技能'!E:E = H51)) | DC51: 完成 | DD51: 完成
A52: Injection King | B52: 加注王 | D52: =IF($A52="","","WPN"&VLOOKUP(E52,'引用数据库'!Z:AC,4,FALSE)&VLOOKUP(H52,'引用数据库'!N:P,3,FALSE)&VLOOKUP(I52,'引用数据库'!S:U,3,FALSE)&TEXT(F52,"00")) | E52: 劳旅 | F52: 1 | G52: =G51 | H52: =H51 | I52: =I51 | J52: 手动 | K52: =K51 | M52: =M51 | N52: =N51 | O52: N/A | P52: 0 | Q52: =Q51 | R52: =R51 | S52: 0 | T52: =SUM(P52:S52) | U52: =2*T52/(15*(1+(5-BD52)*0.1)) | W52: 120 | X52: 120 | Y52: 0 | Z52: 0 | AB52: 0 | AC52: 1 | AD52: =(W52+AB52)*AC52 | AE52: =(X52+AB52)*AC52 | AJ52: =AJ51 | AK52: =AK51 | AL52: =AL51+0.1 | AM52: =IFS(AJ52 > 1.25, "S", AJ52 > 1, "A", AJ52 > 0.75, "B", AJ52 > 0.5, "C", AJ52 > 0.25, "D", AJ52 > 0, "E", TRUE, "-") | AN52: =IFS(AK52 > 1.25, "S", AK52 > 1, "A", AK52 > 0.75, "B", AK52 > 0.5, "C", AK52 > 0.25, "D", AK52 > 0, "E", TRUE, "-") | AO52: =IFS(AL52 > 1.25, "S", AL52 > 1, "A", AL52 > 0.75, "B", AL52 > 0.5, "C", AL52 > 0.25, "D", AL52 > 0, "E", TRUE, "-") | AP52: 10 | AQ52: 10 | AR52: 10 | AV52: =IF(SUM(AJ52:AL52)=0, 0, (1 + F52 * 0.1) * (0.75 + 0.25 * MAX(0, MIN(1, IF(MAX(AJ52:AL52)=0, 0, (3*MAX(AJ52:AL52)-SUM(AJ52:AL52)) / (2*MAX(AJ52:AL52))))))) | AW52: =MAX(AJ52:AL52) | AX52: =IF(AW52=0, "", AW52 / ((1 + 0.1*N(F52)))) | AY52: =IF(SUM(AJ52:AL52)=0, 0, (1 + F52 * 0.1) * (1 + ((SUM(AJ52:AL52) - MAX(AJ52:AL52)) / (2 * MAX(AJ52:AL52))) * (1/0.75 - 1))) | AZ52: =AJ52+AK52+AL52 | BA52: =IF(AZ52=0, "", AZ52 / ((1 + 0.1*N(F52))/0.75)) | BB52: 0.1 | BD52: =BD51 | BE52: =BE51 | BH52: =BH51 | BL52: =BL51 | BN52: =BN51 | BO52: 3 | BQ52: =BQ51 | BR52: =IFERROR(BQ52*100/CP52,"N/A") | BS52: 1 | BT52: 1 | BW52: =BW51 | BX52: =CP52/BW52 | BY52: =BW52/T52 | CA52: =CA51+20 | CB52: =CA52*BB52*(AP52*AJ52+AQ52*AK52+AR52*AL52) | CC52: =CA52+CB52 | CK52: =CK51 | CN52: =CK52*CC52 | CP52: =CN52*BS52*BT52 | CQ52: =CP52/T52 | CR52: =100/CP52 | CS52: =100/CQ52 | CT52: =CQ52-CQ51 | CU52: =(CQ52-CQ51)/CQ51 | CV52: =BL52/T52 | CW52: =100/CV52 | DC52: 完成 | DD52: 完成
A53: Injection King | B53: 加注王 | D53: =IF($A53="","","WPN"&VLOOKUP(E53,'引用数据库'!Z:AC,4,FALSE)&VLOOKUP(H53,'引用数据库'!N:P,3,FALSE)&VLOOKUP(I53,'引用数据库'!S:U,3,FALSE)&TEXT(F53,"00")) | E53: 劳旅 | F53: 2 | G53: =G52 | H53: =H52 | I53: =I52 | J53: 手动 | K53: =K52 | M53: =M52 | N53: =N52 | O53: N/A | P53: 0 | Q53: =Q52 | R53: =R52 | S53: 0 | T53: =SUM(P53:S53) | U53: =2*T53/(15*(1+(5-BD53)*0.1)) | W53: 120 | X53: 120 | Y53: 0 | Z53: 0 | AB53: 0 | AC53: 1 | AD53: =(W53+AB53)*AC53 | AE53: =(X53+AB53)*AC53 | AJ53: =AJ52 | AK53: =AK52 | AL53: =AL52+0.1 | AM53: =IFS(AJ53 > 1.25, "S", AJ53 > 1, "A", AJ53 > 0.75, "B", AJ53 > 0.5, "C", AJ53 > 0.25, "D", AJ53 > 0, "E", TRUE, "-") | AN53: =IFS(AK53 > 1.25, "S", AK53 > 1, "A", AK53 > 0.75, "B", AK53 > 0.5, "C", AK53 > 0.25, "D", AK53 > 0, "E", TRUE, "-") | AO53: =IFS(AL53 > 1.25, "S", AL53 > 1, "A", AL53 > 0.75, "B", AL53 > 0.5, "C", AL53 > 0.25, "D", AL53 > 0, "E", TRUE, "-") | AP53: 10 | AQ53: 10 | AR53: 10 | AV53: =IF(SUM(AJ53:AL53)=0, 0, (1 + F53 * 0.1) * (0.75 + 0.25 * MAX(0, MIN(1, IF(MAX(AJ53:AL53)=0, 0, (3*MAX(AJ53:AL53)-SUM(AJ53:AL53)) / (2*MAX(AJ53:AL53))))))) | AW53: =MAX(AJ53:AL53) | AX53: =IF(AW53=0, "", AW53 / ((1 + 0.1*N(F53)))) | AY53: =IF(SUM(AJ53:AL53)=0, 0, (1 + F53 * 0.1) * (1 + ((SUM(AJ53:AL53) - MAX(AJ53:AL53)) / (2 * MAX(AJ53:AL53))) * (1/0.75 - 1))) | AZ53: =AJ53+AK53+AL53 | BA53: =IF(AZ53=0, "", AZ53 / ((1 + 0.1*N(F53))/0.75)) | BB53: 0.1 | BD53: =BD52 | BE53: =BE52 | BH53: =BH52 | BL53: =BL52 | BN53: =BN52 | BO53: 3 | BQ53: =BQ52 | BR53: =IFERROR(BQ53*100/CP53,"N/A") | BS53: 1 | BT53: 1 | BW53: =BW52 | BX53: =CP53/BW53 | BY53: =BW53/T53 | CA53: =CA52+10 | CB53: =CA53*BB53*(AP53*AJ53+AQ53*AK53+AR53*AL53) | CC53: =CA53+CB53 | CK53: =CK52 | CN53: =CK53*CC53 | CP53: =CN53*BS53*BT53 | CQ53: =CP53/T53 | CR53: =100/CP53 | CS53: =100/CQ53 | CT53: =CQ53-CQ52 | CU53: =(CQ53-CQ52)/CQ52 | CV53: =BL53/T53 | CW53: =100/CV53 | DC53: 完成 | DD53: 完成
A54: Injection King | B54: 加注王 | D54: =IF($A54="","","WPN"&VLOOKUP(E54,'引用数据库'!Z:AC,4,FALSE)&VLOOKUP(H54,'引用数据库'!N:P,3,FALSE)&VLOOKUP(I54,'引用数据库'!S:U,3,FALSE)&TEXT(F54,"00")) | E54: 劳旅 | F54: 3 | G54: =G53 | H54: =H53 | I54: =I53 | J54: 手动 | K54: =K53 | M54: =M53 | N54: =N53 | O54: N/A | P54: 0 | Q54: =Q53 | R54: =R53 | S54: 0 | T54: =SUM(P54:S54) | U54: =2*T54/(15*(1+(5-BD54)*0.1)) | W54: 120 | X54: 120 | Y54: 0 | Z54: 0 | AB54: 0 | AC54: 1 | AD54: =(W54+AB54)*AC54 | AE54: =(X54+AB54)*AC54 | AJ54: =AJ53 | AK54: =AK53 | AL54: =AL53+0.1 | AM54: =IFS(AJ54 > 1.25, "S", AJ54 > 1, "A", AJ54 > 0.75, "B", AJ54 > 0.5, "C", AJ54 > 0.25, "D", AJ54 > 0, "E", TRUE, "-") | AN54: =IFS(AK54 > 1.25, "S", AK54 > 1, "A", AK54 > 0.75, "B", AK54 > 0.5, "C", AK54 > 0.25, "D", AK54 > 0, "E", TRUE, "-") | AO54: =IFS(AL54 > 1.25, "S", AL54 > 1, "A", AL54 > 0.75, "B", AL54 > 0.5, "C", AL54 > 0.25, "D", AL54 > 0, "E", TRUE, "-") | AP54: 10 | AQ54: 10 | AR54: 10 | AV54: =IF(SUM(AJ54:AL54)=0, 0, (1 + F54 * 0.1) * (0.75 + 0.25 * MAX(0, MIN(1, IF(MAX(AJ54:AL54)=0, 0, (3*MAX(AJ54:AL54)-SUM(AJ54:AL54)) / (2*MAX(AJ54:AL54))))))) | AW54: =MAX(AJ54:AL54) | AX54: =IF(AW54=0, "", AW54 / ((1 + 0.1*N(F54)))) | AY54: =IF(SUM(AJ54:AL54)=0, 0, (1 + F54 * 0.1) * (1 + ((SUM(AJ54:AL54) - MAX(AJ54:AL54)) / (2 * MAX(AJ54:AL54))) * (1/0.75 - 1))) | AZ54: =AJ54+AK54+AL54 | BA54: =IF(AZ54=0, "", AZ54 / ((1 + 0.1*N(F54))/0.75)) | BB54: 0.1 | BD54: =BD53 | BE54: =BE53 | BH54: =BH53 | BL54: =BL53 | BN54: =BN53 | BO54: 3 | BQ54: =BQ53 | BR54: =IFERROR(BQ54*100/CP54,"N/A") | BS54: 1 | BT54: 1 | BW54: =BW53 | BX54: =CP54/BW54 | BY54: =BW54/T54 | CA54: =CA53+10 | CB54: =CA54*BB54*(AP54*AJ54+AQ54*AK54+AR54*AL54) | CC54: =CA54+CB54 | CK54: =CK53 | CN54: =CK54*CC54 | CP54: =CN54*BS54*BT54 | CQ54: =CP54/T54 | CR54: =100/CP54 | CS54: =100/CQ54 | CT54: =CQ54-CQ53 | CU54: =(CQ54-CQ53)/CQ53 | CV54: =BL54/T54 | CW54: =100/CV54 | DC54: 完成 | DD54: 完成
A55: Injection King | B55: 加注王 | D55: =IF($A55="","","WPN"&VLOOKUP(E55,'引用数据库'!Z:AC,4,FALSE)&VLOOKUP(H55,'引用数据库'!N:P,3,FALSE)&VLOOKUP(I55,'引用数据库'!S:U,3,FALSE)&TEXT(F55,"00")) | E55: 劳旅 | F55: 4 | G55: =G54 | H55: =H54 | I55: =I54 | J55: 手动 | K55: =K54 | M55: =M54 | N55: =N54 | O55: N/A | P55: 0 | Q55: =Q54 | R55: =R54 | S55: 0 | T55: =SUM(P55:S55) | U55: =2*T55/(15*(1+(5-BD55)*0.1)) | W55: 120 | X55: 120 | Y55: 0 | Z55: 0 | AB55: 0 | AC55: 1 | AD55: =(W55+AB55)*AC55 | AE55: =(X55+AB55)*AC55 | AJ55: =AJ54 | AK55: =AK54 | AL55: =AL54+0.1 | AM55: =IFS(AJ55 > 1.25, "S", AJ55 > 1, "A", AJ55 > 0.75, "B", AJ55 > 0.5, "C", AJ55 > 0.25, "D", AJ55 > 0, "E", TRUE, "-") | AN55: =IFS(AK55 > 1.25, "S", AK55 > 1, "A", AK55 > 0.75, "B", AK55 > 0.5, "C", AK55 > 0.25, "D", AK55 > 0, "E", TRUE, "-") | AO55: =IFS(AL55 > 1.25, "S", AL55 > 1, "A", AL55 > 0.75, "B", AL55 > 0.5, "C", AL55 > 0.25, "D", AL55 > 0, "E", TRUE, "-") | AP55: 10 | AQ55: 10 | AR55: 10 | AV55: =IF(SUM(AJ55:AL55)=0, 0, (1 + F55 * 0.1) * (0.75 + 0.25 * MAX(0, MIN(1, IF(MAX(AJ55:AL55)=0, 0, (3*MAX(AJ55:AL55)-SUM(AJ55:AL55)) / (2*MAX(AJ55:AL55))))))) | AW55: =MAX(AJ55:AL55) | AX55: =IF(AW55=0, "", AW55 / ((1 + 0.1*N(F55)))) | AY55: =IF(SUM(AJ55:AL55)=0, 0, (1 + F55 * 0.1) * (1 + ((SUM(AJ55:AL55) - MAX(AJ55:AL55)) / (2 * MAX(AJ55:AL55))) * (1/0.75 - 1))) | AZ55: =AJ55+AK55+AL55 | BA55: =IF(AZ55=0, "", AZ55 / ((1 + 0.1*N(F55))/0.75)) | BB55: 0.1 | BD55: =BD54 | BE55: =BE54 | BH55: =BH54 | BL55: =BL54 | BN55: =BN54 | BO55: 3 | BQ55: =BQ54 | BR55: =IFERROR(BQ55*100/CP55,"N/A") | BS55: 1 | BT55: 1 | BW55: =BW54 | BX55: =CP55/BW55 | BY55: =BW55/T55 | CA55: =CA54+10 | CB55: =CA55*BB55*(AP55*AJ55+AQ55*AK55+AR55*AL55) | CC55: =CA55+CB55 | CK55: =CK54 | CN55: =CK55*CC55 | CP55: =CN55*BS55*BT55 | CQ55: =CP55/T55 | CR55: =100/CP55 | CS55: =100/CQ55 | CT55: =CQ55-CQ54 | CU55: =(CQ55-CQ54)/CQ54 | CV55: =BL55/T55 | CW55: =100/CV55 | DC55: 完成 | DD55: 完成
A56: Injection King | B56: 加注王 | D56: =IF($A56="","","WPN"&VLOOKUP(E56,'引用数据库'!Z:AC,4,FALSE)&VLOOKUP(H56,'引用数据库'!N:P,3,FALSE)&VLOOKUP(I56,'引用数据库'!S:U,3,FALSE)&TEXT(F56,"00")) | E56: 劳旅 | F56: 5 | G56: =G55 | H56: =H55 | I56: =I55 | J56: 手动 | K56: =K55 | M56: =M55 | N56: =N55 | O56: N/A | P56: 0 | Q56: =Q55 | R56: =R55 | S56: 0 | T56: =SUM(P56:S56) | U56: =2*T56/(15*(1+(5-BD56)*0.1)) | W56: 120 | X56: 120 | Y56: 0 | Z56: 0 | AB56: 0 | AC56: 1 | AD56: =(W56+AB56)*AC56 | AE56: =(X56+AB56)*AC56 | AJ56: =AJ55 | AK56: =AK55 | AL56: =AL55+0.1 | AM56: =IFS(AJ56 > 1.25, "S", AJ56 > 1, "A", AJ56 > 0.75, "B", AJ56 > 0.5, "C", AJ56 > 0.25, "D", AJ56 > 0, "E", TRUE, "-") | AN56: =IFS(AK56 > 1.25, "S", AK56 > 1, "A", AK56 > 0.75, "B", AK56 > 0.5, "C", AK56 > 0.25, "D", AK56 > 0, "E", TRUE, "-") | AO56: =IFS(AL56 > 1.25, "S", AL56 > 1, "A", AL56 > 0.75, "B", AL56 > 0.5, "C", AL56 > 0.25, "D", AL56 > 0, "E", TRUE, "-") | AP56: 10 | AQ56: 10 | AR56: 10 | AV56: =IF(SUM(AJ56:AL56)=0, 0, (1 + F56 * 0.1) * (0.75 + 0.25 * MAX(0, MIN(1, IF(MAX(AJ56:AL56)=0, 0, (3*MAX(AJ56:AL56)-SUM(AJ56:AL56)) / (2*MAX(AJ56:AL56))))))) | AW56: =MAX(AJ56:AL56) | AX56: =IF(AW56=0, "", AW56 / ((1 + 0.1*N(F56)))) | AY56: =IF(SUM(AJ56:AL56)=0, 0, (1 + F56 * 0.1) * (1 + ((SUM(AJ56:AL56) - MAX(AJ56:AL56)) / (2 * MAX(AJ56:AL56))) * (1/0.75 - 1))) | AZ56: =AJ56+AK56+AL56 | BA56: =IF(AZ56=0, "", AZ56 / ((1 + 0.1*N(F56))/0.75)) | BB56: 0.1 | BD56: =BD55 | BE56: =BE55 | BH56: =BH55 | BL56: =BL55 | BN56: =BN55 | BO56: 3 | BQ56: =BQ55 | BR56: =IFERROR(BQ56*100/CP56,"N/A") | BS56: 1 | BT56: 1 | BW56: =BW55 | BX56: =CP56/BW56 | BY56: =BW56/T56 | CA56: =CA55+10 | CB56: =CA56*BB56*(AP56*AJ56+AQ56*AK56+AR56*AL56) | CC56: =CA56+CB56 | CK56: =CK55 | CN56: =CK56*CC56 | CP56: =CN56*BS56*BT56 | CQ56: =CP56/T56 | CR56: =100/CP56 | CS56: =100/CQ56 | CT56: =CQ56-CQ55 | CU56: =(CQ56-CQ55)/CQ55 | CV56: =BL56/T56 | CW56: =100/CV56 | DC56: 完成 | DD56: 完成
A57: Hodor | B57: 门神 | D57: =IF($A57="","","WPN"&VLOOKUP(E57,'引用数据库'!Z:AC,4,FALSE)&VLOOKUP(H57,'引用数据库'!N:P,3,FALSE)&VLOOKUP(I57,'引用数据库'!S:U,3,FALSE)&TEXT(F57,"00")) | E57: 劳旅 | F57: 0 | G57: 近战 | H57: 巨锤 | I57: 动能 | J57: 手动 | K57: =K56 | M57: 1 | N57: 150 | O57: 160 | P57: 0.5 | Q57: 0.1 | R57: 0.5 | S57: 0 | T57: =SUM(P57:S57) | U57: =2*T57/(15*(1+(5-BD57)*0.1)) | W57: N/A | X57: N/A | Y57: N/A | Z57: N/A | AD57: N/A | AE57: N/A | AJ57: 0.92 | AK57: 0 | AL57: 0.1 | AM57: =IFS(AJ57 > 1.25, "S", AJ57 > 1, "A", AJ57 > 0.75, "B", AJ57 > 0.5, "C", AJ57 > 0.25, "D", AJ57 > 0, "E", TRUE, "-") | AN57: =IFS(AK57 > 1.25, "S", AK57 > 1, "A", AK57 > 0.75, "B", AK57 > 0.5, "C", AK57 > 0.25, "D", AK57 > 0, "E", TRUE, "-") | AO57: =IFS(AL57 > 1.25, "S", AL57 > 1, "A", AL57 > 0.75, "B", AL57 > 0.5, "C", AL57 > 0.25, "D", AL57 > 0, "E", TRUE, "-") | AP57: 10 | AQ57: 10 | AR57: 10 | AV57: =IF(SUM(AJ57:AL57)=0, 0, (1 + F57 * 0.1) * (0.75 + 0.25 * MAX(0, MIN(1, IF(MAX(AJ57:AL57)=0, 0, (3*MAX(AJ57:AL57)-SUM(AJ57:AL57)) / (2*MAX(AJ57:AL57))))))) | AW57: =MAX(AJ57:AL57) | AX57: =IF(AW57=0, "", AW57 / ((1 + 0.1*N(F57)))) | AY57: =IF(SUM(AJ57:AL57)=0, 0, (1 + F57 * 0.1) * (1 + ((SUM(AJ57:AL57) - MAX(AJ57:AL57)) / (2 * MAX(AJ57:AL57))) * (1/0.75 - 1))) | AZ57: =AJ57+AK57+AL57 | BA57: =IF(AZ57=0, "", AZ57 / ((1 + 0.1*N(F57))/0.75)) | BB57: 0.1 | BD57: 3 | BE57: 4 | BF57: 5 | BG57: =T57*20*(16 * BF57) / (15 + 20 * BF57 - 3 * POWER(BF57, 2))/BT57/BS57 | BH57: =BG57 | BJ57: 3 | BK57: =T57*33*(16 * BJ57) / (15 + 20 * BJ57 - 3 * POWER(BJ57, 2))/BT57 | BL57: =BK57 | BN57: N/A | BO57: N/A | BP57: 0 | BQ57: 0 | BR57: =IFERROR(BQ57*100/CP57,"N/A") | BS57: 1 | BT57: 1 | BV57: =CP57/1.5 | BW57: =ROUND(BV57) | BX57: =CP57/BW57 | BY57: =BW57/T57 | CA57: 10 | CB57: =CA57*BB57*(AP57*AJ57+AQ57*AK57+AR57*AL57) | CC57: =CA57+CB57 | CD57: =T57 * 2 / BS57 / BT57 * (0.9 + 0.2 * IF(G57="近战", EXP(-64 * (T57 - 0.75)^2), EXP(-400 * (T57 - 0.15)^2))) | CE57: =0.9 + 0.2 / (1 + (N57/600)^1) | CF57: =LET( k, K57, be, BS57, bf, BT57, m, N57, n, O57, v, X57, vEff, IF(ISNUMBER(v), v, 0), angle, IF( ISNUMBER(n), IF(n>0, n, IF(ISNUMBER(v), IF(v>0, v, 0), 0 ) ), IF(ISNUMBER(v), IF(v>0, v, 0), 0 ) ), T, IF(k=1, be * bf * 20 / MAX(vEff, 1), IF(k=2, (m/150)^2 * (angle/120), IF(k=3, be * (MIN(bf, 99)/99) * (m/1000), be * bf * (m/1000) * (n/200)^2 ))), b, 0.8, c, 1.2, r, (c-1)/(1-b), k_s, 1, b + (c-b) / (1 + r * EXP(-k_s*(1-T)))) | CG57: =IF(T57<=0,1, (0.9 + 0.2 / (1 + EXP(-0.8 * (5 - BD57)))) * (0.9 + 0.2 / (1 + EXP(-1 * (3.5 - BE57)))) * (0.9 + 0.2 / (1 + EXP(-0.6 * (20 - BS57*BH57/T57))))) | CH57: =IF(T57<=0, 1, 0.9 + 0.2 / (1 + EXP(0.1 * (BL57*BS57*BT57/T57 - 33)))) | CI57: =LET( x_val, W57, bq_val, BS57, Check_Fail, OR(NOT(ISNUMBER(x_val)), bq_val <= 1), IF(Check_Fail, 1, LET( Ratio, x_val / bq_val, calc_A, 2.2 / (1 + EXP(-0.276 * (Ratio - 0.66))), calc_B, 2.2 / (1 + EXP(-0.0138 * (x_val - 13.2))), calc_A + calc_B ) )) | CJ57: =CD57*CE57*CF57*CG57*CH57*CI57 | CK57: =CJ57 | CL57: =T57 * 2 / BS57 / BT57 | CM57: =CK57/CL57 | CN57: =CK57*CC57 | CP57: =CN57*BS57*BT57 | CQ57: =CP57/T57 | CR57: =100/CP57 | CS57: =100/CQ57 | CV57: =BL57/T57 | CW57: =100/CV57 | CY57: AI梦时代的标准隧道挖掘设备， 可以快速展开提供支撑结构。 原则上应该由机械矿工单手各持一把， 对普通人来说双手持握则会更为合理。 | DA57: =TEXTJOIN("、", TRUE, FILTER('武器技能'!B:B, '武器技能'!E:E = H57)) | DC57: 完成 | DD57: 完成
A58: Hodor | B58: 门神 | D58: =IF($A58="","","WPN"&VLOOKUP(E58,'引用数据库'!Z:AC,4,FALSE)&VLOOKUP(H58,'引用数据库'!N:P,3,FALSE)&VLOOKUP(I58,'引用数据库'!S:U,3,FALSE)&TEXT(F58,"00")) | E58: 劳旅 | F58: 1 | G58: =G57 | H58: =H57 | I58: =I57 | J58: 手动 | K58: =K57 | M58: =M57 | N58: 150 | O58: 160 | P58: =P57 | Q58: =Q57 | R58: =R57 | S58: 0 | T58: =SUM(P58:S58) | U58: =2*T58/(15*(1+(5-BD58)*0.1)) | W58: N/A | X58: N/A | Y58: N/A | Z58: N/A | AD58: N/A | AE58: N/A | AJ58: =AJ57+0.1 | AK58: 0 | AL58: =AL57 | AM58: =IFS(AJ58 > 1.25, "S", AJ58 > 1, "A", AJ58 > 0.75, "B", AJ58 > 0.5, "C", AJ58 > 0.25, "D", AJ58 > 0, "E", TRUE, "-") | AN58: =IFS(AK58 > 1.25, "S", AK58 > 1, "A", AK58 > 0.75, "B", AK58 > 0.5, "C", AK58 > 0.25, "D", AK58 > 0, "E", TRUE, "-") | AO58: =IFS(AL58 > 1.25, "S", AL58 > 1, "A", AL58 > 0.75, "B", AL58 > 0.5, "C", AL58 > 0.25, "D", AL58 > 0, "E", TRUE, "-") | AP58: 10 | AQ58: 10 | AR58: 10 | AV58: =IF(SUM(AJ58:AL58)=0, 0, (1 + F58 * 0.1) * (0.75 + 0.25 * MAX(0, MIN(1, IF(MAX(AJ58:AL58)=0, 0, (3*MAX(AJ58:AL58)-SUM(AJ58:AL58)) / (2*MAX(AJ58:AL58))))))) | AW58: =MAX(AJ58:AL58) | AX58: =IF(AW58=0, "", AW58 / ((1 + 0.1*N(F58)))) | AY58: =IF(SUM(AJ58:AL58)=0, 0, (1 + F58 * 0.1) * (1 + ((SUM(AJ58:AL58) - MAX(AJ58:AL58)) / (2 * MAX(AJ58:AL58))) * (1/0.75 - 1))) | AZ58: =AJ58+AK58+AL58 | BA58: =IF(AZ58=0, "", AZ58 / ((1 + 0.1*N(F58))/0.75)) | BB58: 0.1 | BD58: =BD57 | BE58: =BE57 | BH58: =BH57 | BL58: =BL57 | BN58: N/A | BO58: N/A | BQ58: 0 | BR58: =IFERROR(BQ58*100/CP58,"N/A") | BS58: 1 | BT58: 1 | BW58: =BW57 | BX58: =CP58/BW58 | BY58: =BW58/T58 | CA58: =CA57+20 | CB58: =CA58*BB58*(AP58*AJ58+AQ58*AK58+AR58*AL58) | CC58: =CA58+CB58 | CK58: =CK57 | CN58: =CK58*CC58 | CP58: =CN58*BS58*BT58 | CQ58: =CP58/T58 | CR58: =100/CP58 | CS58: =100/CQ58 | CT58: =CQ58-CQ57 | CU58: =(CQ58-CQ57)/CQ57 | CV58: =BL58/T58 | CW58: =100/CV58 | DC58: 完成 | DD58: 完成
A59: Hodor | B59: 门神 | D59: =IF($A59="","","WPN"&VLOOKUP(E59,'引用数据库'!Z:AC,4,FALSE)&VLOOKUP(H59,'引用数据库'!N:P,3,FALSE)&VLOOKUP(I59,'引用数据库'!S:U,3,FALSE)&TEXT(F59,"00")) | E59: 劳旅 | F59: 2 | G59: =G58 | H59: =H58 | I59: =I58 | J59: 手动 | K59: =K58 | M59: =M58 | N59: 150 | O59: 160 | P59: =P58 | Q59: =Q58 | R59: =R58 | S59: 0 | T59: =SUM(P59:S59) | U59: =2*T59/(15*(1+(5-BD59)*0.1)) | W59: N/A | X59: N/A | Y59: N/A | Z59: N/A | AD59: N/A | AE59: N/A | AJ59: 1.12 | AK59: 0 | AL59: =AL58 | AM59: =IFS(AJ59 > 1.25, "S", AJ59 > 1, "A", AJ59 > 0.75, "B", AJ59 > 0.5, "C", AJ59 > 0.25, "D", AJ59 > 0, "E", TRUE, "-") | AN59: =IFS(AK59 > 1.25, "S", AK59 > 1, "A", AK59 > 0.75, "B", AK59 > 0.5, "C", AK59 > 0.25, "D", AK59 > 0, "E", TRUE, "-") | AO59: =IFS(AL59 > 1.25, "S", AL59 > 1, "A", AL59 > 0.75, "B", AL59 > 0.5, "C", AL59 > 0.25, "D", AL59 > 0, "E", TRUE, "-") | AP59: 10 | AQ59: 10 | AR59: 10 | AV59: =IF(SUM(AJ59:AL59)=0, 0, (1 + F59 * 0.1) * (0.75 + 0.25 * MAX(0, MIN(1, IF(MAX(AJ59:AL59)=0, 0, (3*MAX(AJ59:AL59)-SUM(AJ59:AL59)) / (2*MAX(AJ59:AL59))))))) | AW59: =MAX(AJ59:AL59) | AX59: =IF(AW59=0, "", AW59 / ((1 + 0.1*N(F59)))) | AY59: =IF(SUM(AJ59:AL59)=0, 0, (1 + F59 * 0.1) * (1 + ((SUM(AJ59:AL59) - MAX(AJ59:AL59)) / (2 * MAX(AJ59:AL59))) * (1/0.75 - 1))) | AZ59: =AJ59+AK59+AL59 | BA59: =IF(AZ59=0, "", AZ59 / ((1 + 0.1*N(F59))/0.75)) | BB59: 0.1 | BD59: =BD58 | BE59: =BE58 | BH59: =BH58 | BL59: =BL58 | BN59: N/A | BO59: N/A | BQ59: 0 | BR59: =IFERROR(BQ59*100/CP59,"N/A") | BS59: 1 | BT59: 1 | BW59: =BW58 | BX59: =CP59/BW59 | BY59: =BW59/T59 | CA59: =CA58+10 | CB59: =CA59*BB59*(AP59*AJ59+AQ59*AK59+AR59*AL59) | CC59: =CA59+CB59 | CK59: =CK58 | CN59: =CK59*CC59 | CP59: =CN59*BS59*BT59 | CQ59: =CP59/T59 | CR59: =100/CP59 | CS59: =100/CQ59 | CT59: =CQ59-CQ58 | CU59: =(CQ59-CQ58)/CQ58 | CV59: =BL59/T59 | CW59: =100/CV59 | DC59: 完成 | DD59: 完成
A60: Hodor | B60: 门神 | D60: =IF($A60="","","WPN"&VLOOKUP(E60,'引用数据库'!Z:AC,4,FALSE)&VLOOKUP(H60,'引用数据库'!N:P,3,FALSE)&VLOOKUP(I60,'引用数据库'!S:U,3,FALSE)&TEXT(F60,"00")) | E60: 劳旅 | F60: 3 | G60: =G59 | H60: =H59 | I60: =I59 | J60: 手动 | K60: =K59 | M60: =M59 | N60: 150 | O60: 160 | P60: =P59 | Q60: =Q59 | R60: =R59 | S60: 0 | T60: =SUM(P60:S60) | U60: =2*T60/(15*(1+(5-BD60)*0.1)) | W60: N/A | X60: N/A | Y60: N/A | Z60: N/A | AD60: N/A | AE60: N/A | AJ60: =AJ59+0.1 | AK60: 0 | AL60: =AL59 | AM60: =IFS(AJ60 > 1.25, "S", AJ60 > 1, "A", AJ60 > 0.75, "B", AJ60 > 0.5, "C", AJ60 > 0.25, "D", AJ60 > 0, "E", TRUE, "-") | AN60: =IFS(AK60 > 1.25, "S", AK60 > 1, "A", AK60 > 0.75, "B", AK60 > 0.5, "C", AK60 > 0.25, "D", AK60 > 0, "E", TRUE, "-") | AO60: =IFS(AL60 > 1.25, "S", AL60 > 1, "A", AL60 > 0.75, "B", AL60 > 0.5, "C", AL60 > 0.25, "D", AL60 > 0, "E", TRUE, "-") | AP60: 10 | AQ60: 10 | AR60: 10 | AV60: =IF(SUM(AJ60:AL60)=0, 0, (1 + F60 * 0.1) * (0.75 + 0.25 * MAX(0, MIN(1, IF(MAX(AJ60:AL60)=0, 0, (3*MAX(AJ60:AL60)-SUM(AJ60:AL60)) / (2*MAX(AJ60:AL60))))))) | AW60: =MAX(AJ60:AL60) | AX60: =IF(AW60=0, "", AW60 / ((1 + 0.1*N(F60)))) | AY60: =IF(SUM(AJ60:AL60)=0, 0, (1 + F60 * 0.1) * (1 + ((SUM(AJ60:AL60) - MAX(AJ60:AL60)) / (2 * MAX(AJ60:AL60))) * (1/0.75 - 1))) | AZ60: =AJ60+AK60+AL60 | BA60: =IF(AZ60=0, "", AZ60 / ((1 + 0.1*N(F60))/0.75)) | BB60: 0.1 | BD60: =BD59 | BE60: =BE59 | BH60: =BH59 | BL60: =BL59 | BN60: N/A | BO60: N/A | BQ60: 0 | BR60: =IFERROR(BQ60*100/CP60,"N/A") | BS60: 1 | BT60: 1 | BW60: =BW59 | BX60: =CP60/BW60 | BY60: =BW60/T60 | CA60: =CA59+10 | CB60: =CA60*BB60*(AP60*AJ60+AQ60*AK60+AR60*AL60) | CC60: =CA60+CB60 | CK60: =CK59 | CN60: =CK60*CC60 | CP60: =CN60*BS60*BT60 | CQ60: =CP60/T60 | CR60: =100/CP60 | CS60: =100/CQ60 | CT60: =CQ60-CQ59 | CU60: =(CQ60-CQ59)/CQ59 | CV60: =BL60/T60 | CW60: =100/CV60 | DC60: 完成 | DD60: 完成
A61: Hodor | B61: 门神 | D61: =IF($A61="","","WPN"&VLOOKUP(E61,'引用数据库'!Z:AC,4,FALSE)&VLOOKUP(H61,'引用数据库'!N:P,3,FALSE)&VLOOKUP(I61,'引用数据库'!S:U,3,FALSE)&TEXT(F61,"00")) | E61: 劳旅 | F61: 4 | G61: =G60 | H61: =H60 | I61: =I60 | J61: 手动 | K61: =K60 | M61: =M60 | N61: 150 | O61: 160 | P61: =P60 | Q61: =Q60 | R61: =R60 | S61: 0 | T61: =SUM(P61:S61) | U61: =2*T61/(15*(1+(5-BD61)*0.1)) | W61: N/A | X61: N/A | Y61: N/A | Z61: N/A | AD61: N/A | AE61: N/A | AJ61: 1.39 | AK61: 0 | AL61: =AL60 | AM61: =IFS(AJ61 > 1.25, "S", AJ61 > 1, "A", AJ61 > 0.75, "B", AJ61 > 0.5, "C", AJ61 > 0.25, "D", AJ61 > 0, "E", TRUE, "-") | AN61: =IFS(AK61 > 1.25, "S", AK61 > 1, "A", AK61 > 0.75, "B", AK61 > 0.5, "C", AK61 > 0.25, "D", AK61 > 0, "E", TRUE, "-") | AO61: =IFS(AL61 > 1.25, "S", AL61 > 1, "A", AL61 > 0.75, "B", AL61 > 0.5, "C", AL61 > 0.25, "D", AL61 > 0, "E", TRUE, "-") | AP61: 10 | AQ61: 10 | AR61: 10 | AV61: =IF(SUM(AJ61:AL61)=0, 0, (1 + F61 * 0.1) * (0.75 + 0.25 * MAX(0, MIN(1, IF(MAX(AJ61:AL61)=0, 0, (3*MAX(AJ61:AL61)-SUM(AJ61:AL61)) / (2*MAX(AJ61:AL61))))))) | AW61: =MAX(AJ61:AL61) | AX61: =IF(AW61=0, "", AW61 / ((1 + 0.1*N(F61)))) | AY61: =IF(SUM(AJ61:AL61)=0, 0, (1 + F61 * 0.1) * (1 + ((SUM(AJ61:AL61) - MAX(AJ61:AL61)) / (2 * MAX(AJ61:AL61))) * (1/0.75 - 1))) | AZ61: =AJ61+AK61+AL61 | BA61: =IF(AZ61=0, "", AZ61 / ((1 + 0.1*N(F61))/0.75)) | BB61: 0.1 | BD61: =BD60 | BE61: =BE60 | BH61: =BH60 | BL61: =BL60 | BN61: N/A | BO61: N/A | BQ61: 0 | BR61: =IFERROR(BQ61*100/CP61,"N/A") | BS61: 1 | BT61: 1 | BW61: =BW60 | BX61: =CP61/BW61 | BY61: =BW61/T61 | CA61: =CA60+10 | CB61: =CA61*BB61*(AP61*AJ61+AQ61*AK61+AR61*AL61) | CC61: =CA61+CB61 | CK61: =CK60 | CN61: =CK61*CC61 | CP61: =CN61*BS61*BT61 | CQ61: =CP61/T61 | CR61: =100/CP61 | CS61: =100/CQ61 | CT61: =CQ61-CQ60 | CU61: =(CQ61-CQ60)/CQ60 | CV61: =BL61/T61 | CW61: =100/CV61 | DC61: 完成 | DD61: 完成
A62: Hodor | B62: 门神 | D62: =IF($A62="","","WPN"&VLOOKUP(E62,'引用数据库'!Z:AC,4,FALSE)&VLOOKUP(H62,'引用数据库'!N:P,3,FALSE)&VLOOKUP(I62,'引用数据库'!S:U,3,FALSE)&TEXT(F62,"00")) | E62: 劳旅 | F62: 5 | G62: =G61 | H62: =H61 | I62: =I61 | J62: 手动 | K62: =K61 | M62: =M61 | N62: 150 | O62: 160 | P62: =P61 | Q62: =Q61 | R62: =R61 | S62: 0 | T62: =SUM(P62:S62) | U62: =2*T62/(15*(1+(5-BD62)*0.1)) | W62: N/A | X62: N/A | Y62: N/A | Z62: N/A | AD62: N/A | AE62: N/A | AJ62: =AJ61+0.1 | AK62: 0 | AL62: =AL61 | AM62: =IFS(AJ62 > 1.25, "S", AJ62 > 1, "A", AJ62 > 0.75, "B", AJ62 > 0.5, "C", AJ62 > 0.25, "D", AJ62 > 0, "E", TRUE, "-") | AN62: =IFS(AK62 > 1.25, "S", AK62 > 1, "A", AK62 > 0.75, "B", AK62 > 0.5, "C", AK62 > 0.25, "D", AK62 > 0, "E", TRUE, "-") | AO62: =IFS(AL62 > 1.25, "S", AL62 > 1, "A", AL62 > 0.75, "B", AL62 > 0.5, "C", AL62 > 0.25, "D", AL62 > 0, "E", TRUE, "-") | AP62: 10 | AQ62: 10 | AR62: 10 | AV62: =IF(SUM(AJ62:AL62)=0, 0, (1 + F62 * 0.1) * (0.75 + 0.25 * MAX(0, MIN(1, IF(MAX(AJ62:AL62)=0, 0, (3*MAX(AJ62:AL62)-SUM(AJ62:AL62)) / (2*MAX(AJ62:AL62))))))) | AW62: =MAX(AJ62:AL62) | AX62: =IF(AW62=0, "", AW62 / ((1 + 0.1*N(F62)))) | AY62: =IF(SUM(AJ62:AL62)=0, 0, (1 + F62 * 0.1) * (1 + ((SUM(AJ62:AL62) - MAX(AJ62:AL62)) / (2 * MAX(AJ62:AL62))) * (1/0.75 - 1))) | AZ62: =AJ62+AK62+AL62 | BA62: =IF(AZ62=0, "", AZ62 / ((1 + 0.1*N(F62))/0.75)) | BB62: 0.1 | BD62: =BD61 | BE62: =BE61 | BH62: =BH61 | BL62: =BL61 | BN62: N/A | BO62: N/A | BQ62: 0 | BR62: =IFERROR(BQ62*100/CP62,"N/A") | BS62: 1 | BT62: 1 | BW62: =BW61 | BX62: =CP62/BW62 | BY62: =BW62/T62 | CA62: =CA61+10 | CB62: =CA62*BB62*(AP62*AJ62+AQ62*AK62+AR62*AL62) | CC62: =CA62+CB62 | CK62: =CK61 | CN62: =CK62*CC62 | CP62: =CN62*BS62*BT62 | CQ62: =CP62/T62 | CR62: =100/CP62 | CS62: =100/CQ62 | CT62: =CQ62-CQ61 | CU62: =(CQ62-CQ61)/CQ61 | CV62: =BL62/T62 | CW62: =100/CV62 | DC62: 完成 | DD62: 完成
A63: Flame Dancer | B63: 炎舞者 | D63: =IF($A63="","","WPN"&VLOOKUP(E63,'引用数据库'!Z:AC,4,FALSE)&VLOOKUP(H63,'引用数据库'!N:P,3,FALSE)&VLOOKUP(I63,'引用数据库'!S:U,3,FALSE)&TEXT(F63,"00")) | E63: 野望 | F63: 0 | G63: 远程 | H63: 发射器 | I63: 热能 | J63: 手动 | K63: 4 | M63: 1 | N63: 3000 | P63: 0 | Q63: 0 | R63: 0.25 | S63: 0 | T63: =SUM(P63:S63) | U63: =2*T63/(15*(1+(5-BD63)*0.1)) | W63: 0 | X63: 20 | Y63: 0.5 | Z63: 0.5 | AD63: =(W63+AB63)*AC63 | AE63: =(X63+AB63)*AC63 | AM63: =IFS(AJ63 > 1.25, "S", AJ63 > 1, "A", AJ63 > 0.75, "B", AJ63 > 0.5, "C", AJ63 > 0.25, "D", AJ63 > 0, "E", TRUE, "-") | AN63: =IFS(AK63 > 1.25, "S", AK63 > 1, "A", AK63 > 0.75, "B", AK63 > 0.5, "C", AK63 > 0.25, "D", AK63 > 0, "E", TRUE, "-") | AO63: =IFS(AL63 > 1.25, "S", AL63 > 1, "A", AL63 > 0.75, "B", AL63 > 0.5, "C", AL63 > 0.25, "D", AL63 > 0, "E", TRUE, "-") | AV63: =IF(SUM(AJ63:AL63)=0, 0, (1 + F63 * 0.1) * (0.75 + 0.25 * MAX(0, MIN(1, IF(MAX(AJ63:AL63)=0, 0, (3*MAX(AJ63:AL63)-SUM(AJ63:AL63)) / (2*MAX(AJ63:AL63))))))) | AW63: =MAX(AJ63:AL63) | AX63: =IF(AW63=0, "", AW63 / ((1 + 0.1*N(F63)))) | AY63: =IF(SUM(AJ63:AL63)=0, 0, (1 + F63 * 0.1) * (1 + ((SUM(AJ63:AL63) - MAX(AJ63:AL63)) / (2 * MAX(AJ63:AL63))) * (1/0.75 - 1))) | BA63: =IF(AZ63=0, "", AZ63 / ((1 + 0.1*N(F63))/0.75)) | BB63: 0.1 | BG63: =T63*20/BT63 | BN63: 1 | BO63: 3 | BP63: =ROUND(CP63/10,1) | BQ63: 16 | BR63: =IFERROR(BQ63*100/CP63,"N/A") | BS63: 1 | BT63: 4 | BW63: =BW64 | BX63: =CP63/BW63 | BY63: =BW63/T63 | CA63: 15 | CB63: =AP63*AJ63+AQ63*AK63+AR63*AL63 | CC63: =CA63+CB63 | CD63: =T63*1.2/BS63 | CE63: =0.8 + 0.4 / (1 + (N63/600)^1) | CF63: =LET( k, K63, be, BS63, bf, BT63, m, N63, n, O63, v, X63, vEff, IF(ISNUMBER(v), v, 0), angle, IF( ISNUMBER(n), IF(n>0, n, IF(ISNUMBER(v), IF(v>0, v, 0), 0 ) ), IF(ISNUMBER(v), IF(v>0, v, 0), 0 ) ), T, IF(k=1, be * bf * 20 / MAX(vEff, 1), IF(k=2, (m/150)^2 * (angle/120), IF(k=3, be * (MIN(bf, 99)/99) * (m/1000), be * bf * (m/1000) * (n/200)^2 ))), b, 0.8, c, 1.2, r, (c-1)/(1-b), k_s, 1, b + (c-b) / (1 + r * EXP(-k_s*(1-T)))) | CG63: =IF(T63<=0,1,( 0.85 + (0.4) / (1 + 1.6666667 * EXP(-0.6 * (2.5 - BD63))))*( 0.85 + (0.4) / (1 + 1.6666667 * EXP(-0.6 * (20 - BS63*BH63/T63))))*( 0.85 + (0.4) / (1 + 1.6666667 * EXP(-0.6 * (2.5 - BE63))))) | CH63: =IF(T63<=0, 1, 0.9 + 0.2 / (1 + EXP(0.1 * (BL63/T63 - 33)))) | CI63: =LET( x_val, X63, bq_val, BS63, Check_Fail, OR(NOT(ISNUMBER(x_val)), bq_val <= 1), IF(Check_Fail, 1, LET( Ratio, x_val / bq_val, calc_A, 2.5 / (1 + EXP(-0.23105 * (Ratio - 3))), calc_B, 2.5 / (1 + EXP(-0.008664 * (x_val - 20))), calc_A + calc_B ) )) | CJ63: =CD63*CE63*CF63*CG63*CH63 | CK63: =CJ63 | CN63: =CK63*CC63 | CP63: =CN63*BS63*BT63 | CQ63: =CP63/T63 | CR63: =100/CP63 | CS63: =100/CQ63 | CV63: =BL63/T63 | CW63: =100/CV63 | CY63: 在黑市里流通的自动步兵火炮， 结构上直接沿用了洛克海德流出的旧版本。 四发并列装的火箭弹带来了良好的火力覆盖， 以及捉襟见肘的战场续航能力。 | DA63: =TEXTJOIN("、", TRUE, FILTER('武器技能'!B:B, '武器技能'!E:E = H63)) | DC63: 待办 | DD63: 待办
A64: Flame Dancer | B64: 炎舞者 | D64: =IF($A64="","","WPN"&VLOOKUP(E64,'引用数据库'!Z:AC,4,FALSE)&VLOOKUP(H64,'引用数据库'!N:P,3,FALSE)&VLOOKUP(I64,'引用数据库'!S:U,3,FALSE)&TEXT(F64,"00")) | E64: 野望 | F64: 1 | G64: =G63 | H64: =H63 | I64: =I63 | J64: 手动 | K64: =K63 | M64: =M63 | N64: 3000 | P64: 0 | Q64: 0 | R64: 0.25 | S64: 0 | T64: =SUM(P64:S64) | U64: =2*T64/(15*(1+(5-BD64)*0.1)) | W64: 0 | X64: 20 | Y64: 0.5 | Z64: 0.5 | AD64: =(W64+AB64)*AC64 | AE64: =(X64+AB64)*AC64 | AM64: =IFS(AJ64 > 1.25, "S", AJ64 > 1, "A", AJ64 > 0.75, "B", AJ64 > 0.5, "C", AJ64 > 0.25, "D", AJ64 > 0, "E", TRUE, "-") | AN64: =IFS(AK64 > 1.25, "S", AK64 > 1, "A", AK64 > 0.75, "B", AK64 > 0.5, "C", AK64 > 0.25, "D", AK64 > 0, "E", TRUE, "-") | AO64: =IFS(AL64 > 1.25, "S", AL64 > 1, "A", AL64 > 0.75, "B", AL64 > 0.5, "C", AL64 > 0.25, "D", AL64 > 0, "E", TRUE, "-") | AV64: =IF(SUM(AJ64:AL64)=0, 0, (1 + F64 * 0.1) * (0.75 + 0.25 * MAX(0, MIN(1, IF(MAX(AJ64:AL64)=0, 0, (3*MAX(AJ64:AL64)-SUM(AJ64:AL64)) / (2*MAX(AJ64:AL64))))))) | AW64: =MAX(AJ64:AL64) | AX64: =IF(AW64=0, "", AW64 / ((1 + 0.1*N(F64)))) | AY64: =IF(SUM(AJ64:AL64)=0, 0, (1 + F64 * 0.1) * (1 + ((SUM(AJ64:AL64) - MAX(AJ64:AL64)) / (2 * MAX(AJ64:AL64))) * (1/0.75 - 1))) | BA64: =IF(AZ64=0, "", AZ64 / ((1 + 0.1*N(F64))/0.75)) | BB64: 0.1 | BD64: =BD63 | BE64: =BE63 | BN64: 1 | BO64: 3 | BQ64: 16 | BR64: =IFERROR(BQ64*100/CP64,"N/A") | BS64: 1 | BT64: 4 | BV64: =IFERROR( ROUND( (10 / $T$4) * ((CP64 / T64) / ($CP$4 / $T$4)) ^ 0.9 * (T64 / $T$4) ^ 0.2 * ((1 + N64) / (1 + $N$4)) ^ 0.15 * ((1 + BQ64) / (1 + $BQ$4)) ^ 0.15 * ((1 + BD64) / (1 + $BD$4)) ^ 0.2 * ((1 + BH64) / (1 + $BH$4)) ^ 0.2 * ((1 + BL64) / (1 + $BL$4)) ^ 0.2 * T64, 0), CP64 * 1000) | BW64: =BV64 | BX64: =CP64/BW64 | BY64: =BW64/T64 | CA64: =CA63+15 | CB64: =AP64*AJ64+AQ64*AK64+AR64*AL64 | CP64: =CN64*BS64*BT64 | CQ64: =CP64/T64 | CR64: =100/CP64 | CS64: =100/CQ64 | CV64: =BL64/T64 | CW64: =100/CV64 | DC64: 待办 | DD64: 待办
A65: Flame Dancer | B65: 炎舞者 | D65: =IF($A65="","","WPN"&VLOOKUP(E65,'引用数据库'!Z:AC,4,FALSE)&VLOOKUP(H65,'引用数据库'!N:P,3,FALSE)&VLOOKUP(I65,'引用数据库'!S:U,3,FALSE)&TEXT(F65,"00")) | E65: 野望 | F65: 2 | G65: =G64 | H65: =H64 | I65: =I64 | J65: 手动 | K65: =K64 | M65: =M64 | N65: 3000 | P65: 0 | Q65: 0 | R65: 0.25 | S65: 0 | T65: =SUM(P65:S65) | U65: =2*T65/(15*(1+(5-BD65)*0.1)) | W65: 0 | X65: 20 | Y65: 0.5 | Z65: 0.5 | AD65: =(W65+AB65)*AC65 | AE65: =(X65+AB65)*AC65 | AM65: =IFS(AJ65 > 1.25, "S", AJ65 > 1, "A", AJ65 > 0.75, "B", AJ65 > 0.5, "C", AJ65 > 0.25, "D", AJ65 > 0, "E", TRUE, "-") | AN65: =IFS(AK65 > 1.25, "S", AK65 > 1, "A", AK65 > 0.75, "B", AK65 > 0.5, "C", AK65 > 0.25, "D", AK65 > 0, "E", TRUE, "-") | AO65: =IFS(AL65 > 1.25, "S", AL65 > 1, "A", AL65 > 0.75, "B", AL65 > 0.5, "C", AL65 > 0.25, "D", AL65 > 0, "E", TRUE, "-") | AV65: =IF(SUM(AJ65:AL65)=0, 0, (1 + F65 * 0.1) * (0.75 + 0.25 * MAX(0, MIN(1, IF(MAX(AJ65:AL65)=0, 0, (3*MAX(AJ65:AL65)-SUM(AJ65:AL65)) / (2*MAX(AJ65:AL65))))))) | AW65: =MAX(AJ65:AL65) | AX65: =IF(AW65=0, "", AW65 / ((1 + 0.1*N(F65)))) | AY65: =IF(SUM(AJ65:AL65)=0, 0, (1 + F65 * 0.1) * (1 + ((SUM(AJ65:AL65) - MAX(AJ65:AL65)) / (2 * MAX(AJ65:AL65))) * (1/0.75 - 1))) | BA65: =IF(AZ65=0, "", AZ65 / ((1 + 0.1*N(F65))/0.75)) | BB65: 0.1 | BD65: =BD64 | BE65: =BE64 | BN65: 1 | BO65: 3 | BQ65: 16 | BR65: =IFERROR(BQ65*100/CP65,"N/A") | BS65: 1 | BT65: 4 | BW65: 5 | BX65: =CP65/BW65 | BY65: =BW65/T65 | CA65: =CA64+5 | CB65: =AP65*AJ65+AQ65*AK65+AR65*AL65 | CP65: =CN65*BS65*BT65 | CQ65: =CP65/T65 | CR65: =100/CP65 | CS65: =100/CQ65 | CV65: =BL65/T65 | CW65: =100/CV65 | DC65: 待办 | DD65: 待办
A66: Flame Dancer | B66: 炎舞者 | D66: =IF($A66="","","WPN"&VLOOKUP(E66,'引用数据库'!Z:AC,4,FALSE)&VLOOKUP(H66,'引用数据库'!N:P,3,FALSE)&VLOOKUP(I66,'引用数据库'!S:U,3,FALSE)&TEXT(F66,"00")) | E66: 野望 | F66: 3 | G66: =G65 | H66: =H65 | I66: =I65 | J66: 手动 | K66: =K65 | M66: =M65 | N66: 3000 | P66: 0 | Q66: 0 | R66: 0.25 | S66: 0 | T66: =SUM(P66:S66) | U66: =2*T66/(15*(1+(5-BD66)*0.1)) | W66: 0 | X66: 20 | Y66: 0.5 | Z66: 0.5 | AD66: =(W66+AB66)*AC66 | AE66: =(X66+AB66)*AC66 | AM66: =IFS(AJ66 > 1.25, "S", AJ66 > 1, "A", AJ66 > 0.75, "B", AJ66 > 0.5, "C", AJ66 > 0.25, "D", AJ66 > 0, "E", TRUE, "-") | AN66: =IFS(AK66 > 1.25, "S", AK66 > 1, "A", AK66 > 0.75, "B", AK66 > 0.5, "C", AK66 > 0.25, "D", AK66 > 0, "E", TRUE, "-") | AO66: =IFS(AL66 > 1.25, "S", AL66 > 1, "A", AL66 > 0.75, "B", AL66 > 0.5, "C", AL66 > 0.25, "D", AL66 > 0, "E", TRUE, "-") | AV66: =IF(SUM(AJ66:AL66)=0, 0, (1 + F66 * 0.1) * (0.75 + 0.25 * MAX(0, MIN(1, IF(MAX(AJ66:AL66)=0, 0, (3*MAX(AJ66:AL66)-SUM(AJ66:AL66)) / (2*MAX(AJ66:AL66))))))) | AW66: =MAX(AJ66:AL66) | AX66: =IF(AW66=0, "", AW66 / ((1 + 0.1*N(F66)))) | AY66: =IF(SUM(AJ66:AL66)=0, 0, (1 + F66 * 0.1) * (1 + ((SUM(AJ66:AL66) - MAX(AJ66:AL66)) / (2 * MAX(AJ66:AL66))) * (1/0.75 - 1))) | BA66: =IF(AZ66=0, "", AZ66 / ((1 + 0.1*N(F66))/0.75)) | BB66: 0.1 | BD66: =BD65 | BE66: =BE65 | BN66: 1 | BO66: 3 | BQ66: 16 | BR66: =IFERROR(BQ66*100/CP66,"N/A") | BS66: 1 | BT66: 4 | BW66: 5 | BX66: =CP66/BW66 | BY66: =BW66/T66 | CA66: =CA65+5 | CB66: =AP66*AJ66+AQ66*AK66+AR66*AL66 | CP66: =CN66*BS66*BT66 | CQ66: =CP66/T66 | CR66: =100/CP66 | CS66: =100/CQ66 | CV66: =BL66/T66 | CW66: =100/CV66 | DC66: 待办 | DD66: 待办
A67: Flame Dancer | B67: 炎舞者 | D67: =IF($A67="","","WPN"&VLOOKUP(E67,'引用数据库'!Z:AC,4,FALSE)&VLOOKUP(H67,'引用数据库'!N:P,3,FALSE)&VLOOKUP(I67,'引用数据库'!S:U,3,FALSE)&TEXT(F67,"00")) | E67: 野望 | F67: 4 | G67: =G66 | H67: =H66 | I67: =I66 | J67: 手动 | K67: =K66 | M67: =M66 | N67: 3000 | P67: 0 | Q67: 0 | R67: 0.25 | S67: 0 | T67: =SUM(P67:S67) | U67: =2*T67/(15*(1+(5-BD67)*0.1)) | W67: 0 | X67: 20 | Y67: 0.5 | Z67: 0.5 | AD67: =(W67+AB67)*AC67 | AE67: =(X67+AB67)*AC67 | AM67: =IFS(AJ67 > 1.25, "S", AJ67 > 1, "A", AJ67 > 0.75, "B", AJ67 > 0.5, "C", AJ67 > 0.25, "D", AJ67 > 0, "E", TRUE, "-") | AN67: =IFS(AK67 > 1.25, "S", AK67 > 1, "A", AK67 > 0.75, "B", AK67 > 0.5, "C", AK67 > 0.25, "D", AK67 > 0, "E", TRUE, "-") | AO67: =IFS(AL67 > 1.25, "S", AL67 > 1, "A", AL67 > 0.75, "B", AL67 > 0.5, "C", AL67 > 0.25, "D", AL67 > 0, "E", TRUE, "-") | AV67: =IF(SUM(AJ67:AL67)=0, 0, (1 + F67 * 0.1) * (0.75 + 0.25 * MAX(0, MIN(1, IF(MAX(AJ67:AL67)=0, 0, (3*MAX(AJ67:AL67)-SUM(AJ67:AL67)) / (2*MAX(AJ67:AL67))))))) | AW67: =MAX(AJ67:AL67) | AX67: =IF(AW67=0, "", AW67 / ((1 + 0.1*N(F67)))) | AY67: =IF(SUM(AJ67:AL67)=0, 0, (1 + F67 * 0.1) * (1 + ((SUM(AJ67:AL67) - MAX(AJ67:AL67)) / (2 * MAX(AJ67:AL67))) * (1/0.75 - 1))) | BA67: =IF(AZ67=0, "", AZ67 / ((1 + 0.1*N(F67))/0.75)) | BB67: 0.1 | BD67: =BD66 | BE67: =BE66 | BN67: 1 | BO67: 3 | BQ67: 16 | BR67: =IFERROR(BQ67*100/CP67,"N/A") | BS67: 1 | BT67: 4 | BW67: 5 | BX67: =CP67/BW67 | BY67: =BW67/T67 | CA67: =CA66+5 | CB67: =AP67*AJ67+AQ67*AK67+AR67*AL67 | CP67: =CN67*BS67*BT67 | CQ67: =CP67/T67 | CR67: =100/CP67 | CS67: =100/CQ67 | CV67: =BL67/T67 | CW67: =100/CV67 | DC67: 待办 | DD67: 待办
A68: Flame Dancer | B68: 炎舞者 | D68: =IF($A68="","","WPN"&VLOOKUP(E68,'引用数据库'!Z:AC,4,FALSE)&VLOOKUP(H68,'引用数据库'!N:P,3,FALSE)&VLOOKUP(I68,'引用数据库'!S:U,3,FALSE)&TEXT(F68,"00")) | E68: 野望 | F68: 5 | G68: =G67 | H68: =H67 | I68: =I67 | J68: 手动 | K68: =K67 | M68: =M67 | N68: 3000 | P68: 0 | Q68: 0 | R68: 0.25 | S68: 0 | T68: =SUM(P68:S68) | U68: =2*T68/(15*(1+(5-BD68)*0.1)) | W68: 0 | X68: 20 | Y68: 0.5 | Z68: 0.5 | AD68: =(W68+AB68)*AC68 | AE68: =(X68+AB68)*AC68 | AM68: =IFS(AJ68 > 1.25, "S", AJ68 > 1, "A", AJ68 > 0.75, "B", AJ68 > 0.5, "C", AJ68 > 0.25, "D", AJ68 > 0, "E", TRUE, "-") | AN68: =IFS(AK68 > 1.25, "S", AK68 > 1, "A", AK68 > 0.75, "B", AK68 > 0.5, "C", AK68 > 0.25, "D", AK68 > 0, "E", TRUE, "-") | AO68: =IFS(AL68 > 1.25, "S", AL68 > 1, "A", AL68 > 0.75, "B", AL68 > 0.5, "C", AL68 > 0.25, "D", AL68 > 0, "E", TRUE, "-") | AV68: =IF(SUM(AJ68:AL68)=0, 0, (1 + F68 * 0.1) * (0.75 + 0.25 * MAX(0, MIN(1, IF(MAX(AJ68:AL68)=0, 0, (3*MAX(AJ68:AL68)-SUM(AJ68:AL68)) / (2*MAX(AJ68:AL68))))))) | AW68: =MAX(AJ68:AL68) | AX68: =IF(AW68=0, "", AW68 / ((1 + 0.1*N(F68)))) | AY68: =IF(SUM(AJ68:AL68)=0, 0, (1 + F68 * 0.1) * (1 + ((SUM(AJ68:AL68) - MAX(AJ68:AL68)) / (2 * MAX(AJ68:AL68))) * (1/0.75 - 1))) | BA68: =IF(AZ68=0, "", AZ68 / ((1 + 0.1*N(F68))/0.75)) | BB68: 0.1 | BD68: =BD67 | BE68: =BE67 | BN68: 1 | BO68: 3 | BQ68: 16 | BR68: =IFERROR(BQ68*100/CP68,"N/A") | BS68: 1 | BT68: 4 | BW68: 5 | BX68: =CP68/BW68 | BY68: =BW68/T68 | CA68: =CA67+5 | CB68: =AP68*AJ68+AQ68*AK68+AR68*AL68 | CP68: =CN68*BS68*BT68 | CQ68: =CP68/T68 | CR68: =100/CP68 | CS68: =100/CQ68 | CV68: =BL68/T68 | CW68: =100/CV68 | DC68: 待办 | DD68: 待办
A69: RPG-33 | B69: RPG-33 | D69: =IF($A69="","","WPN"&VLOOKUP(E69,'引用数据库'!Z:AC,4,FALSE)&VLOOKUP(H69,'引用数据库'!N:P,3,FALSE)&VLOOKUP(I69,'引用数据库'!S:U,3,FALSE)&TEXT(F69,"00")) | E69: 纪念碑 | F69: 0 | G69: 远程 | H69: 发射器 | I69: 动能 | J69: 手动 | K69: 4 | M69: 1 | N69: 0 | O69: N/A | U69: =2*T69/(15*(1+(5-BD69)*0.1)) | AD69: =(W69+AB69)*AC69 | AE69: =(X69+AB69)*AC69 | AM69: =IFS(AJ69 > 1.25, "S", AJ69 > 1, "A", AJ69 > 0.75, "B", AJ69 > 0.5, "C", AJ69 > 0.25, "D", AJ69 > 0, "E", TRUE, "-") | AN69: =IFS(AK69 > 1.25, "S", AK69 > 1, "A", AK69 > 0.75, "B", AK69 > 0.5, "C", AK69 > 0.25, "D", AK69 > 0, "E", TRUE, "-") | AO69: =IFS(AL69 > 1.25, "S", AL69 > 1, "A", AL69 > 0.75, "B", AL69 > 0.5, "C", AL69 > 0.25, "D", AL69 > 0, "E", TRUE, "-") | AV69: =IF(SUM(AJ69:AL69)=0, 0, (1 + F69 * 0.1) * (0.75 + 0.25 * MAX(0, MIN(1, IF(MAX(AJ69:AL69)=0, 0, (3*MAX(AJ69:AL69)-SUM(AJ69:AL69)) / (2*MAX(AJ69:AL69))))))) | AW69: =MAX(AJ69:AL69) | AX69: =IF(AW69=0, "", AW69 / ((1 + 0.1*N(F69)))) | AY69: =IF(SUM(AJ69:AL69)=0, 0, (1 + F69 * 0.1) * (1 + ((SUM(AJ69:AL69) - MAX(AJ69:AL69)) / (2 * MAX(AJ69:AL69))) * (1/0.75 - 1))) | BA69: =IF(AZ69=0, "", AZ69 / ((1 + 0.1*N(F69))/0.75)) | BB69: 0.1 | BG69: =T69*20/BT69/BS69 | BN69: 1 | BQ69: 4 | BR69: =IFERROR(BQ69*100/CP69,"N/A") | CP69: =CN69*BS69*BT69 | CR69: =100/CP69 | CS69: =100/CQ69 | CV69: =BL69/T69 | CW69: =100/CV69 | CY69: 经典反坦克火箭筒的延伸版本， 广泛用于企业与黑帮的各种小规模武装冲突。 由于火箭筒结构过于简单， 在升级了无壳打印弹兼容后， 打印一个火箭筒比打印一枚火箭弹耗时还短。 | DA69: =TEXTJOIN("、", TRUE, FILTER('武器技能'!B:B, '武器技能'!E:E = H69)) | DC69: 不急 | DD69: 不急
A70: RPG-33 | B70: RPG-33 | D70: =IF($A70="","","WPN"&VLOOKUP(E70,'引用数据库'!Z:AC,4,FALSE)&VLOOKUP(H70,'引用数据库'!N:P,3,FALSE)&VLOOKUP(I70,'引用数据库'!S:U,3,FALSE)&TEXT(F70,"00")) | E70: 纪念碑 | F70: 1 | G70: =G69 | H70: =H69 | I70: =I69 | J70: =J69 | K70: =K69 | M70: =M69 | N70: 0 | O70: N/A | U70: =2*T70/(15*(1+(5-BD70)*0.1)) | AD70: =(W70+AB70)*AC70 | AE70: =(X70+AB70)*AC70 | AM70: =IFS(AJ70 > 1.25, "S", AJ70 > 1, "A", AJ70 > 0.75, "B", AJ70 > 0.5, "C", AJ70 > 0.25, "D", AJ70 > 0, "E", TRUE, "-") | AN70: =IFS(AK70 > 1.25, "S", AK70 > 1, "A", AK70 > 0.75, "B", AK70 > 0.5, "C", AK70 > 0.25, "D", AK70 > 0, "E", TRUE, "-") | AO70: =IFS(AL70 > 1.25, "S", AL70 > 1, "A", AL70 > 0.75, "B", AL70 > 0.5, "C", AL70 > 0.25, "D", AL70 > 0, "E", TRUE, "-") | AV70: =IF(SUM(AJ70:AL70)=0, 0, (1 + F70 * 0.1) * (0.75 + 0.25 * MAX(0, MIN(1, IF(MAX(AJ70:AL70)=0, 0, (3*MAX(AJ70:AL70)-SUM(AJ70:AL70)) / (2*MAX(AJ70:AL70))))))) | AW70: =MAX(AJ70:AL70) | AX70: =IF(AW70=0, "", AW70 / ((1 + 0.1*N(F70)))) | AY70: =IF(SUM(AJ70:AL70)=0, 0, (1 + F70 * 0.1) * (1 + ((SUM(AJ70:AL70) - MAX(AJ70:AL70)) / (2 * MAX(AJ70:AL70))) * (1/0.75 - 1))) | BA70: =IF(AZ70=0, "", AZ70 / ((1 + 0.1*N(F70))/0.75)) | BB70: 0.1 | BD70: =BD69 | BE70: =BE69 | BN70: 1 | BQ70: 4 | BR70: =IFERROR(BQ70*100/CP70,"N/A") | BV70: =IFERROR( ROUND( (10 / $T$4) * ((CP70 / T70) / ($CP$4 / $T$4)) ^ 0.9 * (T70 / $T$4) ^ 0.2 * ((1 + N70) / (1 + $N$4)) ^ 0.15 * ((1 + BQ70) / (1 + $BQ$4)) ^ 0.15 * ((1 + BD70) / (1 + $BD$4)) ^ 0.2 * ((1 + BH70) / (1 + $BH$4)) ^ 0.2 * ((1 + BL70) / (1 + $BL$4)) ^ 0.2 * T70, 0), CP70 * 1000) | CP70: =CN70*BS70*BT70 | CR70: =100/CP70 | CS70: =100/CQ70 | CV70: =BL70/T70 | CW70: =100/CV70 | DC70: 不急 | DD70: 不急
A71: RPG-33 | B71: RPG-33 | D71: =IF($A71="","","WPN"&VLOOKUP(E71,'引用数据库'!Z:AC,4,FALSE)&VLOOKUP(H71,'引用数据库'!N:P,3,FALSE)&VLOOKUP(I71,'引用数据库'!S:U,3,FALSE)&TEXT(F71,"00")) | E71: 纪念碑 | F71: 2 | G71: =G70 | H71: =H70 | I71: =I70 | J71: =J70 | K71: =K70 | M71: =M70 | N71: 0 | O71: N/A | U71: =2*T71/(15*(1+(5-BD71)*0.1)) | AD71: =(W71+AB71)*AC71 | AE71: =(X71+AB71)*AC71 | AM71: =IFS(AJ71 > 1.25, "S", AJ71 > 1, "A", AJ71 > 0.75, "B", AJ71 > 0.5, "C", AJ71 > 0.25, "D", AJ71 > 0, "E", TRUE, "-") | AN71: =IFS(AK71 > 1.25, "S", AK71 > 1, "A", AK71 > 0.75, "B", AK71 > 0.5, "C", AK71 > 0.25, "D", AK71 > 0, "E", TRUE, "-") | AO71: =IFS(AL71 > 1.25, "S", AL71 > 1, "A", AL71 > 0.75, "B", AL71 > 0.5, "C", AL71 > 0.25, "D", AL71 > 0, "E", TRUE, "-") | AV71: =IF(SUM(AJ71:AL71)=0, 0, (1 + F71 * 0.1) * (0.75 + 0.25 * MAX(0, MIN(1, IF(MAX(AJ71:AL71)=0, 0, (3*MAX(AJ71:AL71)-SUM(AJ71:AL71)) / (2*MAX(AJ71:AL71))))))) | AW71: =MAX(AJ71:AL71) | AX71: =IF(AW71=0, "", AW71 / ((1 + 0.1*N(F71)))) | AY71: =IF(SUM(AJ71:AL71)=0, 0, (1 + F71 * 0.1) * (1 + ((SUM(AJ71:AL71) - MAX(AJ71:AL71)) / (2 * MAX(AJ71:AL71))) * (1/0.75 - 1))) | BA71: =IF(AZ71=0, "", AZ71 / ((1 + 0.1*N(F71))/0.75)) | BB71: 0.1 | BD71: =BD70 | BE71: =BE70 | BN71: 1 | BQ71: 4 | BR71: =IFERROR(BQ71*100/CP71,"N/A") | CP71: =CN71*BS71*BT71 | CR71: =100/CP71 | CS71: =100/CQ71 | CV71: =BL71/T71 | CW71: =100/CV71 | DC71: 不急 | DD71: 不急
A72: RPG-33 | B72: RPG-33 | D72: =IF($A72="","","WPN"&VLOOKUP(E72,'引用数据库'!Z:AC,4,FALSE)&VLOOKUP(H72,'引用数据库'!N:P,3,FALSE)&VLOOKUP(I72,'引用数据库'!S:U,3,FALSE)&TEXT(F72,"00")) | E72: 纪念碑 | F72: 3 | G72: =G71 | H72: =H71 | I72: =I71 | J72: =J71 | K72: =K71 | M72: =M71 | N72: 0 | O72: N/A | U72: =2*T72/(15*(1+(5-BD72)*0.1)) | AD72: =(W72+AB72)*AC72 | AE72: =(X72+AB72)*AC72 | AM72: =IFS(AJ72 > 1.25, "S", AJ72 > 1, "A", AJ72 > 0.75, "B", AJ72 > 0.5, "C", AJ72 > 0.25, "D", AJ72 > 0, "E", TRUE, "-") | AN72: =IFS(AK72 > 1.25, "S", AK72 > 1, "A", AK72 > 0.75, "B", AK72 > 0.5, "C", AK72 > 0.25, "D", AK72 > 0, "E", TRUE, "-") | AO72: =IFS(AL72 > 1.25, "S", AL72 > 1, "A", AL72 > 0.75, "B", AL72 > 0.5, "C", AL72 > 0.25, "D", AL72 > 0, "E", TRUE, "-") | AV72: =IF(SUM(AJ72:AL72)=0, 0, (1 + F72 * 0.1) * (0.75 + 0.25 * MAX(0, MIN(1, IF(MAX(AJ72:AL72)=0, 0, (3*MAX(AJ72:AL72)-SUM(AJ72:AL72)) / (2*MAX(AJ72:AL72))))))) | AW72: =MAX(AJ72:AL72) | AX72: =IF(AW72=0, "", AW72 / ((1 + 0.1*N(F72)))) | AY72: =IF(SUM(AJ72:AL72)=0, 0, (1 + F72 * 0.1) * (1 + ((SUM(AJ72:AL72) - MAX(AJ72:AL72)) / (2 * MAX(AJ72:AL72))) * (1/0.75 - 1))) | BA72: =IF(AZ72=0, "", AZ72 / ((1 + 0.1*N(F72))/0.75)) | BB72: 0.1 | BD72: =BD71 | BE72: =BE71 | BN72: 1 | BQ72: 4 | BR72: =IFERROR(BQ72*100/CP72,"N/A") | CP72: =CN72*BS72*BT72 | CR72: =100/CP72 | CS72: =100/CQ72 | CV72: =BL72/T72 | CW72: =100/CV72 | DC72: 不急 | DD72: 不急
A73: RPG-33 | B73: RPG-33 | D73: =IF($A73="","","WPN"&VLOOKUP(E73,'引用数据库'!Z:AC,4,FALSE)&VLOOKUP(H73,'引用数据库'!N:P,3,FALSE)&VLOOKUP(I73,'引用数据库'!S:U,3,FALSE)&TEXT(F73,"00")) | E73: 纪念碑 | F73: 4 | G73: =G72 | H73: =H72 | I73: =I72 | J73: =J72 | K73: =K72 | M73: =M72 | N73: 0 | O73: N/A | U73: =2*T73/(15*(1+(5-BD73)*0.1)) | AD73: =(W73+AB73)*AC73 | AE73: =(X73+AB73)*AC73 | AM73: =IFS(AJ73 > 1.25, "S", AJ73 > 1, "A", AJ73 > 0.75, "B", AJ73 > 0.5, "C", AJ73 > 0.25, "D", AJ73 > 0, "E", TRUE, "-") | AN73: =IFS(AK73 > 1.25, "S", AK73 > 1, "A", AK73 > 0.75, "B", AK73 > 0.5, "C", AK73 > 0.25, "D", AK73 > 0, "E", TRUE, "-") | AO73: =IFS(AL73 > 1.25, "S", AL73 > 1, "A", AL73 > 0.75, "B", AL73 > 0.5, "C", AL73 > 0.25, "D", AL73 > 0, "E", TRUE, "-") | AV73: =IF(SUM(AJ73:AL73)=0, 0, (1 + F73 * 0.1) * (0.75 + 0.25 * MAX(0, MIN(1, IF(MAX(AJ73:AL73)=0, 0, (3*MAX(AJ73:AL73)-SUM(AJ73:AL73)) / (2*MAX(AJ73:AL73))))))) | AW73: =MAX(AJ73:AL73) | AX73: =IF(AW73=0, "", AW73 / ((1 + 0.1*N(F73)))) | AY73: =IF(SUM(AJ73:AL73)=0, 0, (1 + F73 * 0.1) * (1 + ((SUM(AJ73:AL73) - MAX(AJ73:AL73)) / (2 * MAX(AJ73:AL73))) * (1/0.75 - 1))) | BA73: =IF(AZ73=0, "", AZ73 / ((1 + 0.1*N(F73))/0.75)) | BB73: 0.1 | BD73: =BD72 | BE73: =BE72 | BN73: 1 | BQ73: 4 | BR73: =IFERROR(BQ73*100/CP73,"N/A") | CP73: =CN73*BS73*BT73 | CR73: =100/CP73 | CS73: =100/CQ73 | CV73: =BL73/T73 | CW73: =100/CV73 | DC73: 不急 | DD73: 不急
A74: RPG-33 | B74: RPG-33 | D74: =IF($A74="","","WPN"&VLOOKUP(E74,'引用数据库'!Z:AC,4,FALSE)&VLOOKUP(H74,'引用数据库'!N:P,3,FALSE)&VLOOKUP(I74,'引用数据库'!S:U,3,FALSE)&TEXT(F74,"00")) | E74: 纪念碑 | F74: 5 | G74: =G73 | H74: =H73 | I74: =I73 | J74: =J73 | K74: =K73 | M74: =M73 | N74: 0 | O74: N/A | U74: =2*T74/(15*(1+(5-BD74)*0.1)) | AD74: =(W74+AB74)*AC74 | AE74: =(X74+AB74)*AC74 | AM74: =IFS(AJ74 > 1.25, "S", AJ74 > 1, "A", AJ74 > 0.75, "B", AJ74 > 0.5, "C", AJ74 > 0.25, "D", AJ74 > 0, "E", TRUE, "-") | AN74: =IFS(AK74 > 1.25, "S", AK74 > 1, "A", AK74 > 0.75, "B", AK74 > 0.5, "C", AK74 > 0.25, "D", AK74 > 0, "E", TRUE, "-") | AO74: =IFS(AL74 > 1.25, "S", AL74 > 1, "A", AL74 > 0.75, "B", AL74 > 0.5, "C", AL74 > 0.25, "D", AL74 > 0, "E", TRUE, "-") | AV74: =IF(SUM(AJ74:AL74)=0, 0, (1 + F74 * 0.1) * (0.75 + 0.25 * MAX(0, MIN(1, IF(MAX(AJ74:AL74)=0, 0, (3*MAX(AJ74:AL74)-SUM(AJ74:AL74)) / (2*MAX(AJ74:AL74))))))) | AW74: =MAX(AJ74:AL74) | AX74: =IF(AW74=0, "", AW74 / ((1 + 0.1*N(F74)))) | AY74: =IF(SUM(AJ74:AL74)=0, 0, (1 + F74 * 0.1) * (1 + ((SUM(AJ74:AL74) - MAX(AJ74:AL74)) / (2 * MAX(AJ74:AL74))) * (1/0.75 - 1))) | BA74: =IF(AZ74=0, "", AZ74 / ((1 + 0.1*N(F74))/0.75)) | BB74: 0.1 | BD74: =BD73 | BE74: =BE73 | BN74: 1 | BQ74: 4 | BR74: =IFERROR(BQ74*100/CP74,"N/A") | CP74: =CN74*BS74*BT74 | CR74: =100/CP74 | CS74: =100/CQ74 | CV74: =BL74/T74 | CW74: =100/CV74 | DC74: 不急 | DD74: 不急
A75: Arctic Savior | B75: 北极救星 | D75: =IF($A75="","","WPN"&VLOOKUP(E75,'引用数据库'!Z:AC,4,FALSE)&VLOOKUP(H75,'引用数据库'!N:P,3,FALSE)&VLOOKUP(I75,'引用数据库'!S:U,3,FALSE)&TEXT(F75,"00")) | E75: 洛克海德 | F75: 0 | G75: 远程 | H75: 狙击枪 | I75: 热能 | J75: 手动 | K75: 1 | M75: 1 | O75: N/A | U75: =2*T75/(15*(1+(5-BD75)*0.1)) | AD75: =(W75+AB75)*AC75 | AE75: =(X75+AB75)*AC75 | AM75: =IFS(AJ75 > 1.25, "S", AJ75 > 1, "A", AJ75 > 0.75, "B", AJ75 > 0.5, "C", AJ75 > 0.25, "D", AJ75 > 0, "E", TRUE, "-") | AN75: =IFS(AK75 > 1.25, "S", AK75 > 1, "A", AK75 > 0.75, "B", AK75 > 0.5, "C", AK75 > 0.25, "D", AK75 > 0, "E", TRUE, "-") | AO75: =IFS(AL75 > 1.25, "S", AL75 > 1, "A", AL75 > 0.75, "B", AL75 > 0.5, "C", AL75 > 0.25, "D", AL75 > 0, "E", TRUE, "-") | AV75: =IF(SUM(AJ75:AL75)=0, 0, (1 + F75 * 0.1) * (0.75 + 0.25 * MAX(0, MIN(1, IF(MAX(AJ75:AL75)=0, 0, (3*MAX(AJ75:AL75)-SUM(AJ75:AL75)) / (2*MAX(AJ75:AL75))))))) | AW75: =MAX(AJ75:AL75) | AX75: =IF(AW75=0, "", AW75 / ((1 + 0.1*N(F75)))) | AY75: =IF(SUM(AJ75:AL75)=0, 0, (1 + F75 * 0.1) * (1 + ((SUM(AJ75:AL75) - MAX(AJ75:AL75)) / (2 * MAX(AJ75:AL75))) * (1/0.75 - 1))) | BA75: =IF(AZ75=0, "", AZ75 / ((1 + 0.1*N(F75))/0.75)) | BB75: 0.1 | BG75: =T75*20/BT75/BS75 | BN75: 5 | BR75: =IFERROR(BQ75*100/CP75,"N/A") | CP75: =CN75*BS75*BT75 | CR75: =100/CP75 | CS75: =100/CQ75 | CV75: =BL75/T75 | CW75: =100/CV75 | CY75: 著名的反器械狙击步枪， 最初在“荒地突袭”事件中为洛克海德打出名声。 “消泡”事件后自动机械作战单位的数量大幅减少，但它依旧在对抗赛博格的战场上表现出众。 | DA75: =TEXTJOIN("、", TRUE, FILTER('武器技能'!B:B, '武器技能'!E:E = H75)) | DC75: 不急 | DD75: 不急
A76: Arctic Savior | B76: 北极救星 | D76: =IF($A76="","","WPN"&VLOOKUP(E76,'引用数据库'!Z:AC,4,FALSE)&VLOOKUP(H76,'引用数据库'!N:P,3,FALSE)&VLOOKUP(I76,'引用数据库'!S:U,3,FALSE)&TEXT(F76,"00")) | E76: 洛克海德 | F76: 1 | G76: =G75 | H76: =H75 | I76: =I75 | J76: =J75 | K76: =K75 | M76: =M75 | O76: N/A | U76: =2*T76/(15*(1+(5-BD76)*0.1)) | AD76: =(W76+AB76)*AC76 | AE76: =(X76+AB76)*AC76 | AM76: =IFS(AJ76 > 1.25, "S", AJ76 > 1, "A", AJ76 > 0.75, "B", AJ76 > 0.5, "C", AJ76 > 0.25, "D", AJ76 > 0, "E", TRUE, "-") | AN76: =IFS(AK76 > 1.25, "S", AK76 > 1, "A", AK76 > 0.75, "B", AK76 > 0.5, "C", AK76 > 0.25, "D", AK76 > 0, "E", TRUE, "-") | AO76: =IFS(AL76 > 1.25, "S", AL76 > 1, "A", AL76 > 0.75, "B", AL76 > 0.5, "C", AL76 > 0.25, "D", AL76 > 0, "E", TRUE, "-") | AV76: =IF(SUM(AJ76:AL76)=0, 0, (1 + F76 * 0.1) * (0.75 + 0.25 * MAX(0, MIN(1, IF(MAX(AJ76:AL76)=0, 0, (3*MAX(AJ76:AL76)-SUM(AJ76:AL76)) / (2*MAX(AJ76:AL76))))))) | AW76: =MAX(AJ76:AL76) | AX76: =IF(AW76=0, "", AW76 / ((1 + 0.1*N(F76)))) | AY76: =IF(SUM(AJ76:AL76)=0, 0, (1 + F76 * 0.1) * (1 + ((SUM(AJ76:AL76) - MAX(AJ76:AL76)) / (2 * MAX(AJ76:AL76))) * (1/0.75 - 1))) | BA76: =IF(AZ76=0, "", AZ76 / ((1 + 0.1*N(F76))/0.75)) | BB76: 0.1 | BD76: =BD75 | BE76: =BE75 | BN76: 5 | BR76: =IFERROR(BQ76*100/CP76,"N/A") | BV76: =IFERROR( ROUND( (10 / $T$4) * ((CP76 / T76) / ($CP$4 / $T$4)) ^ 0.9 * (T76 / $T$4) ^ 0.2 * ((1 + N76) / (1 + $N$4)) ^ 0.15 * ((1 + BQ76) / (1 + $BQ$4)) ^ 0.15 * ((1 + BD76) / (1 + $BD$4)) ^ 0.2 * ((1 + BH76) / (1 + $BH$4)) ^ 0.2 * ((1 + BL76) / (1 + $BL$4)) ^ 0.2 * T76, 0), CP76 * 1000) | CP76: =CN76*BS76*BT76 | CR76: =100/CP76 | CS76: =100/CQ76 | CV76: =BL76/T76 | CW76: =100/CV76 | DC76: 不急 | DD76: 不急
A77: Arctic Savior | B77: 北极救星 | D77: =IF($A77="","","WPN"&VLOOKUP(E77,'引用数据库'!Z:AC,4,FALSE)&VLOOKUP(H77,'引用数据库'!N:P,3,FALSE)&VLOOKUP(I77,'引用数据库'!S:U,3,FALSE)&TEXT(F77,"00")) | E77: 洛克海德 | F77: 2 | G77: =G76 | H77: =H76 | I77: =I76 | J77: =J76 | K77: =K76 | M77: =M76 | O77: N/A | U77: =2*T77/(15*(1+(5-BD77)*0.1)) | AD77: =(W77+AB77)*AC77 | AE77: =(X77+AB77)*AC77 | AM77: =IFS(AJ77 > 1.25, "S", AJ77 > 1, "A", AJ77 > 0.75, "B", AJ77 > 0.5, "C", AJ77 > 0.25, "D", AJ77 > 0, "E", TRUE, "-") | AN77: =IFS(AK77 > 1.25, "S", AK77 > 1, "A", AK77 > 0.75, "B", AK77 > 0.5, "C", AK77 > 0.25, "D", AK77 > 0, "E", TRUE, "-") | AO77: =IFS(AL77 > 1.25, "S", AL77 > 1, "A", AL77 > 0.75, "B", AL77 > 0.5, "C", AL77 > 0.25, "D", AL77 > 0, "E", TRUE, "-") | AV77: =IF(SUM(AJ77:AL77)=0, 0, (1 + F77 * 0.1) * (0.75 + 0.25 * MAX(0, MIN(1, IF(MAX(AJ77:AL77)=0, 0, (3*MAX(AJ77:AL77)-SUM(AJ77:AL77)) / (2*MAX(AJ77:AL77))))))) | AW77: =MAX(AJ77:AL77) | AX77: =IF(AW77=0, "", AW77 / ((1 + 0.1*N(F77)))) | AY77: =IF(SUM(AJ77:AL77)=0, 0, (1 + F77 * 0.1) * (1 + ((SUM(AJ77:AL77) - MAX(AJ77:AL77)) / (2 * MAX(AJ77:AL77))) * (1/0.75 - 1))) | BA77: =IF(AZ77=0, "", AZ77 / ((1 + 0.1*N(F77))/0.75)) | BB77: 0.1 | BD77: =BD76 | BE77: =BE76 | BN77: 5 | BR77: =IFERROR(BQ77*100/CP77,"N/A") | CP77: =CN77*BS77*BT77 | CR77: =100/CP77 | CS77: =100/CQ77 | CV77: =BL77/T77 | CW77: =100/CV77 | DC77: 不急 | DD77: 不急
A78: Arctic Savior | B78: 北极救星 | D78: =IF($A78="","","WPN"&VLOOKUP(E78,'引用数据库'!Z:AC,4,FALSE)&VLOOKUP(H78,'引用数据库'!N:P,3,FALSE)&VLOOKUP(I78,'引用数据库'!S:U,3,FALSE)&TEXT(F78,"00")) | E78: 洛克海德 | F78: 3 | G78: =G77 | H78: =H77 | I78: =I77 | J78: =J77 | K78: =K77 | M78: =M77 | O78: N/A | U78: =2*T78/(15*(1+(5-BD78)*0.1)) | AD78: =(W78+AB78)*AC78 | AE78: =(X78+AB78)*AC78 | AM78: =IFS(AJ78 > 1.25, "S", AJ78 > 1, "A", AJ78 > 0.75, "B", AJ78 > 0.5, "C", AJ78 > 0.25, "D", AJ78 > 0, "E", TRUE, "-") | AN78: =IFS(AK78 > 1.25, "S", AK78 > 1, "A", AK78 > 0.75, "B", AK78 > 0.5, "C", AK78 > 0.25, "D", AK78 > 0, "E", TRUE, "-") | AO78: =IFS(AL78 > 1.25, "S", AL78 > 1, "A", AL78 > 0.75, "B", AL78 > 0.5, "C", AL78 > 0.25, "D", AL78 > 0, "E", TRUE, "-") | AV78: =IF(SUM(AJ78:AL78)=0, 0, (1 + F78 * 0.1) * (0.75 + 0.25 * MAX(0, MIN(1, IF(MAX(AJ78:AL78)=0, 0, (3*MAX(AJ78:AL78)-SUM(AJ78:AL78)) / (2*MAX(AJ78:AL78))))))) | AW78: =MAX(AJ78:AL78) | AX78: =IF(AW78=0, "", AW78 / ((1 + 0.1*N(F78)))) | AY78: =IF(SUM(AJ78:AL78)=0, 0, (1 + F78 * 0.1) * (1 + ((SUM(AJ78:AL78) - MAX(AJ78:AL78)) / (2 * MAX(AJ78:AL78))) * (1/0.75 - 1))) | BA78: =IF(AZ78=0, "", AZ78 / ((1 + 0.1*N(F78))/0.75)) | BB78: 0.1 | BD78: =BD77 | BE78: =BE77 | BN78: 5 | BR78: =IFERROR(BQ78*100/CP78,"N/A") | CP78: =CN78*BS78*BT78 | CR78: =100/CP78 | CS78: =100/CQ78 | CV78: =BL78/T78 | CW78: =100/CV78 | DC78: 不急 | DD78: 不急
A79: Arctic Savior | B79: 北极救星 | D79: =IF($A79="","","WPN"&VLOOKUP(E79,'引用数据库'!Z:AC,4,FALSE)&VLOOKUP(H79,'引用数据库'!N:P,3,FALSE)&VLOOKUP(I79,'引用数据库'!S:U,3,FALSE)&TEXT(F79,"00")) | E79: 洛克海德 | F79: 4 | G79: =G78 | H79: =H78 | I79: =I78 | J79: =J78 | K79: =K78 | M79: =M78 | O79: N/A | U79: =2*T79/(15*(1+(5-BD79)*0.1)) | AD79: =(W79+AB79)*AC79 | AE79: =(X79+AB79)*AC79 | AM79: =IFS(AJ79 > 1.25, "S", AJ79 > 1, "A", AJ79 > 0.75, "B", AJ79 > 0.5, "C", AJ79 > 0.25, "D", AJ79 > 0, "E", TRUE, "-") | AN79: =IFS(AK79 > 1.25, "S", AK79 > 1, "A", AK79 > 0.75, "B", AK79 > 0.5, "C", AK79 > 0.25, "D", AK79 > 0, "E", TRUE, "-") | AO79: =IFS(AL79 > 1.25, "S", AL79 > 1, "A", AL79 > 0.75, "B", AL79 > 0.5, "C", AL79 > 0.25, "D", AL79 > 0, "E", TRUE, "-") | AV79: =IF(SUM(AJ79:AL79)=0, 0, (1 + F79 * 0.1) * (0.75 + 0.25 * MAX(0, MIN(1, IF(MAX(AJ79:AL79)=0, 0, (3*MAX(AJ79:AL79)-SUM(AJ79:AL79)) / (2*MAX(AJ79:AL79))))))) | AW79: =MAX(AJ79:AL79) | AX79: =IF(AW79=0, "", AW79 / ((1 + 0.1*N(F79)))) | AY79: =IF(SUM(AJ79:AL79)=0, 0, (1 + F79 * 0.1) * (1 + ((SUM(AJ79:AL79) - MAX(AJ79:AL79)) / (2 * MAX(AJ79:AL79))) * (1/0.75 - 1))) | BA79: =IF(AZ79=0, "", AZ79 / ((1 + 0.1*N(F79))/0.75)) | BB79: 0.1 | BD79: =BD78 | BE79: =BE78 | BN79: 5 | BR79: =IFERROR(BQ79*100/CP79,"N/A") | CP79: =CN79*BS79*BT79 | CR79: =100/CP79 | CS79: =100/CQ79 | CV79: =BL79/T79 | CW79: =100/CV79 | DC79: 不急 | DD79: 不急
A80: Arctic Savior | B80: 北极救星 | D80: =IF($A80="","","WPN"&VLOOKUP(E80,'引用数据库'!Z:AC,4,FALSE)&VLOOKUP(H80,'引用数据库'!N:P,3,FALSE)&VLOOKUP(I80,'引用数据库'!S:U,3,FALSE)&TEXT(F80,"00")) | E80: 洛克海德 | F80: 5 | G80: =G79 | H80: =H79 | I80: =I79 | J80: =J79 | K80: =K79 | M80: =M79 | O80: N/A | U80: =2*T80/(15*(1+(5-BD80)*0.1)) | AD80: =(W80+AB80)*AC80 | AE80: =(X80+AB80)*AC80 | AM80: =IFS(AJ80 > 1.25, "S", AJ80 > 1, "A", AJ80 > 0.75, "B", AJ80 > 0.5, "C", AJ80 > 0.25, "D", AJ80 > 0, "E", TRUE, "-") | AN80: =IFS(AK80 > 1.25, "S", AK80 > 1, "A", AK80 > 0.75, "B", AK80 > 0.5, "C", AK80 > 0.25, "D", AK80 > 0, "E", TRUE, "-") | AO80: =IFS(AL80 > 1.25, "S", AL80 > 1, "A", AL80 > 0.75, "B", AL80 > 0.5, "C", AL80 > 0.25, "D", AL80 > 0, "E", TRUE, "-") | AV80: =IF(SUM(AJ80:AL80)=0, 0, (1 + F80 * 0.1) * (0.75 + 0.25 * MAX(0, MIN(1, IF(MAX(AJ80:AL80)=0, 0, (3*MAX(AJ80:AL80)-SUM(AJ80:AL80)) / (2*MAX(AJ80:AL80))))))) | AW80: =MAX(AJ80:AL80) | AX80: =IF(AW80=0, "", AW80 / ((1 + 0.1*N(F80)))) | AY80: =IF(SUM(AJ80:AL80)=0, 0, (1 + F80 * 0.1) * (1 + ((SUM(AJ80:AL80) - MAX(AJ80:AL80)) / (2 * MAX(AJ80:AL80))) * (1/0.75 - 1))) | BA80: =IF(AZ80=0, "", AZ80 / ((1 + 0.1*N(F80))/0.75)) | BB80: 0.1 | BD80: =BD79 | BE80: =BE79 | BN80: 5 | BR80: =IFERROR(BQ80*100/CP80,"N/A") | CP80: =CN80*BS80*BT80 | CR80: =100/CP80 | CS80: =100/CQ80 | CV80: =BL80/T80 | CW80: =100/CV80 | DC80: 不急 | DD80: 不急
A81: Knock Knock | B81: 开门红 | D81: =IF($A81="","","WPN"&VLOOKUP(E81,'引用数据库'!Z:AC,4,FALSE)&VLOOKUP(H81,'引用数据库'!N:P,3,FALSE)&VLOOKUP(I81,'引用数据库'!S:U,3,FALSE)&TEXT(F81,"00")) | E81: 劳旅 | F81: 0 | G81: 远程 | H81: 霰弹枪 | I81: 电磁 | J81: 手动 | K81: 1 | M81: 1 | N81: 800 | O81: N/A | P81: 0 | Q81: 0 | R81: 0.3 | S81: 0 | T81: =SUM(P81:S81) | U81: =2*T81/(15*(1+(5-BD81)*0.1)) | W81: 60 | X81: 90 | Y81: 0.25 | Z81: 0.25 | AB81: 10 | AC81: 1 | AD81: =(W81+AB81)*AC81 | AE81: =(X81+AB81)*AC81 | AM81: =IFS(AJ81 > 1.25, "S", AJ81 > 1, "A", AJ81 > 0.75, "B", AJ81 > 0.5, "C", AJ81 > 0.25, "D", AJ81 > 0, "E", TRUE, "-") | AN81: =IFS(AK81 > 1.25, "S", AK81 > 1, "A", AK81 > 0.75, "B", AK81 > 0.5, "C", AK81 > 0.25, "D", AK81 > 0, "E", TRUE, "-") | AO81: =IFS(AL81 > 1.25, "S", AL81 > 1, "A", AL81 > 0.75, "B", AL81 > 0.5, "C", AL81 > 0.25, "D", AL81 > 0, "E", TRUE, "-") | AV81: =IF(SUM(AJ81:AL81)=0, 0, (1 + F81 * 0.1) * (0.75 + 0.25 * MAX(0, MIN(1, IF(MAX(AJ81:AL81)=0, 0, (3*MAX(AJ81:AL81)-SUM(AJ81:AL81)) / (2*MAX(AJ81:AL81))))))) | AW81: =MAX(AJ81:AL81) | AX81: =IF(AW81=0, "", AW81 / ((1 + 0.1*N(F81)))) | AY81: =IF(SUM(AJ81:AL81)=0, 0, (1 + F81 * 0.1) * (1 + ((SUM(AJ81:AL81) - MAX(AJ81:AL81)) / (2 * MAX(AJ81:AL81))) * (1/0.75 - 1))) | BA81: =IF(AZ81=0, "", AZ81 / ((1 + 0.1*N(F81))/0.75)) | BB81: 0.1 | BD81: 3 | BE81: 2 | BG81: =T81*20/BT81/BS81 | BH81: 20 | BL81: 20 | BN81: 32 | BO81: 1.5 | BQ81: 2 | BR81: =IFERROR(BQ81*100/CP81,"N/A") | BS81: 16 | BT81: 9 | BW81: =BW82 | CA81: 10 | CB81: =CA81*BB81*(AP81*AJ81+AQ81*AK81+AR81*AL81) | CC81: =CA81+CB81 | CJ81: 2.5 | CK81: =CJ81/BS81 | CN81: =CK81*CC81 | CP81: =CN81*BS81*BT81 | CQ81: =CP81/T81 | CR81: =100/CP81 | CS81: =100/CQ81 | CV81: =BL81/T81 | CW81: =100/CV81 | CY81: 东城区劳旅总工头“浩”曾经的配枪， 在“浩”站稳脚跟之前，是他唯一能够信任的伙伴。 如今的“浩”早已不再需要这把枪， 但他仍将其放在办公室里来提醒自己， 他能坐在现在这个位置，付出过多少代价。 | DA81: =TEXTJOIN("、", TRUE, FILTER('武器技能'!B:B, '武器技能'!E:E = H81)) | DC81: 待办 | DD81: 待办
A82: Knock Knock | B82: 开门红 | D82: =IF($A82="","","WPN"&VLOOKUP(E82,'引用数据库'!Z:AC,4,FALSE)&VLOOKUP(H82,'引用数据库'!N:P,3,FALSE)&VLOOKUP(I82,'引用数据库'!S:U,3,FALSE)&TEXT(F82,"00")) | E82: 劳旅 | F82: 1 | G82: =G81 | H82: =H81 | I82: =I81 | J82: =J81 | K82: =K81 | M82: =M81 | N82: 800 | O82: N/A | P82: 0 | Q82: 0 | R82: 0.3 | S82: 0 | T82: =SUM(P82:S82) | U82: =2*T82/(15*(1+(5-BD82)*0.1)) | W82: 60 | X82: 90 | Y82: 0.25 | Z82: 0.25 | AB82: 10 | AC82: 1 | AD82: =(W82+AB82)*AC82 | AE82: =(X82+AB82)*AC82 | AM82: =IFS(AJ82 > 1.25, "S", AJ82 > 1, "A", AJ82 > 0.75, "B", AJ82 > 0.5, "C", AJ82 > 0.25, "D", AJ82 > 0, "E", TRUE, "-") | AN82: =IFS(AK82 > 1.25, "S", AK82 > 1, "A", AK82 > 0.75, "B", AK82 > 0.5, "C", AK82 > 0.25, "D", AK82 > 0, "E", TRUE, "-") | AO82: =IFS(AL82 > 1.25, "S", AL82 > 1, "A", AL82 > 0.75, "B", AL82 > 0.5, "C", AL82 > 0.25, "D", AL82 > 0, "E", TRUE, "-") | AV82: =IF(SUM(AJ82:AL82)=0, 0, (1 + F82 * 0.1) * (0.75 + 0.25 * MAX(0, MIN(1, IF(MAX(AJ82:AL82)=0, 0, (3*MAX(AJ82:AL82)-SUM(AJ82:AL82)) / (2*MAX(AJ82:AL82))))))) | AW82: =MAX(AJ82:AL82) | AX82: =IF(AW82=0, "", AW82 / ((1 + 0.1*N(F82)))) | AY82: =IF(SUM(AJ82:AL82)=0, 0, (1 + F82 * 0.1) * (1 + ((SUM(AJ82:AL82) - MAX(AJ82:AL82)) / (2 * MAX(AJ82:AL82))) * (1/0.75 - 1))) | BA82: =IF(AZ82=0, "", AZ82 / ((1 + 0.1*N(F82))/0.75)) | BB82: 0.1 | BD82: =BD81 | BE82: =BE81 | BH82: 20 | BL82: 20 | BN82: 32 | BO82: 1.5 | BQ82: 2 | BR82: =IFERROR(BQ82*100/CP82,"N/A") | BS82: 16 | BT82: 9 | BV82: =IFERROR( ROUND( (10 / $T$4) * ((CP82 / T82) / ($CP$4 / $T$4)) ^ 0.9 * (T82 / $T$4) ^ 0.2 * ((1 + N82) / (1 + $N$4)) ^ 0.15 * ((1 + BQ82) / (1 + $BQ$4)) ^ 0.15 * ((1 + BD82) / (1 + $BD$4)) ^ 0.2 * ((1 + BH82) / (1 + $BH$4)) ^ 0.2 * ((1 + BL82) / (1 + $BL$4)) ^ 0.2 * T82, 0), CP82 * 1000) | BW82: =#REF! | CA82: 20 | CB82: =CA82*BB82*(AP82*AJ82+AQ82*AK82+AR82*AL82) | CC82: =CA82+CB82 | CJ82: 2.5 | CK82: =CJ82/BS82 | CN82: =CK82*CC82 | CP82: =CN82*BS82*BT82 | CQ82: =CP82/T82 | CR82: =100/CP82 | CS82: =100/CQ82 | CV82: =BL82/T82 | CW82: =100/CV82 | DC82: 待办 | DD82: 待办
A83: Knock Knock | B83: 开门红 | D83: =IF($A83="","","WPN"&VLOOKUP(E83,'引用数据库'!Z:AC,4,FALSE)&VLOOKUP(H83,'引用数据库'!N:P,3,FALSE)&VLOOKUP(I83,'引用数据库'!S:U,3,FALSE)&TEXT(F83,"00")) | E83: 劳旅 | F83: 2 | G83: =G82 | H83: =H82 | I83: =I82 | J83: =J82 | K83: =K82 | M83: =M82 | N83: 800 | O83: N/A | P83: 0 | Q83: 0 | R83: 0.3 | S83: 0 | T83: =SUM(P83:S83) | U83: =2*T83/(15*(1+(5-BD83)*0.1)) | W83: 60 | X83: 90 | Y83: 0.25 | Z83: 0.25 | AB83: 10 | AC83: 1 | AD83: =(W83+AB83)*AC83 | AE83: =(X83+AB83)*AC83 | AM83: =IFS(AJ83 > 1.25, "S", AJ83 > 1, "A", AJ83 > 0.75, "B", AJ83 > 0.5, "C", AJ83 > 0.25, "D", AJ83 > 0, "E", TRUE, "-") | AN83: =IFS(AK83 > 1.25, "S", AK83 > 1, "A", AK83 > 0.75, "B", AK83 > 0.5, "C", AK83 > 0.25, "D", AK83 > 0, "E", TRUE, "-") | AO83: =IFS(AL83 > 1.25, "S", AL83 > 1, "A", AL83 > 0.75, "B", AL83 > 0.5, "C", AL83 > 0.25, "D", AL83 > 0, "E", TRUE, "-") | AV83: =IF(SUM(AJ83:AL83)=0, 0, (1 + F83 * 0.1) * (0.75 + 0.25 * MAX(0, MIN(1, IF(MAX(AJ83:AL83)=0, 0, (3*MAX(AJ83:AL83)-SUM(AJ83:AL83)) / (2*MAX(AJ83:AL83))))))) | AW83: =MAX(AJ83:AL83) | AX83: =IF(AW83=0, "", AW83 / ((1 + 0.1*N(F83)))) | AY83: =IF(SUM(AJ83:AL83)=0, 0, (1 + F83 * 0.1) * (1 + ((SUM(AJ83:AL83) - MAX(AJ83:AL83)) / (2 * MAX(AJ83:AL83))) * (1/0.75 - 1))) | BA83: =IF(AZ83=0, "", AZ83 / ((1 + 0.1*N(F83))/0.75)) | BB83: 0.1 | BD83: =BD82 | BE83: =BE82 | BH83: 20 | BL83: 20 | BN83: 32 | BO83: 1.5 | BQ83: 2 | BR83: =IFERROR(BQ83*100/CP83,"N/A") | BS83: 16 | BT83: 9 | BW83: =BW82 | CA83: 30 | CB83: =CA83*BB83*(AP83*AJ83+AQ83*AK83+AR83*AL83) | CC83: =CA83+CB83 | CJ83: 2.5 | CK83: =CJ83/BS83 | CN83: =CK83*CC83 | CP83: =CN83*BS83*BT83 | CQ83: =CP83/T83 | CR83: =100/CP83 | CS83: =100/CQ83 | CV83: =BL83/T83 | CW83: =100/CV83 | DC83: 待办 | DD83: 待办
A84: Knock Knock | B84: 开门红 | D84: =IF($A84="","","WPN"&VLOOKUP(E84,'引用数据库'!Z:AC,4,FALSE)&VLOOKUP(H84,'引用数据库'!N:P,3,FALSE)&VLOOKUP(I84,'引用数据库'!S:U,3,FALSE)&TEXT(F84,"00")) | E84: 劳旅 | F84: 3 | G84: =G83 | H84: =H83 | I84: =I83 | J84: =J83 | K84: =K83 | M84: =M83 | N84: 800 | O84: N/A | P84: 0 | Q84: 0 | R84: 0.3 | S84: 0 | T84: =SUM(P84:S84) | U84: =2*T84/(15*(1+(5-BD84)*0.1)) | W84: 60 | X84: 90 | Y84: 0.25 | Z84: 0.25 | AB84: 10 | AC84: 1 | AD84: =(W84+AB84)*AC84 | AE84: =(X84+AB84)*AC84 | AM84: =IFS(AJ84 > 1.25, "S", AJ84 > 1, "A", AJ84 > 0.75, "B", AJ84 > 0.5, "C", AJ84 > 0.25, "D", AJ84 > 0, "E", TRUE, "-") | AN84: =IFS(AK84 > 1.25, "S", AK84 > 1, "A", AK84 > 0.75, "B", AK84 > 0.5, "C", AK84 > 0.25, "D", AK84 > 0, "E", TRUE, "-") | AO84: =IFS(AL84 > 1.25, "S", AL84 > 1, "A", AL84 > 0.75, "B", AL84 > 0.5, "C", AL84 > 0.25, "D", AL84 > 0, "E", TRUE, "-") | AV84: =IF(SUM(AJ84:AL84)=0, 0, (1 + F84 * 0.1) * (0.75 + 0.25 * MAX(0, MIN(1, IF(MAX(AJ84:AL84)=0, 0, (3*MAX(AJ84:AL84)-SUM(AJ84:AL84)) / (2*MAX(AJ84:AL84))))))) | AW84: =MAX(AJ84:AL84) | AX84: =IF(AW84=0, "", AW84 / ((1 + 0.1*N(F84)))) | AY84: =IF(SUM(AJ84:AL84)=0, 0, (1 + F84 * 0.1) * (1 + ((SUM(AJ84:AL84) - MAX(AJ84:AL84)) / (2 * MAX(AJ84:AL84))) * (1/0.75 - 1))) | BA84: =IF(AZ84=0, "", AZ84 / ((1 + 0.1*N(F84))/0.75)) | BB84: 0.1 | BD84: =BD83 | BE84: =BE83 | BH84: 20 | BL84: 20 | BN84: 32 | BO84: 1.5 | BQ84: 2 | BR84: =IFERROR(BQ84*100/CP84,"N/A") | BS84: 16 | BT84: 9 | BW84: =BW83 | CA84: 40 | CB84: =CA84*BB84*(AP84*AJ84+AQ84*AK84+AR84*AL84) | CC84: =CA84+CB84 | CJ84: 2.5 | CK84: =CJ84/BS84 | CN84: =CK84*CC84 | CP84: =CN84*BS84*BT84 | CQ84: =CP84/T84 | CR84: =100/CP84 | CS84: =100/CQ84 | CV84: =BL84/T84 | CW84: =100/CV84 | DC84: 待办 | DD84: 待办
A85: Knock Knock | B85: 开门红 | D85: =IF($A85="","","WPN"&VLOOKUP(E85,'引用数据库'!Z:AC,4,FALSE)&VLOOKUP(H85,'引用数据库'!N:P,3,FALSE)&VLOOKUP(I85,'引用数据库'!S:U,3,FALSE)&TEXT(F85,"00")) | E85: 劳旅 | F85: 4 | G85: =G84 | H85: =H84 | I85: =I84 | J85: =J84 | K85: =K84 | M85: =M84 | N85: 800 | O85: N/A | P85: 0 | Q85: 0 | R85: 0.3 | S85: 0 | T85: =SUM(P85:S85) | U85: =2*T85/(15*(1+(5-BD85)*0.1)) | W85: 60 | X85: 90 | Y85: 0.25 | Z85: 0.25 | AB85: 10 | AC85: 1 | AD85: =(W85+AB85)*AC85 | AE85: =(X85+AB85)*AC85 | AM85: =IFS(AJ85 > 1.25, "S", AJ85 > 1, "A", AJ85 > 0.75, "B", AJ85 > 0.5, "C", AJ85 > 0.25, "D", AJ85 > 0, "E", TRUE, "-") | AN85: =IFS(AK85 > 1.25, "S", AK85 > 1, "A", AK85 > 0.75, "B", AK85 > 0.5, "C", AK85 > 0.25, "D", AK85 > 0, "E", TRUE, "-") | AO85: =IFS(AL85 > 1.25, "S", AL85 > 1, "A", AL85 > 0.75, "B", AL85 > 0.5, "C", AL85 > 0.25, "D", AL85 > 0, "E", TRUE, "-") | AV85: =IF(SUM(AJ85:AL85)=0, 0, (1 + F85 * 0.1) * (0.75 + 0.25 * MAX(0, MIN(1, IF(MAX(AJ85:AL85)=0, 0, (3*MAX(AJ85:AL85)-SUM(AJ85:AL85)) / (2*MAX(AJ85:AL85))))))) | AW85: =MAX(AJ85:AL85) | AX85: =IF(AW85=0, "", AW85 / ((1 + 0.1*N(F85)))) | AY85: =IF(SUM(AJ85:AL85)=0, 0, (1 + F85 * 0.1) * (1 + ((SUM(AJ85:AL85) - MAX(AJ85:AL85)) / (2 * MAX(AJ85:AL85))) * (1/0.75 - 1))) | BA85: =IF(AZ85=0, "", AZ85 / ((1 + 0.1*N(F85))/0.75)) | BB85: 0.1 | BD85: =BD84 | BE85: =BE84 | BH85: 20 | BL85: 20 | BN85: 32 | BO85: 1.5 | BQ85: 2 | BR85: =IFERROR(BQ85*100/CP85,"N/A") | BS85: 16 | BT85: 9 | BW85: =BW84 | CA85: 50 | CB85: =CA85*BB85*(AP85*AJ85+AQ85*AK85+AR85*AL85) | CC85: =CA85+CB85 | CJ85: 2.5 | CK85: =CJ85/BS85 | CN85: =CK85*CC85 | CP85: =CN85*BS85*BT85 | CQ85: =CP85/T85 | CR85: =100/CP85 | CS85: =100/CQ85 | CV85: =BL85/T85 | CW85: =100/CV85 | DC85: 待办 | DD85: 待办
A86: Knock Knock | B86: 开门红 | D86: =IF($A86="","","WPN"&VLOOKUP(E86,'引用数据库'!Z:AC,4,FALSE)&VLOOKUP(H86,'引用数据库'!N:P,3,FALSE)&VLOOKUP(I86,'引用数据库'!S:U,3,FALSE)&TEXT(F86,"00")) | E86: 劳旅 | F86: 5 | G86: =G85 | H86: =H85 | I86: =I85 | J86: =J85 | K86: =K85 | M86: =M85 | N86: 800 | O86: N/A | P86: 0 | Q86: 0 | R86: 0.3 | S86: 0 | T86: =SUM(P86:S86) | U86: =2*T86/(15*(1+(5-BD86)*0.1)) | W86: 60 | X86: 90 | Y86: 0.25 | Z86: 0.25 | AB86: 10 | AC86: 1 | AD86: =(W86+AB86)*AC86 | AE86: =(X86+AB86)*AC86 | AM86: =IFS(AJ86 > 1.25, "S", AJ86 > 1, "A", AJ86 > 0.75, "B", AJ86 > 0.5, "C", AJ86 > 0.25, "D", AJ86 > 0, "E", TRUE, "-") | AN86: =IFS(AK86 > 1.25, "S", AK86 > 1, "A", AK86 > 0.75, "B", AK86 > 0.5, "C", AK86 > 0.25, "D", AK86 > 0, "E", TRUE, "-") | AO86: =IFS(AL86 > 1.25, "S", AL86 > 1, "A", AL86 > 0.75, "B", AL86 > 0.5, "C", AL86 > 0.25, "D", AL86 > 0, "E", TRUE, "-") | AV86: =IF(SUM(AJ86:AL86)=0, 0, (1 + F86 * 0.1) * (0.75 + 0.25 * MAX(0, MIN(1, IF(MAX(AJ86:AL86)=0, 0, (3*MAX(AJ86:AL86)-SUM(AJ86:AL86)) / (2*MAX(AJ86:AL86))))))) | AW86: =MAX(AJ86:AL86) | AX86: =IF(AW86=0, "", AW86 / ((1 + 0.1*N(F86)))) | AY86: =IF(SUM(AJ86:AL86)=0, 0, (1 + F86 * 0.1) * (1 + ((SUM(AJ86:AL86) - MAX(AJ86:AL86)) / (2 * MAX(AJ86:AL86))) * (1/0.75 - 1))) | BA86: =IF(AZ86=0, "", AZ86 / ((1 + 0.1*N(F86))/0.75)) | BB86: 0.1 | BD86: =BD85 | BE86: =BE85 | BH86: 20 | BL86: 20 | BN86: 32 | BO86: 1.5 | BQ86: 2 | BR86: =IFERROR(BQ86*100/CP86,"N/A") | BS86: 16 | BT86: 9 | BW86: =BW85 | CA86: 60 | CB86: =CA86*BB86*(AP86*AJ86+AQ86*AK86+AR86*AL86) | CC86: =CA86+CB86 | CJ86: 2.5 | CK86: =CJ86/BS86 | CN86: =CK86*CC86 | CP86: =CN86*BS86*BT86 | CQ86: =CP86/T86 | CR86: =100/CP86 | CS86: =100/CQ86 | CV86: =BL86/T86 | CW86: =100/CV86 | DC86: 待办 | DD86: 待办
A87: Shadowfang | B87: 影牙 | D87: =IF($A87="","","WPN"&VLOOKUP(E87,'引用数据库'!Z:AC,4,FALSE)&VLOOKUP(H87,'引用数据库'!N:P,3,FALSE)&VLOOKUP(I87,'引用数据库'!S:U,3,FALSE)&TEXT(F87,"00")) | E87: 新浦会 | F87: 0 | G87: 近战 | H87: 短刀 | I87: 动能 | J87: 手动 | K87: 2 | M87: 1 | N87: 800 | O87: N/A | P87: 0 | Q87: 0 | R87: 0.3 | S87: 0 | T87: =SUM(P87:S87) | U87: =2*T87/(15*(1+(5-BD87)*0.1)) | W87: 60 | X87: 90 | Y87: 0.25 | Z87: 0.25 | AB87: 10 | AC87: 1 | AD87: =(W87+AB87)*AC87 | AE87: =(X87+AB87)*AC87 | AM87: =IFS(AJ87 > 1.25, "S", AJ87 > 1, "A", AJ87 > 0.75, "B", AJ87 > 0.5, "C", AJ87 > 0.25, "D", AJ87 > 0, "E", TRUE, "-") | AN87: =IFS(AK87 > 1.25, "S", AK87 > 1, "A", AK87 > 0.75, "B", AK87 > 0.5, "C", AK87 > 0.25, "D", AK87 > 0, "E", TRUE, "-") | AO87: =IFS(AL87 > 1.25, "S", AL87 > 1, "A", AL87 > 0.75, "B", AL87 > 0.5, "C", AL87 > 0.25, "D", AL87 > 0, "E", TRUE, "-") | AV87: =IF(SUM(AJ87:AL87)=0, 0, (1 + F87 * 0.1) * (0.75 + 0.25 * MAX(0, MIN(1, IF(MAX(AJ87:AL87)=0, 0, (3*MAX(AJ87:AL87)-SUM(AJ87:AL87)) / (2*MAX(AJ87:AL87))))))) | AW87: =MAX(AJ87:AL87) | AX87: =IF(AW87=0, "", AW87 / ((1 + 0.1*N(F87)))) | AY87: =IF(SUM(AJ87:AL87)=0, 0, (1 + F87 * 0.1) * (1 + ((SUM(AJ87:AL87) - MAX(AJ87:AL87)) / (2 * MAX(AJ87:AL87))) * (1/0.75 - 1))) | BA87: =IF(AZ87=0, "", AZ87 / ((1 + 0.1*N(F87))/0.75)) | BB87: 0.1 | BD87: 3 | BE87: 2 | BG87: =T87*20/BT87/BS87 | BH87: 20 | BL87: 20 | BN87: 32 | BO87: 1.5 | BQ87: 2 | BR87: =IFERROR(BQ87*100/CP87,"N/A") | BS87: 16 | BT87: 9 | BW87: =BW88 | CA87: 10 | CB87: =CA87*BB87*(AP87*AJ87+AQ87*AK87+AR87*AL87) | CC87: =CA87+CB87 | CJ87: 2.5 | CK87: =CJ87/BS87 | CN87: =CK87*CC87 | CP87: =CN87*BS87*BT87 | CQ87: =CP87/T87 | CR87: =100/CP87 | CS87: =100/CQ87 | CV87: =BL87/T87 | CW87: =100/CV87 | CY87: 历任新浦会会长贴身保镖“影”的佩刀， 刀身通体漆黑，令人难以察觉它的锋利。 “影”是新浦会中一个较为特殊的存在， 与一直担任会长的李家一样，一直由王家出任。 | DA87: =TEXTJOIN("、", TRUE, FILTER('武器技能'!B:B, '武器技能'!E:E = H87)) | DC87: 待办 | DD87: 待办
A88: Shadowfang | B88: 影牙 | D88: =IF($A88="","","WPN"&VLOOKUP(E88,'引用数据库'!Z:AC,4,FALSE)&VLOOKUP(H88,'引用数据库'!N:P,3,FALSE)&VLOOKUP(I88,'引用数据库'!S:U,3,FALSE)&TEXT(F88,"00")) | E88: 新浦会 | F88: 1 | G88: =G87 | H88: =H87 | I88: =I87 | J88: =J87 | K88: =K87 | M88: =M87 | N88: 800 | O88: N/A | P88: 0 | Q88: 0 | R88: 0.3 | S88: 0 | T88: =SUM(P88:S88) | U88: =2*T88/(15*(1+(5-BD88)*0.1)) | W88: 60 | X88: 90 | Y88: 0.25 | Z88: 0.25 | AB88: 10 | AC88: 1 | AD88: =(W88+AB88)*AC88 | AE88: =(X88+AB88)*AC88 | AM88: =IFS(AJ88 > 1.25, "S", AJ88 > 1, "A", AJ88 > 0.75, "B", AJ88 > 0.5, "C", AJ88 > 0.25, "D", AJ88 > 0, "E", TRUE, "-") | AN88: =IFS(AK88 > 1.25, "S", AK88 > 1, "A", AK88 > 0.75, "B", AK88 > 0.5, "C", AK88 > 0.25, "D", AK88 > 0, "E", TRUE, "-") | AO88: =IFS(AL88 > 1.25, "S", AL88 > 1, "A", AL88 > 0.75, "B", AL88 > 0.5, "C", AL88 > 0.25, "D", AL88 > 0, "E", TRUE, "-") | AV88: =IF(SUM(AJ88:AL88)=0, 0, (1 + F88 * 0.1) * (0.75 + 0.25 * MAX(0, MIN(1, IF(MAX(AJ88:AL88)=0, 0, (3*MAX(AJ88:AL88)-SUM(AJ88:AL88)) / (2*MAX(AJ88:AL88))))))) | AW88: =MAX(AJ88:AL88) | AX88: =IF(AW88=0, "", AW88 / ((1 + 0.1*N(F88)))) | AY88: =IF(SUM(AJ88:AL88)=0, 0, (1 + F88 * 0.1) * (1 + ((SUM(AJ88:AL88) - MAX(AJ88:AL88)) / (2 * MAX(AJ88:AL88))) * (1/0.75 - 1))) | BA88: =IF(AZ88=0, "", AZ88 / ((1 + 0.1*N(F88))/0.75)) | BB88: 0.1 | BD88: =BD87 | BE88: =BE87 | BH88: 20 | BL88: 20 | BN88: 32 | BO88: 1.5 | BQ88: 2 | BR88: =IFERROR(BQ88*100/CP88,"N/A") | BS88: 16 | BT88: 9 | BV88: =IFERROR( ROUND( (10 / $T$4) * ((CP88 / T88) / ($CP$4 / $T$4)) ^ 0.9 * (T88 / $T$4) ^ 0.2 * ((1 + N88) / (1 + $N$4)) ^ 0.15 * ((1 + BQ88) / (1 + $BQ$4)) ^ 0.15 * ((1 + BD88) / (1 + $BD$4)) ^ 0.2 * ((1 + BH88) / (1 + $BH$4)) ^ 0.2 * ((1 + BL88) / (1 + $BL$4)) ^ 0.2 * T88, 0), CP88 * 1000) | BW88: =#REF! | CA88: 20 | CB88: =CA88*BB88*(AP88*AJ88+AQ88*AK88+AR88*AL88) | CC88: =CA88+CB88 | CJ88: 2.5 | CK88: =CJ88/BS88 | CN88: =CK88*CC88 | CP88: =CN88*BS88*BT88 | CQ88: =CP88/T88 | CR88: =100/CP88 | CS88: =100/CQ88 | CV88: =BL88/T88 | CW88: =100/CV88 | DC88: 待办 | DD88: 待办
A89: Shadowfang | B89: 影牙 | D89: =IF($A89="","","WPN"&VLOOKUP(E89,'引用数据库'!Z:AC,4,FALSE)&VLOOKUP(H89,'引用数据库'!N:P,3,FALSE)&VLOOKUP(I89,'引用数据库'!S:U,3,FALSE)&TEXT(F89,"00")) | E89: 新浦会 | F89: 2 | G89: =G88 | H89: =H88 | I89: =I88 | J89: =J88 | K89: =K88 | M89: =M88 | N89: 800 | O89: N/A | P89: 0 | Q89: 0 | R89: 0.3 | S89: 0 | T89: =SUM(P89:S89) | U89: =2*T89/(15*(1+(5-BD89)*0.1)) | W89: 60 | X89: 90 | Y89: 0.25 | Z89: 0.25 | AB89: 10 | AC89: 1 | AD89: =(W89+AB89)*AC89 | AE89: =(X89+AB89)*AC89 | AM89: =IFS(AJ89 > 1.25, "S", AJ89 > 1, "A", AJ89 > 0.75, "B", AJ89 > 0.5, "C", AJ89 > 0.25, "D", AJ89 > 0, "E", TRUE, "-") | AN89: =IFS(AK89 > 1.25, "S", AK89 > 1, "A", AK89 > 0.75, "B", AK89 > 0.5, "C", AK89 > 0.25, "D", AK89 > 0, "E", TRUE, "-") | AO89: =IFS(AL89 > 1.25, "S", AL89 > 1, "A", AL89 > 0.75, "B", AL89 > 0.5, "C", AL89 > 0.25, "D", AL89 > 0, "E", TRUE, "-") | AV89: =IF(SUM(AJ89:AL89)=0, 0, (1 + F89 * 0.1) * (0.75 + 0.25 * MAX(0, MIN(1, IF(MAX(AJ89:AL89)=0, 0, (3*MAX(AJ89:AL89)-SUM(AJ89:AL89)) / (2*MAX(AJ89:AL89))))))) | AW89: =MAX(AJ89:AL89) | AX89: =IF(AW89=0, "", AW89 / ((1 + 0.1*N(F89)))) | AY89: =IF(SUM(AJ89:AL89)=0, 0, (1 + F89 * 0.1) * (1 + ((SUM(AJ89:AL89) - MAX(AJ89:AL89)) / (2 * MAX(AJ89:AL89))) * (1/0.75 - 1))) | BA89: =IF(AZ89=0, "", AZ89 / ((1 + 0.1*N(F89))/0.75)) | BB89: 0.1 | BD89: =BD88 | BE89: =BE88 | BH89: 20 | BL89: 20 | BN89: 32 | BO89: 1.5 | BQ89: 2 | BR89: =IFERROR(BQ89*100/CP89,"N/A") | BS89: 16 | BT89: 9 | BW89: =BW88 | CA89: 30 | CB89: =CA89*BB89*(AP89*AJ89+AQ89*AK89+AR89*AL89) | CC89: =CA89+CB89 | CJ89: 2.5 | CK89: =CJ89/BS89 | CN89: =CK89*CC89 | CP89: =CN89*BS89*BT89 | CQ89: =CP89/T89 | CR89: =100/CP89 | CS89: =100/CQ89 | CV89: =BL89/T89 | CW89: =100/CV89 | DC89: 待办 | DD89: 待办
A90: Shadowfang | B90: 影牙 | D90: =IF($A90="","","WPN"&VLOOKUP(E90,'引用数据库'!Z:AC,4,FALSE)&VLOOKUP(H90,'引用数据库'!N:P,3,FALSE)&VLOOKUP(I90,'引用数据库'!S:U,3,FALSE)&TEXT(F90,"00")) | E90: 新浦会 | F90: 3 | G90: =G89 | H90: =H89 | I90: =I89 | J90: =J89 | K90: =K89 | M90: =M89 | N90: 800 | O90: N/A | P90: 0 | Q90: 0 | R90: 0.3 | S90: 0 | T90: =SUM(P90:S90) | U90: =2*T90/(15*(1+(5-BD90)*0.1)) | W90: 60 | X90: 90 | Y90: 0.25 | Z90: 0.25 | AB90: 10 | AC90: 1 | AD90: =(W90+AB90)*AC90 | AE90: =(X90+AB90)*AC90 | AM90: =IFS(AJ90 > 1.25, "S", AJ90 > 1, "A", AJ90 > 0.75, "B", AJ90 > 0.5, "C", AJ90 > 0.25, "D", AJ90 > 0, "E", TRUE, "-") | AN90: =IFS(AK90 > 1.25, "S", AK90 > 1, "A", AK90 > 0.75, "B", AK90 > 0.5, "C", AK90 > 0.25, "D", AK90 > 0, "E", TRUE, "-") | AO90: =IFS(AL90 > 1.25, "S", AL90 > 1, "A", AL90 > 0.75, "B", AL90 > 0.5, "C", AL90 > 0.25, "D", AL90 > 0, "E", TRUE, "-") | AV90: =IF(SUM(AJ90:AL90)=0, 0, (1 + F90 * 0.1) * (0.75 + 0.25 * MAX(0, MIN(1, IF(MAX(AJ90:AL90)=0, 0, (3*MAX(AJ90:AL90)-SUM(AJ90:AL90)) / (2*MAX(AJ90:AL90))))))) | AW90: =MAX(AJ90:AL90) | AX90: =IF(AW90=0, "", AW90 / ((1 + 0.1*N(F90)))) | AY90: =IF(SUM(AJ90:AL90)=0, 0, (1 + F90 * 0.1) * (1 + ((SUM(AJ90:AL90) - MAX(AJ90:AL90)) / (2 * MAX(AJ90:AL90))) * (1/0.75 - 1))) | BA90: =IF(AZ90=0, "", AZ90 / ((1 + 0.1*N(F90))/0.75)) | BB90: 0.1 | BD90: =BD89 | BE90: =BE89 | BH90: 20 | BL90: 20 | BN90: 32 | BO90: 1.5 | BQ90: 2 | BR90: =IFERROR(BQ90*100/CP90,"N/A") | BS90: 16 | BT90: 9 | BW90: =BW89 | CA90: 40 | CB90: =CA90*BB90*(AP90*AJ90+AQ90*AK90+AR90*AL90) | CC90: =CA90+CB90 | CJ90: 2.5 | CK90: =CJ90/BS90 | CN90: =CK90*CC90 | CP90: =CN90*BS90*BT90 | CQ90: =CP90/T90 | CR90: =100/CP90 | CS90: =100/CQ90 | CV90: =BL90/T90 | CW90: =100/CV90 | DC90: 待办 | DD90: 待办
A91: Shadowfang | B91: 影牙 | D91: =IF($A91="","","WPN"&VLOOKUP(E91,'引用数据库'!Z:AC,4,FALSE)&VLOOKUP(H91,'引用数据库'!N:P,3,FALSE)&VLOOKUP(I91,'引用数据库'!S:U,3,FALSE)&TEXT(F91,"00")) | E91: 新浦会 | F91: 4 | G91: =G90 | H91: =H90 | I91: =I90 | J91: =J90 | K91: =K90 | M91: =M90 | N91: 800 | O91: N/A | P91: 0 | Q91: 0 | R91: 0.3 | S91: 0 | T91: =SUM(P91:S91) | U91: =2*T91/(15*(1+(5-BD91)*0.1)) | W91: 60 | X91: 90 | Y91: 0.25 | Z91: 0.25 | AB91: 10 | AC91: 1 | AD91: =(W91+AB91)*AC91 | AE91: =(X91+AB91)*AC91 | AM91: =IFS(AJ91 > 1.25, "S", AJ91 > 1, "A", AJ91 > 0.75, "B", AJ91 > 0.5, "C", AJ91 > 0.25, "D", AJ91 > 0, "E", TRUE, "-") | AN91: =IFS(AK91 > 1.25, "S", AK91 > 1, "A", AK91 > 0.75, "B", AK91 > 0.5, "C", AK91 > 0.25, "D", AK91 > 0, "E", TRUE, "-") | AO91: =IFS(AL91 > 1.25, "S", AL91 > 1, "A", AL91 > 0.75, "B", AL91 > 0.5, "C", AL91 > 0.25, "D", AL91 > 0, "E", TRUE, "-") | AV91: =IF(SUM(AJ91:AL91)=0, 0, (1 + F91 * 0.1) * (0.75 + 0.25 * MAX(0, MIN(1, IF(MAX(AJ91:AL91)=0, 0, (3*MAX(AJ91:AL91)-SUM(AJ91:AL91)) / (2*MAX(AJ91:AL91))))))) | AW91: =MAX(AJ91:AL91) | AX91: =IF(AW91=0, "", AW91 / ((1 + 0.1*N(F91)))) | AY91: =IF(SUM(AJ91:AL91)=0, 0, (1 + F91 * 0.1) * (1 + ((SUM(AJ91:AL91) - MAX(AJ91:AL91)) / (2 * MAX(AJ91:AL91))) * (1/0.75 - 1))) | BA91: =IF(AZ91=0, "", AZ91 / ((1 + 0.1*N(F91))/0.75)) | BB91: 0.1 | BD91: =BD90 | BE91: =BE90 | BH91: 20 | BL91: 20 | BN91: 32 | BO91: 1.5 | BQ91: 2 | BR91: =IFERROR(BQ91*100/CP91,"N/A") | BS91: 16 | BT91: 9 | BW91: =BW90 | CA91: 50 | CB91: =CA91*BB91*(AP91*AJ91+AQ91*AK91+AR91*AL91) | CC91: =CA91+CB91 | CJ91: 2.5 | CK91: =CJ91/BS91 | CN91: =CK91*CC91 | CP91: =CN91*BS91*BT91 | CQ91: =CP91/T91 | CR91: =100/CP91 | CS91: =100/CQ91 | CV91: =BL91/T91 | CW91: =100/CV91 | DC91: 待办 | DD91: 待办
A92: Shadowfang | B92: 影牙 | D92: =IF($A92="","","WPN"&VLOOKUP(E92,'引用数据库'!Z:AC,4,FALSE)&VLOOKUP(H92,'引用数据库'!N:P,3,FALSE)&VLOOKUP(I92,'引用数据库'!S:U,3,FALSE)&TEXT(F92,"00")) | E92: 新浦会 | F92: 5 | G92: =G91 | H92: =H91 | I92: =I91 | J92: =J91 | K92: =K91 | M92: =M91 | N92: 800 | O92: N/A | P92: 0 | Q92: 0 | R92: 0.3 | S92: 0 | T92: =SUM(P92:S92) | U92: =2*T92/(15*(1+(5-BD92)*0.1)) | W92: 60 | X92: 90 | Y92: 0.25 | Z92: 0.25 | AB92: 10 | AC92: 1 | AD92: =(W92+AB92)*AC92 | AE92: =(X92+AB92)*AC92 | AM92: =IFS(AJ92 > 1.25, "S", AJ92 > 1, "A", AJ92 > 0.75, "B", AJ92 > 0.5, "C", AJ92 > 0.25, "D", AJ92 > 0, "E", TRUE, "-") | AN92: =IFS(AK92 > 1.25, "S", AK92 > 1, "A", AK92 > 0.75, "B", AK92 > 0.5, "C", AK92 > 0.25, "D", AK92 > 0, "E", TRUE, "-") | AO92: =IFS(AL92 > 1.25, "S", AL92 > 1, "A", AL92 > 0.75, "B", AL92 > 0.5, "C", AL92 > 0.25, "D", AL92 > 0, "E", TRUE, "-") | AV92: =IF(SUM(AJ92:AL92)=0, 0, (1 + F92 * 0.1) * (0.75 + 0.25 * MAX(0, MIN(1, IF(MAX(AJ92:AL92)=0, 0, (3*MAX(AJ92:AL92)-SUM(AJ92:AL92)) / (2*MAX(AJ92:AL92))))))) | AW92: =MAX(AJ92:AL92) | AX92: =IF(AW92=0, "", AW92 / ((1 + 0.1*N(F92)))) | AY92: =IF(SUM(AJ92:AL92)=0, 0, (1 + F92 * 0.1) * (1 + ((SUM(AJ92:AL92) - MAX(AJ92:AL92)) / (2 * MAX(AJ92:AL92))) * (1/0.75 - 1))) | BA92: =IF(AZ92=0, "", AZ92 / ((1 + 0.1*N(F92))/0.75)) | BB92: 0.1 | BD92: =BD91 | BE92: =BE91 | BH92: 20 | BL92: 20 | BN92: 32 | BO92: 1.5 | BQ92: 2 | BR92: =IFERROR(BQ92*100/CP92,"N/A") | BS92: 16 | BT92: 9 | BW92: =BW91 | CA92: 60 | CB92: =CA92*BB92*(AP92*AJ92+AQ92*AK92+AR92*AL92) | CC92: =CA92+CB92 | CJ92: 2.5 | CK92: =CJ92/BS92 | CN92: =CK92*CC92 | CP92: =CN92*BS92*BT92 | CQ92: =CP92/T92 | CR92: =100/CP92 | CS92: =100/CQ92 | CV92: =BL92/T92 | CW92: =100/CV92 | DC92: 待办 | DD92: 待办
A93: Regulated Rage | B93: 工人之怒 | D93: =IF($A93="","","WPN"&VLOOKUP(E93,'引用数据库'!Z:AC,4,FALSE)&VLOOKUP(H93,'引用数据库'!N:P,3,FALSE)&VLOOKUP(I93,'引用数据库'!S:U,3,FALSE)&TEXT(F93,"00")) | E93: 劳旅 | F93: 0 | G93: 近战 | H93: 长刀 | I93: 热能 | J93: 手动 | K93: =K92 | U93: =2*T93/(15*(1+(5-BD93)*0.1)) | AM93: =IFS(AJ93 > 1.25, "S", AJ93 > 1, "A", AJ93 > 0.75, "B", AJ93 > 0.5, "C", AJ93 > 0.25, "D", AJ93 > 0, "E", TRUE, "-") | AN93: =IFS(AK93 > 1.25, "S", AK93 > 1, "A", AK93 > 0.75, "B", AK93 > 0.5, "C", AK93 > 0.25, "D", AK93 > 0, "E", TRUE, "-") | AO93: =IFS(AL93 > 1.25, "S", AL93 > 1, "A", AL93 > 0.75, "B", AL93 > 0.5, "C", AL93 > 0.25, "D", AL93 > 0, "E", TRUE, "-") | AV93: =IF(SUM(AJ93:AL93)=0, 0, (1 + F93 * 0.1) * (0.75 + 0.25 * MAX(0, MIN(1, IF(MAX(AJ93:AL93)=0, 0, (3*MAX(AJ93:AL93)-SUM(AJ93:AL93)) / (2*MAX(AJ93:AL93))))))) | AW93: =MAX(AJ93:AL93) | AX93: =IF(AW93=0, "", AW93 / ((1 + 0.1*N(F93)))) | AY93: =IF(SUM(AJ93:AL93)=0, 0, (1 + F93 * 0.1) * (1 + ((SUM(AJ93:AL93) - MAX(AJ93:AL93)) / (2 * MAX(AJ93:AL93))) * (1/0.75 - 1))) | BA93: =IF(AZ93=0, "", AZ93 / ((1 + 0.1*N(F93))/0.75)) | BB93: 0.1 | BG93: =T93*20/BT93/BS93 | BR93: =IFERROR(BQ93*100/CP93,"N/A") | CP93: =CN93*BS93*BT93 | CR93: =100/CP93 | CS93: =100/CQ93 | CV93: =BL93/T93 | CW93: =100/CV93 | CY93: 用工地随手可得的素材拼接出来的武器， 诡异的外形仿佛在诉说着其主人打造它时的怒火。 曾有一名压榨劳工的工头惨死于工人刀下。 原始凶器虽早已被销毁， 但这把武器的设计图却始终在工人之间暗中流传。 | DA93: =TEXTJOIN("、", TRUE, FILTER('武器技能'!B:B, '武器技能'!E:E = H93)) | DC93: 待办 | DD93: 待办
A94: Regulated Rage | B94: 工人之怒 | D94: =IF($A94="","","WPN"&VLOOKUP(E94,'引用数据库'!Z:AC,4,FALSE)&VLOOKUP(H94,'引用数据库'!N:P,3,FALSE)&VLOOKUP(I94,'引用数据库'!S:U,3,FALSE)&TEXT(F94,"00")) | E94: 劳旅 | F94: 1 | G94: =G93 | H94: =H93 | I94: =I93 | J94: =J93 | K94: =K93 | U94: =2*T94/(15*(1+(5-BD94)*0.1)) | AM94: =IFS(AJ94 > 1.25, "S", AJ94 > 1, "A", AJ94 > 0.75, "B", AJ94 > 0.5, "C", AJ94 > 0.25, "D", AJ94 > 0, "E", TRUE, "-") | AN94: =IFS(AK94 > 1.25, "S", AK94 > 1, "A", AK94 > 0.75, "B", AK94 > 0.5, "C", AK94 > 0.25, "D", AK94 > 0, "E", TRUE, "-") | AO94: =IFS(AL94 > 1.25, "S", AL94 > 1, "A", AL94 > 0.75, "B", AL94 > 0.5, "C", AL94 > 0.25, "D", AL94 > 0, "E", TRUE, "-") | AV94: =IF(SUM(AJ94:AL94)=0, 0, (1 + F94 * 0.1) * (0.75 + 0.25 * MAX(0, MIN(1, IF(MAX(AJ94:AL94)=0, 0, (3*MAX(AJ94:AL94)-SUM(AJ94:AL94)) / (2*MAX(AJ94:AL94))))))) | AW94: =MAX(AJ94:AL94) | AX94: =IF(AW94=0, "", AW94 / ((1 + 0.1*N(F94)))) | AY94: =IF(SUM(AJ94:AL94)=0, 0, (1 + F94 * 0.1) * (1 + ((SUM(AJ94:AL94) - MAX(AJ94:AL94)) / (2 * MAX(AJ94:AL94))) * (1/0.75 - 1))) | BA94: =IF(AZ94=0, "", AZ94 / ((1 + 0.1*N(F94))/0.75)) | BB94: 0.1 | BR94: =IFERROR(BQ94*100/CP94,"N/A") | CP94: =CN94*BS94*BT94 | CR94: =100/CP94 | CS94: =100/CQ94 | CV94: =BL94/T94 | CW94: =100/CV94 | DC94: 待办 | DD94: 待办
A95: Regulated Rage | B95: 工人之怒 | D95: =IF($A95="","","WPN"&VLOOKUP(E95,'引用数据库'!Z:AC,4,FALSE)&VLOOKUP(H95,'引用数据库'!N:P,3,FALSE)&VLOOKUP(I95,'引用数据库'!S:U,3,FALSE)&TEXT(F95,"00")) | E95: 劳旅 | F95: 2 | G95: =G94 | H95: =H94 | I95: =I94 | J95: =J94 | K95: =K94 | U95: =2*T95/(15*(1+(5-BD95)*0.1)) | AM95: =IFS(AJ95 > 1.25, "S", AJ95 > 1, "A", AJ95 > 0.75, "B", AJ95 > 0.5, "C", AJ95 > 0.25, "D", AJ95 > 0, "E", TRUE, "-") | AN95: =IFS(AK95 > 1.25, "S", AK95 > 1, "A", AK95 > 0.75, "B", AK95 > 0.5, "C", AK95 > 0.25, "D", AK95 > 0, "E", TRUE, "-") | AO95: =IFS(AL95 > 1.25, "S", AL95 > 1, "A", AL95 > 0.75, "B", AL95 > 0.5, "C", AL95 > 0.25, "D", AL95 > 0, "E", TRUE, "-") | AV95: =IF(SUM(AJ95:AL95)=0, 0, (1 + F95 * 0.1) * (0.75 + 0.25 * MAX(0, MIN(1, IF(MAX(AJ95:AL95)=0, 0, (3*MAX(AJ95:AL95)-SUM(AJ95:AL95)) / (2*MAX(AJ95:AL95))))))) | AW95: =MAX(AJ95:AL95) | AX95: =IF(AW95=0, "", AW95 / ((1 + 0.1*N(F95)))) | AY95: =IF(SUM(AJ95:AL95)=0, 0, (1 + F95 * 0.1) * (1 + ((SUM(AJ95:AL95) - MAX(AJ95:AL95)) / (2 * MAX(AJ95:AL95))) * (1/0.75 - 1))) | BA95: =IF(AZ95=0, "", AZ95 / ((1 + 0.1*N(F95))/0.75)) | BB95: 0.1 | BR95: =IFERROR(BQ95*100/CP95,"N/A") | CP95: =CN95*BS95*BT95 | CR95: =100/CP95 | CS95: =100/CQ95 | CV95: =BL95/T95 | CW95: =100/CV95 | DC95: 待办 | DD95: 待办
A96: Regulated Rage | B96: 工人之怒 | D96: =IF($A96="","","WPN"&VLOOKUP(E96,'引用数据库'!Z:AC,4,FALSE)&VLOOKUP(H96,'引用数据库'!N:P,3,FALSE)&VLOOKUP(I96,'引用数据库'!S:U,3,FALSE)&TEXT(F96,"00")) | E96: 劳旅 | F96: 3 | G96: =G95 | H96: =H95 | I96: =I95 | J96: =J95 | K96: =K95 | U96: =2*T96/(15*(1+(5-BD96)*0.1)) | AM96: =IFS(AJ96 > 1.25, "S", AJ96 > 1, "A", AJ96 > 0.75, "B", AJ96 > 0.5, "C", AJ96 > 0.25, "D", AJ96 > 0, "E", TRUE, "-") | AN96: =IFS(AK96 > 1.25, "S", AK96 > 1, "A", AK96 > 0.75, "B", AK96 > 0.5, "C", AK96 > 0.25, "D", AK96 > 0, "E", TRUE, "-") | AO96: =IFS(AL96 > 1.25, "S", AL96 > 1, "A", AL96 > 0.75, "B", AL96 > 0.5, "C", AL96 > 0.25, "D", AL96 > 0, "E", TRUE, "-") | AV96: =IF(SUM(AJ96:AL96)=0, 0, (1 + F96 * 0.1) * (0.75 + 0.25 * MAX(0, MIN(1, IF(MAX(AJ96:AL96)=0, 0, (3*MAX(AJ96:AL96)-SUM(AJ96:AL96)) / (2*MAX(AJ96:AL96))))))) | AW96: =MAX(AJ96:AL96) | AX96: =IF(AW96=0, "", AW96 / ((1 + 0.1*N(F96)))) | AY96: =IF(SUM(AJ96:AL96)=0, 0, (1 + F96 * 0.1) * (1 + ((SUM(AJ96:AL96) - MAX(AJ96:AL96)) / (2 * MAX(AJ96:AL96))) * (1/0.75 - 1))) | BA96: =IF(AZ96=0, "", AZ96 / ((1 + 0.1*N(F96))/0.75)) | BB96: 0.1 | BR96: =IFERROR(BQ96*100/CP96,"N/A") | CP96: =CN96*BS96*BT96 | CR96: =100/CP96 | CS96: =100/CQ96 | CV96: =BL96/T96 | CW96: =100/CV96 | DC96: 待办 | DD96: 待办
